Workbook
Name 切片器_订单状态: #N/A

Sheet Sheet1
A3: 行标签 | B3: 计数项:订单编号
A4: DD-20260512-0102 | B4: 2
A5: DD-20260603-0126 | B5: 2
A6: 总计 | B6: 4

Sheet Sheet3
A3: #VALUE!
A59: 行标签 | B59: 求和项:金额(修正后)
A60: A | B60: 979267
A61: 办公耗材 | B61: 247993
A62: 办公设备 | B62: 178827
A63: 电子数码 | B63: 353638
A64: 软件服务 | B64: 198809
A65: B | B65: 1090774
A66: 办公耗材 | B66: 319871
A67: 办公设备 | B67: 117840
A68: 电子数码 | B68: 492909
A69: 软件服务 | B69: 160154
A70: C | B70: 911286
A71: 办公耗材 | B71: 323083
... A75: 总计 | B75: 2981327
A84: 行标签 | B84: 求和项:金额(修正后)
A85: A | B85: 979267
A86: 办公耗材 | B86: 247993
A87: 办公设备 | B87: 178827
A88: 电子数码 | B88: 353638
A89: 软件服务 | B89: 198809
A90: B | B90: 1090774
A91: 办公耗材 | B91: 319871
A92: 办公设备 | B92: 117840
A93: 电子数码 | B93: 492909
A94: 软件服务 | B94: 160154
A95: C | B95: 911286
A96: 办公耗材 | B96: 323083
... A100: 总计 | B100: 2981327

Sheet 统计计算
A3: 行标签 | B3: 计数项:订单编号 | C3: 求和项:金额(修正后)
A4: 待付款 | B4: 24 | C4: 346554
A5: 已发货 | B5: 47 | C5: 641423
A6: 已取消 | B6: 19 | C6: 291512
A7: 已完成 | B7: 112 | C7: 1701838
A8: (空白)
A9: 总计 | B9: 202 | C9: 2981327
A19: 行标签 | B19: 平均值项:金额(修正后)
A20: 陈静 | B20: 17359.364
A21: 李娜 | B21: 12536.56
A22: 刘洋 | B22: 8105.1333
A23: 孙悦 | B23: 15897.773
A24: 王强 | B24: 19083.818
A25: 杨帆 | B25: 11349.273
A26: 张伟 | B26: 17490.2
A27: 赵磊 | B27: 13804.586
A28: 总计 | B28: 14698.443
A36: 求和项:金额(修正后) | B36: 列标签
B37: 1月 | P37: 1月 汇总 | Q37: 2月 | X37: 2月 汇总 | Y37: 3月 | AK37: 3月 汇总 | AL37: 4月 | BB37: 4月 汇总 | BC37: 5月 | BY37: 5月 汇总 | BZ37: 6月 | CQ37: 6月 汇总 | CR37: 7月 | DK37: 7月 汇总 | DL37: 8月 | DZ37: 8月 汇总 | EA37: 总计
A38: 行标签 | B38: 46025 | C38: 46029 | D38: 46031 | E38: 46035 | F38: 46039 | G38: 46042 | H38: 46045 | I38: 46046 | J38: 46047 | K38: 46048 | L38: 46049 | M38: 46051 | N38: 46052 | O38: 46053 | Q38: 46056 | R38: 46059 | S38: 46061 | T38: 46069 | U38: 46074 | V38: 46076 | W38: 46080 | Y38: 46084 | Z38: 46087 | AA38: 46089 | AB38: 46091 | AC38: 46096 | AD38: 46097 | AE38: 46098 | AF38: 46102 | AG38: 46103 | AH38: 46104 | AI38: 46110 | AJ38: 46112 | AL38: 46114 | AM38: 46115 | AN38: 46117 | AO38: 46124 | AP38: 46125 | AQ38: 46130 | AR38: 46131 | AS38: 46132 | AT38: 46133 | AU38: 46134 | AV38: 46135 | AW38: 46138 | AX38: 46139 | AY38: 46140 | AZ38: 46141 | BA38: 46142 | BC38: 46143 | BD38: 46145 | BE38: 46146 | BF38: 46148 | BG38: 46150 | BH38: 46151 | BI38: 46152 | BJ38: 46153 | BK38: 46154 | BL38: 46155 | BM38: 46156 | BN38: 46157 | BO38: 46160 | BP38: 46162 | BQ38: 46163 | BR38: 46164 | BS38: 46165 | BT38: 46166 | BU38: 46167 | BV38: 46169 | BW38: 46170 | BX38: 46173 | BZ38: 46175 | CA38: 46176 | CB38: 46180 | CC38: 46182 | CD38: 46183 | CE38: 46186 | CF38: 46188 | CG38: 46189 | CH38: 46192 | CI38: 46194 | CJ38: 46195 | CK38: 46196 | CL38: 46199 | CM38: 46200 | CN38: 46201 | CO38: 46202 | CP38: 46203 | CR38: 46204 | CS38: 46205 | CT38: 46206 | CU38: 46208 | CV38: 46209 | CW38: 46210 | CX38: 46213 | CY38: 46215 | CZ38: 46219 | DA38: 46220 | DB38: 46221 | DC38: 46223 | DD38: 46227 | DE38: 46228 | DF38: 46229 | DG38: 46230 | DH38: 46231 | DI38: 46232 | DJ38: 46234 | DL38: 46235 | DM38: 46238 | DN38: 46239 | DO38: 46240 | DP38: 46243 | DQ38: 46244 | DR38: 46245 | DS38: 46247 | DT38: 46248 | DU38: 46249 | DV38: 46250 | DW38: 46251 | DX38: 46252 | DY38: 46254
A39: 华北 | D39: 3825 | G39: 1797 | J39: 12320 | K39: 9996 | P39: 27938 | V39: 28495 | X39: 28495 | Z39: 15588 | AA39: 7188 | AC39: 22163 | AH39: 27261 | AK39: 72200 | AP39: 15588 | AS39: 6293 | BB39: 21881 | BE39: 2944 | BF39: 11691 | BG39: 2598 | BH39: 22762 | BL39: 10010 | BQ39: 14592 | BR39: 17097 | BS39: 5196 | BT39: 9240 | BX39: 6495 | BY39: 102625 | CA39: 68381 | CC39: 9625 | CI39: 34087 | CP39: 2691 | CQ39: 114784 | CT39: 48142 | CY39: 7497 | DF39: 53515 | DK39: 109154 | DO39: 2093 | DQ39: 22163 | DS39: 8576 | DU39: 7497 | DZ39: 40329 | EA39: 517406
A40: 华东 | B40: 2691 | F40: 3495 | M40: 13980 | N40: 2691 | P40: 22857 | R40: 4635 | S40: 598 | T40: 62689 | U40: 13980 | X40: 81902 | Z40: 15588 | AA40: 15825 | AB40: 17097 | AD40: 50265 | AE40: 765 | AG40: 17475 | AJ40: 15588 | AK40: 132603 | AM40: 1299 | AN40: 10523 | AP40: 38500 | AR40: 2990 | AV40: 13312 | AW40: 30289 | AX40: 34392 | AY40: 9093 | BB40: 140398 | BF40: 14994 | BI40: 6990 | BJ40: 23067 | BK40: 131077 | BM40: 4365 | BO40: 675 | BP40: 12800 | BQ40: 8388 | BS40: 23960 | BU40: 20271 | BY40: 246587 | CA40: 3599 | CD40: 6528 | CF40: 25410 | CG40: 15378 | CH40: 5196 | CO40: 3596 | CP40: 39893 | CQ40: 99600 | CU40: 2990 | DA40: 18174 | DB40: 12579 | DC40: 68388 | DE40: 2990 | DF40: 8448 | DG40: 14976 | DH40: 23766 | DI40: 17493 | DK40: 169804 | DL40: 897 | DM40: 35035 | DN40: 5592 | DS40: 7497 | DT40: 5248 | DW40: 34392 | DZ40: 88661 | EA40: 982412
A41: 华南 | B41: 899 | P41: 899 | AC41: 5699 | AF41: 1794 | AK41: 7493 | AL41: 1797 | AQ41: 21594 | AR41: 28792 | AT41: 28105 | AU41: 3588 | AY41: 12288 | BA41: 22368 | BB41: 118532 | BC41: 39565 | BD41: 31559 | BF41: 20405 | BK41: 26562 | BS41: 1080 | BV41: 13281 | BY41: 132452 | CB41: 1299 | CC41: 2097 | CF41: 3465 | CJ41: 10797 | CL41: 19168 | CM41: 14396 | CQ41: 51222 | CW41: 5196 | CY41: 3840 | CZ41: 20360 | DD41: 3588 | DJ41: 11883 | DK41: 44867 | DL41: 5592 | DP41: 14396 | DR41: 19992 | DU41: 7699 | DZ41: 47679 | EA41: 403144
A42: 华中 | C42: 5394 | D42: 2560 | E42: 3596 | K42: 3596 | L42: 19190 | O42: 11398 | P42: 45734 | Y42: 46200 | AH42: 899 | AK42: 47099 | AY42: 25193 | BB42: 25193 | BF42: 25794 | BG42: 24465 | BK42: 21495 | BM42: 1797 | BW42: 8704 | BY42: 82255 | CE42: 15104 | CK42: 25863 | CN42: 5504 | CQ42: 46471 | CR42: 2697 | CZ42: 598 | DC42: 1794 | DE42: 18480 | DK42: 23569 | DM42: 2816 | DU42: 12990 | DW42: 51588 | DY42: 9996 | DZ42: 77390 | EA42: 347711
A43: 西南 | H43: 7689 | I43: 36960 | P43: 44649 | Q43: 3596 | R43: 10010 | W43: 14376 | X43: 27982 | AB43: 9093 | AI43: 42735 | AK43: 51828 | AO43: 4905 | AQ43: 17995 | AR43: 6291 | AV43: 27261 | AZ43: 25794 | BB43: 82246 | BK43: 14289 | BN43: 8832 | BY43: 23121 | BZ43: 24465 | CF43: 27335 | CQ43: 51800 | CS43: 47289 | CV43: 3825 | CX43: 7787 | DF43: 10183 | DI43: 20790 | DK43: 89874 | DO43: 51291 | DV43: 9856 | DX43: 6495 | DZ43: 67642 | EA43: 439142
A44: 总计 | B44: 3590 | C44: 5394 | D44: 6385 | E44: 3596 | F44: 3495 | G44: 1797 | H44: 7689 | I44: 36960 | J44: 12320 | K44: 13592 | L44: 19190 | M44: 13980 | N44: 2691 | O44: 11398 | P44: 142077 | Q44: 3596 | R44: 14645 | S44: 598 | T44: 62689 | U44: 13980 | V44: 28495 | W44: 14376 | X44: 138379 | Y44: 46200 | Z44: 31176 | AA44: 23013 | AB44: 26190 | AC44: 27862 | AD44: 50265 | AE44: 765 | AF44: 1794 | AG44: 17475 | AH44: 28160 | AI44: 42735 | AJ44: 15588 | AK44: 311223 | AL44: 1797 | AM44: 1299 | AN44: 10523 | AO44: 4905 | AP44: 54088 | AQ44: 39589 | AR44: 38073 | AS44: 6293 | AT44: 28105 | AU44: 3588 | AV44: 40573 | AW44: 30289 | AX44: 34392 | AY44: 46574 | AZ44: 25794 | BA44: 22368 | BB44: 388250 | BC44: 39565 | BD44: 31559 | BE44: 2944 | BF44: 72884 | BG44: 27063 | BH44: 22762 | BI44: 6990 | BJ44: 23067 | BK44: 193423 | BL44: 10010 | BM44: 6162 | BN44: 8832 | BO44: 675 | BP44: 12800 | BQ44: 22980 | BR44: 17097 | BS44: 30236 | BT44: 9240 | BU44: 20271 | BV44: 13281 | BW44: 8704 | BX44: 6495 | BY44: 587040 | BZ44: 24465 | CA44: 71980 | CB44: 1299 | CC44: 11722 | CD44: 6528 | CE44: 15104 | CF44: 56210 | CG44: 15378 | CH44: 5196 | CI44: 34087 | CJ44: 10797 | CK44: 25863 | CL44: 19168 | CM44: 14396 | CN44: 5504 | CO44: 3596 | CP44: 42584 | CQ44: 363877 | CR44: 2697 | CS44: 47289 | CT44: 48142 | CU44: 2990 | CV44: 3825 | CW44: 5196 | CX44: 7787 | CY44: 11337 | CZ44: 20958 | DA44: 18174 | DB44: 12579 | DC44: 70182 | DD44: 3588 | DE44: 21470 | DF44: 72146 | DG44: 14976 | DH44: 23766 | DI44: 38283 | DJ44: 11883 | DK44: 437268 | DL44: 6489 | DM44: 37851 | DN44: 5592 | DO44: 53384 | DP44: 14396 | DQ44: 22163 | DR44: 19992 | DS44: 16073 | DT44: 5248 | DU44: 28186 | DV44: 9856 | DW44: 85980 | DX44: 6495 | DY44: 9996 | DZ44: 321701 | EA44: 2689815

Sheet Sheet5
A3: 月(日期) | B3: 求和项:金额(修正后) | C3: 求和项:金额(修正后)2
A4: 1月 | B4: 161324
A5: 2月 | B5: 235656 | C5: 0.46076219
A6: 3月 | B6: 321219 | C6: 0.36308433
A7: 4月 | B7: 407561 | C7: 0.26879481
A8: 5月 | B8: 699396 | C8: 0.71605232
A9: 6月 | B9: 390909 | C9: -0.4410763
A10: 7月 | B10: 443561 | C10: 0.13469119
A11: 8月 | B11: 321701 | C11: -0.2747311

Sheet 订单表_原始
A1: 订单编号 | B1: 下单日期 | C1: 下单日期(修正后) | D1: 客户ID | E1: 客户名称(修正后) | F1: 客户名称 | G1: 客户ID(修正后) | H1: 产品类别 | I1: 日期 | J1: 流水号 | K1: 用户登记（修正后） | L1: 销售员 | M1: 区域 | N1: 区域(修正后) | O1: 产品编码 | P1: 产品名称 | Q1: 单价(元) | R1: 数量 | S1: 修正后 | T1: 折扣(修正后) | U1: 金额(元) | V1: 金额(修正后) | W1: 订单状态 | X1: 应收金额 | Y1: 成本 | Z1: 毛利率
A2: DD-20260101-0001 | B2: 46023 | C2: =TEXT(SUBSTITUTE(B2,".","/"),"yyyy-mm-dd") -> 2026-01-01 | D2: KH003 | E2: =VLOOKUP(D2,客户信息表!A$3:H$23,2,0) -> 广州启航教育 | F2: 广州启航教育 | G2: =INDEX(客户信息表!$A$4:$H$23,MATCH(F2,客户信息表!$B$4:$B$23,0),1) -> KH003 | H2: =_xlfn.XLOOKUP(O2,产品信息表!$A$4:$A$15,产品信息表!$C$4:$C$15) -> 软件服务 | I2: =DATE(MID(A2,4,4),MID(A2,8,2),MID(A2,10,2)) -> 46023 | J2: =RIGHT(A2,4) -> 0001 | K2: =VLOOKUP(D2,客户信息表!$A$3:$H$23,5,0) -> A | L2: 孙悦 | M2: 华南 | N2: =SUBSTITUTE(TRIM(M2),"区","") -> 华南 | O2: CP011 | P2: 办公软件年费授权 | Q2: 699 | S2: =IF(ISBLANK(R2),U2/Q2,VALUE(R2)) -> 11 | T2: =VLOOKUP(S2,折扣阶梯!$A$3:$C$7,2,TRUE) -> 0.95 | U2: 7689 | V2: =IF(Q2*S2=VALUE(SUBSTITUTE(U2,"¥","")),VALUE(SUBSTITUTE(U2,"¥","")),Q2*S2) -> 7689 | W2: 已取消 | X2: =V2*T2 -> 7304.55 | Y2: =_xlfn.XLOOKUP(O2,产品信息表!$A$4:$A$15,产品信息表!$E$4:$E$15) -> 300 | Z2: =(X2-Y2*S2)/X2 -> 0.54822679 | AA2: =_xlfn.RANK.EQ(V2,V2:V203,0) -> 117
A3: DD-20260103-0002 | B3: 46025 | C3: =TEXT(SUBSTITUTE(B3,".","/"),"yyyy-mm-dd") -> 2026-01-03 | D3: KH002 | E3: =VLOOKUP(D3,客户信息表!A$3:H$23,2,0) -> 上海锦程贸易 | F3: 上海锦程贸易 | G3: =INDEX(客户信息表!$A$4:$H$23,MATCH(F3,客户信息表!$B$4:$B$23,0),1) -> KH002 | H3: =_xlfn.XLOOKUP(O3,产品信息表!$A$4:$A$15,产品信息表!$C$4:$C$15) -> 电子数码 | I3: =DATE(MID(A3,4,4),MID(A3,8,2),MID(A3,10,2)) -> 46025 | J3: =RIGHT(A3,4) -> 0002 | K3: =VLOOKUP(D3,客户信息表!$A$3:$H$23,5,0) -> B | L3: 李娜 | M3: 华东 | N3: =SUBSTITUTE(TRIM(M3),"区","") -> 华东 | O3: CP007 | P3: 无线键鼠套装 KeyFree 2.0 | Q3: 299 | R3: 9 | S3: =IF(ISBLANK(R3),U3/Q3,VALUE(R3)) -> 9 | T3: =VLOOKUP(S3,折扣阶梯!$A$3:$C$7,2,TRUE) -> 1 | U3: 2691 | V3: =IF(Q3*S3=VALUE(SUBSTITUTE(U3,"¥","")),VALUE(SUBSTITUTE(U3,"¥","")),Q3*S3) -> 2691 | W3: 已发货 | X3: =V3*T3 -> 2691 | Y3: =_xlfn.XLOOKUP(O3,产品信息表!$A$4:$A$15,产品信息表!$E$4:$E$15) -> 190 | Z3: =(X3-Y3*S3)/X3 -> 0.36454849 | AA3: =_xlfn.RANK.EQ(V3,V3:V204,0) -> 174
A4: DD-20260103-0003 | B4: 46025 | C4: =TEXT(SUBSTITUTE(B4,".","/"),"yyyy-mm-dd") -> 2026-01-03 | D4: KH003 | E4: =VLOOKUP(D4,客户信息表!A$3:H$23,2,0) -> 广州启航教育 | F4: 广州启航教育 | G4: =INDEX(客户信息表!$A$4:$H$23,MATCH(F4,客户信息表!$B$4:$B$23,0),1) -> KH003 | H4: =_xlfn.XLOOKUP(O4,产品信息表!$A$4:$A$15,产品信息表!$C$4:$C$15) -> 办公设备 | I4: =DATE(MID(A4,4,4),MID(A4,8,2),MID(A4,10,2)) -> 46025 | J4: =RIGHT(A4,4) -> 0003 | K4: =VLOOKUP(D4,客户信息表!$A$3:$H$23,5,0) -> A | L4: 陈静 | M4: 华南 | N4: =SUBSTITUTE(TRIM(M4),"区","") -> 华南 | O4: CP003 | P4: 碎纸机 SafeCut S8 | Q4: 899 | R4: 1 | S4: =IF(ISBLANK(R4),U4/Q4,VALUE(R4)) -> 1 | T4: =VLOOKUP(S4,折扣阶梯!$A$3:$C$7,2,TRUE) -> 1 | U4: 899 | V4: =IF(Q4*S4=VALUE(SUBSTITUTE(U4,"¥","")),VALUE(SUBSTITUTE(U4,"¥","")),Q4*S4) -> 899 | W4: 已发货 | X4: =V4*T4 -> 899 | Y4: =_xlfn.XLOOKUP(O4,产品信息表!$A$4:$A$15,产品信息表!$E$4:$E$15) -> 620 | Z4: =(X4-Y4*S4)/X4 -> 0.31034483 | AA4: =_xlfn.RANK.EQ(V4,V4:V205,0) -> 193
A5: DD-20260107-0004 | B5: 2026年1月7日 | C5: =TEXT(SUBSTITUTE(B5,".","/"),"yyyy-mm-dd") -> 2026-01-07 | D5: KH012 | E5: =VLOOKUP(D5,客户信息表!A$3:H$23,2,0) -> 长沙麓山科技 | F5: 长沙麓山科技 | G5: =INDEX(客户信息表!$A$4:$H$23,MATCH(F5,客户信息表!$B$4:$B$23,0),1) -> KH012 | H5: =_xlfn.XLOOKUP(O5,产品信息表!$A$4:$A$15,产品信息表!$C$4:$C$15) -> 办公设备 | I5: =DATE(MID(A5,4,4),MID(A5,8,2),MID(A5,10,2)) -> 46029 | J5: =RIGHT(A5,4) -> 0004 | K5: =VLOOKUP(D5,客户信息表!$A$3:$H$23,5,0) -> B | L5: 孙悦 | M5: 华中区 | N5: =SUBSTITUTE(TRIM(M5),"区","") -> 华中 | O5: CP003 | P5: 碎纸机 SafeCut S8 | Q5: 899 | R5: 6 | S5: =IF(ISBLANK(R5),U5/Q5,VALUE(R5)) -> 6 | T5: =VLOOKUP(S5,折扣阶梯!$A$3:$C$7,2,TRUE) -> 1 | U5: 5394 | V5: =IF(Q5*S5=VALUE(SUBSTITUTE(U5,"¥","")),VALUE(SUBSTITUTE(U5,"¥","")),Q5*S5) -> 5394 | W5: 已发货 | X5: =V5*T5 -> 5394 | Y5: =_xlfn.XLOOKUP(O5,产品信息表!$A$4:$A$15,产品信息表!$E$4:$E$15) -> 620 | Z5: =(X5-Y5*S5)/X5 -> 0.31034483 | AA5: =_xlfn.RANK.EQ(V5,V5:V206,0) -> 138
A6: DD-20260107-0005 | B6: 46029 | C6: =TEXT(SUBSTITUTE(B6,".","/"),"yyyy-mm-dd") -> 2026-01-07 | D6: KH019 | E6: =VLOOKUP(D6,客户信息表!A$3:H$23,2,0) -> 北京中关新材 | F6: 北京中关新材 | G6: =INDEX(客户信息表!$A$4:$H$23,MATCH(F6,客户信息表!$B$4:$B$23,0),1) -> KH019 | H6: =_xlfn.XLOOKUP(O6,产品信息表!$A$4:$A$15,产品信息表!$C$4:$C$15) -> 办公耗材 | I6: =DATE(MID(A6,4,4),MID(A6,8,2),MID(A6,10,2)) -> 46029 | J6: =RIGHT(A6,4) -> 0005 | K6: =VLOOKUP(D6,客户信息表!$A$3:$H$23,5,0) -> B | L6: 王强 | M6: 华北 | N6: =SUBSTITUTE(TRIM(M6),"区","") -> 华北 | O6: CP008 | P6: A4复印纸（5包/箱） | Q6: 128 | R6: 70 | S6: =IF(ISBLANK(R6),U6/Q6,VALUE(R6)) -> 70 | T6: =VLOOKUP(S6,折扣阶梯!$A$3:$C$7,2,TRUE) -> 0.9 | U6: 8960 | V6: =IF(Q6*S6=VALUE(SUBSTITUTE(U6,"¥","")),VALUE(SUBSTITUTE(U6,"¥","")),Q6*S6) -> 8960 | W6: 已取消 | X6: =V6*T6 -> 8064 | Y6: =_xlfn.XLOOKUP(O6,产品信息表!$A$4:$A$15,产品信息表!$E$4:$E$15) -> 95 | Z6: =(X6-Y6*S6)/X6 -> 0.17534722 | AA6: =_xlfn.RANK.EQ(V6,V6:V207,0) -> 110
A7: DD-20260109-0006 | B7: 46031 | C7: =TEXT(SUBSTITUTE(B7,".","/"),"yyyy-mm-dd") -> 2026-01-09 | D7: KH017 | E7: =VLOOKUP(D7,客户信息表!A$3:H$23,2,0) -> 郑州中原物流 | F7: 郑州中原物流 | G7: =INDEX(客户信息表!$A$4:$H$23,MATCH(F7,客户信息表!$B$4:$B$23,0),1) -> KH017 | H7: =_xlfn.XLOOKUP(O7,产品信息表!$A$4:$A$15,产品信息表!$C$4:$C$15) -> 办公耗材 | I7: =DATE(MID(A7,4,4),MID(A7,8,2),MID(A7,10,2)) -> 46031 | J7: =RIGHT(A7,4) -> 0006 | K7: =VLOOKUP(D7,客户信息表!$A$3:$H$23,5,0) -> B | L7: 赵磊 | M7: 华中 | N7: =SUBSTITUTE(TRIM(M7),"区","") -> 华中 | O7: CP008 | P7: A4复印纸（5包/箱） | Q7: 128 | R7: 20 | S7: =IF(ISBLANK(R7),U7/Q7,VALUE(R7)) -> 20 | T7: =VLOOKUP(S7,折扣阶梯!$A$3:$C$7,2,TRUE) -> 0.95 | U7: 2560 | V7: =IF(Q7*S7=VALUE(SUBSTITUTE(U7,"¥","")),VALUE(SUBSTITUTE(U7,"¥","")),Q7*S7) -> 2560 | W7: 已发货 | X7: =V7*T7 -> 2432 | Y7: =_xlfn.XLOOKUP(O7,产品信息表!$A$4:$A$15,产品信息表!$E$4:$E$15) -> 95 | Z7: =(X7-Y7*S7)/X7 -> 0.21875 | AA7: =_xlfn.RANK.EQ(V7,V7:V208,0) -> 176
A8: DD-20260109-0007 | B8: 46031 | C8: =TEXT(SUBSTITUTE(B8,".","/"),"yyyy-mm-dd") -> 2026-01-09 | D8: KH019 | E8: =VLOOKUP(D8,客户信息表!A$3:H$23,2,0) -> 北京中关新材 | F8: 北京中关新材 | G8: =INDEX(客户信息表!$A$4:$H$23,MATCH(F8,客户信息表!$B$4:$B$23,0),1) -> KH019 | H8: =_xlfn.XLOOKUP(O8,产品信息表!$A$4:$A$15,产品信息表!$C$4:$C$15) -> 办公耗材 | I8: =DATE(MID(A8,4,4),MID(A8,8,2),MID(A8,10,2)) -> 46031 | J8: =RIGHT(A8,4) -> 0007 | K8: =VLOOKUP(D8,客户信息表!$A$3:$H$23,5,0) -> B | L8: 陈静 | M8: 华北 | N8: =SUBSTITUTE(TRIM(M8),"区","") -> 华北 | O8: CP010 | P8: 签字笔盒装（12支） | Q8: 45 | R8: 85 | S8: =IF(ISBLANK(R8),U8/Q8,VALUE(R8)) -> 85 | T8: =VLOOKUP(S8,折扣阶梯!$A$3:$C$7,2,TRUE) -> 0.9 | U8: 3825 | V8: =IF(Q8*S8=VALUE(SUBSTITUTE(U8,"¥","")),VALUE(SUBSTITUTE(U8,"¥","")),Q8*S8) -> 3825 | W8: 已完成 | X8: =V8*T8 -> 3442.5 | Y8: =_xlfn.XLOOKUP(O8,产品信息表!$A$4:$A$15,产品信息表!$E$4:$E$15) -> 28 | Z8: =(X8-Y8*S8)/X8 -> 0.30864198 | AA8: =_xlfn.RANK.EQ(V8,V8:V209,0) -> 152
A9: DD-20260113-0008 | B9: 46035 | C9: =TEXT(SUBSTITUTE(B9,".","/"),"yyyy-mm-dd") -> 2026-01-13 | D9: KH007 | E9: =VLOOKUP(D9,客户信息表!A$3:H$23,2,0) -> 武汉长江实业 | F9: 武汉长江实业 | G9: =INDEX(客户信息表!$A$4:$H$23,MATCH(F9,客户信息表!$B$4:$B$23,0),1) -> KH007 | H9: =_xlfn.XLOOKUP(O9,产品信息表!$A$4:$A$15,产品信息表!$C$4:$C$15) -> 办公设备 | I9: =DATE(MID(A9,4,4),MID(A9,8,2),MID(A9,10,2)) -> 46035 | J9: =RIGHT(A9,4) -> 0008 | K9: =VLOOKUP(D9,客户信息表!$A$3:$H$23,5,0) -> B | L9: 赵磊 | M9: 华中 | N9: =SUBSTITUTE(TRIM(M9),"区","") -> 华中 | O9: CP003 | P9: 碎纸机 SafeCut S8 | Q9: 899 | R9: 4 | S9: =IF(ISBLANK(R9),U9/Q9,VALUE(R9)) -> 4 | T9: =VLOOKUP(S9,折扣阶梯!$A$3:$C$7,2,TRUE) -> 1 | U9: 3596 | V9: =IF(Q9*S9=VALUE(SUBSTITUTE(U9,"¥","")),VALUE(SUBSTITUTE(U9,"¥","")),Q9*S9) -> 3596 | W9: 已完成 | X9: =V9*T9 -> 3596 | Y9: =_xlfn.XLOOKUP(O9,产品信息表!$A$4:$A$15,产品信息表!$E$4:$E$15) -> 620 | Z9: =(X9-Y9*S9)/X9 -> 0.31034483 | AA9: =_xlfn.RANK.EQ(V9,V9:V210,0) -> 154
A10: DD-20260117-0009 | B10: 46039 | C10: =TEXT(SUBSTITUTE(B10,".","/"),"yyyy-mm-dd") -> 2026-01-17 | D10: KH002 | E10: =VLOOKUP(D10,客户信息表!A$3:H$23,2,0) -> 上海锦程贸易 | F10: 上海锦程贸易 | G10: =INDEX(客户信息表!$A$4:$H$23,MATCH(F10,客户信息表!$B$4:$B$23,0),1) -> KH002 | H10: =_xlfn.XLOOKUP(O10,产品信息表!$A$4:$A$15,产品信息表!$C$4:$C$15) -> 软件服务 | I10: =DATE(MID(A10,4,4),MID(A10,8,2),MID(A10,10,2)) -> 46039 | J10: =RIGHT(A10,4) -> 0009 | K10: =VLOOKUP(D10,客户信息表!$A$3:$H$23,5,0) -> B | L10: 杨帆 | M10: 华东 | N10: =SUBSTITUTE(TRIM(M10),"区","") -> 华东 | O10: CP011 | P10: 办公软件年费授权 | Q10: 699 | R10: 5 | S10: =IF(ISBLANK(R10),U10/Q10,VALUE(R10)) -> 5 | T10: =VLOOKUP(S10,折扣阶梯!$A$3:$C$7,2,TRUE) -> 1 | U10: 3495 | V10: =IF(Q10*S10=VALUE(SUBSTITUTE(U10,"¥","")),VALUE(SUBSTITUTE(U10,"¥","")),Q10*S10) -> 3495 | W10: 已发货 | X10: =V10*T10 -> 3495 | Y10: =_xlfn.XLOOKUP(O10,产品信息表!$A$4:$A$15,产品信息表!$E$4:$E$15) -> 300 | Z10: =(X10-Y10*S10)/X10 -> 0.57081545 | AA10: =_xlfn.RANK.EQ(V10,V10:V211,0) -> 159
A11: DD-20260120-0010 | B11: 46042 | C11: =TEXT(SUBSTITUTE(B11,".","/"),"yyyy-mm-dd") -> 2026-01-20 | D11: KH019 | E11: =VLOOKUP(D11,客户信息表!A$3:H$23,2,0) -> 北京中关新材 | F11: 北京中关新材 | G11: =INDEX(客户信息表!$A$4:$H$23,MATCH(F11,客户信息表!$B$4:$B$23,0),1) -> KH019 | H11: =_xlfn.XLOOKUP(O11,产品信息表!$A$4:$A$15,产品信息表!$C$4:$C$15) -> 软件服务 | I11: =DATE(MID(A11,4,4),MID(A11,8,2),MID(A11,10,2)) -> 46042 | J11: =RIGHT(A11,4) -> 0010 | K11: =VLOOKUP(D11,客户信息表!$A$3:$H$23,5,0) -> B | L11: 孙悦 | M11: 华北 | N11: =SUBSTITUTE(TRIM(M11),"区","") -> 华北 | O11: CP012 | P11: 云存储服务（1TB/年） | Q11: 599 | R11: 3 | S11: =IF(ISBLANK(R11),U11/Q11,VALUE(R11)) -> 3 | T11: =VLOOKUP(S11,折扣阶梯!$A$3:$C$7,2,TRUE) -> 1 | U11: 1797 | V11: =IF(Q11*S11=VALUE(SUBSTITUTE(U11,"¥","")),VALUE(SUBSTITUTE(U11,"¥","")),Q11*S11) -> 1797 | W11: 已完成 | X11: =V11*T11 -> 1797 | Y11: =_xlfn.XLOOKUP(O11,产品信息表!$A$4:$A$15,产品信息表!$E$4:$E$15) -> 250 | Z11: =(X11-Y11*S11)/X11 -> 0.58263773 | AA11: =_xlfn.RANK.EQ(V11,V11:V212,0) -> 176
A12: DD-20260121-0011 | B12: 46043 | C12: =TEXT(SUBSTITUTE(B12,".","/"),"yyyy-mm-dd") -> 2026-01-21 | D12: KH005 | E12: =VLOOKUP(D12,客户信息表!A$3:H$23,2,0) -> 杭州云图信息 | F12: 杭州云图信息 | G12: =INDEX(客户信息表!$A$4:$H$23,MATCH(F12,客户信息表!$B$4:$B$23,0),1) -> KH005 | H12: =_xlfn.XLOOKUP(O12,产品信息表!$A$4:$A$15,产品信息表!$C$4:$C$15) -> 电子数码 | I12: =DATE(MID(A12,4,4),MID(A12,8,2),MID(A12,10,2)) -> 46043 | J12: =RIGHT(A12,4) -> 0011 | K12: =VLOOKUP(D12,客户信息表!$A$3:$H$23,5,0) -> A | L12: 孙悦 | M12: 华东 | N12: =SUBSTITUTE(TRIM(M12),"区","") -> 华东 | O12: CP006 | P12: 显示器 ViewMax 27 | Q12: 1299 | R12: 2 | S12: =IF(ISBLANK(R12),U12/Q12,VALUE(R12)) -> 2 | T12: =VLOOKUP(S12,折扣阶梯!$A$3:$C$7,2,TRUE) -> 1 | U12: 2598 | V12: =IF(Q12*S12=VALUE(SUBSTITUTE(U12,"¥","")),VALUE(SUBSTITUTE(U12,"¥","")),Q12*S12) -> 2598 | W12: 已取消 | X12: =V12*T12 -> 2598 | Y12: =_xlfn.XLOOKUP(O12,产品信息表!$A$4:$A$15,产品信息表!$E$4:$E$15) -> 950 | Z12: =(X12-Y12*S12)/X12 -> 0.26866821 | AA12: =_xlfn.RANK.EQ(V12,V12:V213,0) -> 171
A13: DD-20260123-0012 | B13: 46045 | C13: =TEXT(SUBSTITUTE(B13,".","/"),"yyyy-mm-dd") -> 2026-01-23 | D13: KH011 | E13: =VLOOKUP(D13,客户信息表!A$3:H$23,2,0) -> 重庆山城办公设备 | F13: 重庆山城办公设备 | G13: =INDEX(客户信息表!$A$4:$H$23,MATCH(F13,客户信息表!$B$4:$B$23,0),1) -> KH011 | H13: =_xlfn.XLOOKUP(O13,产品信息表!$A$4:$A$15,产品信息表!$C$4:$C$15) -> 软件服务 | I13: =DATE(MID(A13,4,4),MID(A13,8,2),MID(A13,10,2)) -> 46045 | J13: =RIGHT(A13,4) -> 0012 | K13: =VLOOKUP(D13,客户信息表!$A$3:$H$23,5,0) -> B | L13: 刘洋 | M13: 西南 | N13: =SUBSTITUTE(TRIM(M13),"区","") -> 西南 | O13: CP011 | P13: 办公软件年费授权 | Q13: 699 | R13: 11 | S13: =IF(ISBLANK(R13),U13/Q13,VALUE(R13)) -> 11 | T13: =VLOOKUP(S13,折扣阶梯!$A$3:$C$7,2,TRUE) -> 0.95 | U13: 7689 | V13: =IF(Q13*S13=VALUE(SUBSTITUTE(U13,"¥","")),VALUE(SUBSTITUTE(U13,"¥","")),Q13*S13) -> 7689 | W13: 已完成 | X13: =V13*T13 -> 7304.55 | Y13: =_xlfn.XLOOKUP(O13,产品信息表!$A$4:$A$15,产品信息表!$E$4:$E$15) -> 300 | Z13: =(X13-Y13*S13)/X13 -> 0.54822679 | AA13: =_xlfn.RANK.EQ(V13,V13:V214,0) -> 116
A14: DD-20260124-0013 | B14: 46046 | C14: =TEXT(SUBSTITUTE(B14,".","/"),"yyyy-mm-dd") -> 2026-01-24 | D14: KH006 | E14: =VLOOKUP(D14,客户信息表!A$3:H$23,2,0) -> 成都天府商贸 | F14: 成都天府商贸 | G14: =INDEX(客户信息表!$A$4:$H$23,MATCH(F14,客户信息表!$B$4:$B$23,0),1) -> KH006 | H14: =_xlfn.XLOOKUP(O14,产品信息表!$A$4:$A$15,产品信息表!$C$4:$C$15) -> 办公耗材 | I14: =DATE(MID(A14,4,4),MID(A14,8,2),MID(A14,10,2)) -> 46046 | J14: =RIGHT(A14,4) -> 0013 | K14: =VLOOKUP(D14,客户信息表!$A$3:$H$23,5,0) -> C | L14: 李娜 | M14: 西南 | N14: =SUBSTITUTE(TRIM(M14),"区","") -> 西南 | O14: CP009 | P14: 激光硒鼓 TonerMax 12A | Q14: 385 | R14: 96 | S14: =IF(ISBLANK(R14),U14/Q14,VALUE(R14)) -> 96 | T14: =VLOOKUP(S14,折扣阶梯!$A$3:$C$7,2,TRUE) -> 0.9 | U14: 36960 | V14: =IF(Q14*S14=VALUE(SUBSTITUTE(U14,"¥","")),VALUE(SUBSTITUTE(U14,"¥","")),Q14*S14) -> 36960 | W14: 已完成 | X14: =V14*T14 -> 33264 | Y14: =_xlfn.XLOOKUP(O14,产品信息表!$A$4:$A$15,产品信息表!$E$4:$E$15) -> 260 | Z14: =(X14-Y14*S14)/X14 -> 0.24963925 | AA14: =_xlfn.RANK.EQ(V14,V14:V215,0) -> 18
A15: DD-20260125-0014 | B15: 46047 | C15: =TEXT(SUBSTITUTE(B15,".","/"),"yyyy-mm-dd") -> 2026-01-25 | D15: KH001 | E15: =VLOOKUP(D15,客户信息表!A$3:H$23,2,0) -> 北京华信科技 | F15: 北京华信科技 | G15: =INDEX(客户信息表!$A$4:$H$23,MATCH(F15,客户信息表!$B$4:$B$23,0),1) -> KH001 | H15: =_xlfn.XLOOKUP(O15,产品信息表!$A$4:$A$15,产品信息表!$C$4:$C$15) -> 办公耗材 | I15: =DATE(MID(A15,4,4),MID(A15,8,2),MID(A15,10,2)) -> 46047 | J15: =RIGHT(A15,4) -> 0014 | K15: =VLOOKUP(D15,客户信息表!$A$3:$H$23,5,0) -> A | L15: 张伟 | M15: 华北 | N15: =SUBSTITUTE(TRIM(M15),"区","") -> 华北 | O15: CP009 | P15: 激光硒鼓 TonerMax 12A | Q15: 385 | R15: 32 | S15: =IF(ISBLANK(R15),U15/Q15,VALUE(R15)) -> 32 | T15: =VLOOKUP(S15,折扣阶梯!$A$3:$C$7,2,TRUE) -> 0.95 | U15: 12320 | V15: =IF(Q15*S15=VALUE(SUBSTITUTE(U15,"¥","")),VALUE(SUBSTITUTE(U15,"¥","")),Q15*S15) -> 12320 | W15: 已发货 | X15: =V15*T15 -> 11704 | Y15: =_xlfn.XLOOKUP(O15,产品信息表!$A$4:$A$15,产品信息表!$E$4:$E$15) -> 260 | Z15: =(X15-Y15*S15)/X15 -> 0.28913192 | AA15: =_xlfn.RANK.EQ(V15,V15:V216,0) -> 89
A16: DD-20260126-0015 | B16: 46048 | C16: =TEXT(SUBSTITUTE(B16,".","/"),"yyyy-mm-dd") -> 2026-01-26 | D16: KH019 | E16: =VLOOKUP(D16,客户信息表!A$3:H$23,2,0) -> 北京中关新材 | F16: 北京中关新材 | G16: =INDEX(客户信息表!$A$4:$H$23,MATCH(F16,客户信息表!$B$4:$B$23,0),1) -> KH019 | H16: =_xlfn.XLOOKUP(O16,产品信息表!$A$4:$A$15,产品信息表!$C$4:$C$15) -> 办公设备 | I16: =DATE(MID(A16,4,4),MID(A16,8,2),MID(A16,10,2)) -> 46048 | J16: =RIGHT(A16,4) -> 0015 | K16: =VLOOKUP(D16,客户信息表!$A$3:$H$23,5,0) -> B | L16: 孙悦 | M16: 华北 | N16: =SUBSTITUTE(TRIM(M16),"区","") -> 华北 | O16: CP001 | P16: 激光打印机 ProLaser 200 | Q16: 2499 | S16: =IF(ISBLANK(R16),U16/Q16,VALUE(R16)) -> 4 | T16: =VLOOKUP(S16,折扣阶梯!$A$3:$C$7,2,TRUE) -> 1 | U16: 9996 | V16: =IF(Q16*S16=VALUE(SUBSTITUTE(U16,"¥","")),VALUE(SUBSTITUTE(U16,"¥","")),Q16*S16) -> 9996 | W16: 已发货 | X16: =V16*T16 -> 9996 | Y16: =_xlfn.XLOOKUP(O16,产品信息表!$A$4:$A$15,产品信息表!$E$4:$E$15) -> 1850 | Z16: =(X16-Y16*S16)/X16 -> 0.25970388 | AA16: =_xlfn.RANK.EQ(V16,V16:V217,0) -> 100
A17: DD-20260816-0196 | B17: 46250 | C17: =TEXT(SUBSTITUTE(B17,".","/"),"yyyy-mm-dd") -> 2026-08-16 | D17: KH016 | E17: =VLOOKUP(D17,客户信息表!A$3:H$23,2,0) -> 昆明滇池科技 | F17: 昆明滇池科技 | G17: =INDEX(客户信息表!$A$4:$H$23,MATCH(F17,客户信息表!$B$4:$B$23,0),1) -> KH016 | H17: =_xlfn.XLOOKUP(O17,产品信息表!$A$4:$A$15,产品信息表!$C$4:$C$15) -> 办公耗材 | I17: =DATE(MID(A17,4,4),MID(A17,8,2),MID(A17,10,2)) -> 46250 | J17: =RIGHT(A17,4) -> 0196 | K17: =VLOOKUP(D17,客户信息表!$A$3:$H$23,5,0) -> C | L17: 赵磊 | M17: 西南区 | N17: =SUBSTITUTE(TRIM(M17),"区","") -> 西南 | O17: CP008 | P17: A4复印纸（5包/箱） | Q17: 128 | R17: 77 | S17: =IF(ISBLANK(R17),U17/Q17,VALUE(R17)) -> 77 | T17: =VLOOKUP(S17,折扣阶梯!$A$3:$C$7,2,TRUE) -> 0.9 | U17: 9856 | V17: =IF(Q17*S17=VALUE(SUBSTITUTE(U17,"¥","")),VALUE(SUBSTITUTE(U17,"¥","")),Q17*S17) -> 9856 | W17: 已完成 | X17: =V17*T17 -> 8870.4 | Y17: =_xlfn.XLOOKUP(O17,产品信息表!$A$4:$A$15,产品信息表!$E$4:$E$15) -> 95 | Z17: =(X17-Y17*S17)/X17 -> 0.17534722 | AA17: =_xlfn.RANK.EQ(V17,V17:V218,0) -> 102
A18: DD-20260126-0016 | B18: 46048 | C18: =TEXT(SUBSTITUTE(B18,".","/"),"yyyy-mm-dd") -> 2026-01-26 | D18: KH017 | E18: =VLOOKUP(D18,客户信息表!A$3:H$23,2,0) -> 郑州中原物流 | F18: 郑州中原物流 | G18: =INDEX(客户信息表!$A$4:$H$23,MATCH(F18,客户信息表!$B$4:$B$23,0),1) -> KH017 | H18: =_xlfn.XLOOKUP(O18,产品信息表!$A$4:$A$15,产品信息表!$C$4:$C$15) -> 办公设备 | I18: =DATE(MID(A18,4,4),MID(A18,8,2),MID(A18,10,2)) -> 46048 | J18: =RIGHT(A18,4) -> 0016 | K18: =VLOOKUP(D18,客户信息表!$A$3:$H$23,5,0) -> B | L18: 王强 | M18: 华中区 | N18: =SUBSTITUTE(TRIM(M18),"区","") -> 华中 | O18: CP003 | P18: 碎纸机 SafeCut S8 | Q18: 899 | R18: 4 | S18: =IF(ISBLANK(R18),U18/Q18,VALUE(R18)) -> 4 | T18: =VLOOKUP(S18,折扣阶梯!$A$3:$C$7,2,TRUE) -> 1 | U18: 3596 | V18: =IF(Q18*S18=VALUE(SUBSTITUTE(U18,"¥","")),VALUE(SUBSTITUTE(U18,"¥","")),Q18*S18) -> 3596 | W18: 已完成 | X18: =V18*T18 -> 3596 | Y18: =_xlfn.XLOOKUP(O18,产品信息表!$A$4:$A$15,产品信息表!$E$4:$E$15) -> 620 | Z18: =(X18-Y18*S18)/X18 -> 0.31034483 | AA18: =_xlfn.RANK.EQ(V18,V18:V219,0) -> 149
A19: DD-20260127-0017 | B19: 46049 | C19: =TEXT(SUBSTITUTE(B19,".","/"),"yyyy-mm-dd") -> 2026-01-27 | D19: KH017 | E19: =VLOOKUP(D19,客户信息表!A$3:H$23,2,0) -> 郑州中原物流 | F19: 郑州中原物流 | G19: =INDEX(客户信息表!$A$4:$H$23,MATCH(F19,客户信息表!$B$4:$B$23,0),1) -> KH017 | H19: =_xlfn.XLOOKUP(O19,产品信息表!$A$4:$A$15,产品信息表!$C$4:$C$15) -> 电子数码 | I19: =DATE(MID(A19,4,4),MID(A19,8,2),MID(A19,10,2)) -> 46049 | J19: =RIGHT(A19,4) -> 0017 | K19: =VLOOKUP(D19,客户信息表!$A$3:$H$23,5,0) -> B | L19: 赵磊 | M19: 华中 | N19: =SUBSTITUTE(TRIM(M19),"区","") -> 华中 | O19: CP007 | P19: 无线键鼠套装 KeyFree 2.0 | Q19: 299 | R19: 7 | S19: =IF(ISBLANK(R19),U19/Q19,VALUE(R19)) -> 7 | T19: =VLOOKUP(S19,折扣阶梯!$A$3:$C$7,2,TRUE) -> 1 | U19: 2093 | V19: =IF(Q19*S19=VALUE(SUBSTITUTE(U19,"¥","")),VALUE(SUBSTITUTE(U19,"¥","")),Q19*S19) -> 2093 | W19: 待付款 | X19: =V19*T19 -> 2093 | Y19: =_xlfn.XLOOKUP(O19,产品信息表!$A$4:$A$15,产品信息表!$E$4:$E$15) -> 190 | Z19: =(X19-Y19*S19)/X19 -> 0.36454849 | AA19: =_xlfn.RANK.EQ(V19,V19:V220,0) -> 167
A20: DD-20260127-0018 | B20: 46049 | C20: =TEXT(SUBSTITUTE(B20,".","/"),"yyyy-mm-dd") -> 2026-01-27 | D20: KH007 | E20: =VLOOKUP(D20,客户信息表!A$3:H$23,2,0) -> 武汉长江实业 | F20: 武汉长江实业 | G20: =INDEX(客户信息表!$A$4:$H$23,MATCH(F20,客户信息表!$B$4:$B$23,0),1) -> KH007 | H20: =_xlfn.XLOOKUP(O20,产品信息表!$A$4:$A$15,产品信息表!$C$4:$C$15) -> 电子数码 | I20: =DATE(MID(A20,4,4),MID(A20,8,2),MID(A20,10,2)) -> 46049 | J20: =RIGHT(A20,4) -> 0018 | K20: =VLOOKUP(D20,客户信息表!$A$3:$H$23,5,0) -> B | L20: 陈静 | M20: 华中 | N20: =SUBSTITUTE(TRIM(M20),"区","") -> 华中 | O20: CP004 | P20: 笔记本电脑 TechBook 14 | Q20: 5699 | R20: 3 | S20: =IF(ISBLANK(R20),U20/Q20,VALUE(R20)) -> 3 | T20: =VLOOKUP(S20,折扣阶梯!$A$3:$C$7,2,TRUE) -> 1 | U20: 17097 | V20: =IF(Q20*S20=VALUE(SUBSTITUTE(U20,"¥","")),VALUE(SUBSTITUTE(U20,"¥","")),Q20*S20) -> 17097 | W20: 已完成 | X20: =V20*T20 -> 17097 | Y20: =_xlfn.XLOOKUP(O20,产品信息表!$A$4:$A$15,产品信息表!$E$4:$E$15) -> 4800 | Z20: =(X20-Y20*S20)/X20 -> 0.15774697 | AA20: =_xlfn.RANK.EQ(V20,V20:V221,0) -> 63
A21: DD-20260129-0019 | B21: 46051 | C21: =TEXT(SUBSTITUTE(B21,".","/"),"yyyy-mm-dd") -> 2026-01-29 | D21: KH020 | E21: =VLOOKUP(D21,客户信息表!A$3:H$23,2,0) -> 合肥科大国创 | F21: 合肥科大国创 | G21: =INDEX(客户信息表!$A$4:$H$23,MATCH(F21,客户信息表!$B$4:$B$23,0),1) -> KH020 | H21: =_xlfn.XLOOKUP(O21,产品信息表!$A$4:$A$15,产品信息表!$C$4:$C$15) -> 软件服务 | I21: =DATE(MID(A21,4,4),MID(A21,8,2),MID(A21,10,2)) -> 46051 | J21: =RIGHT(A21,4) -> 0019 | K21: =VLOOKUP(D21,客户信息表!$A$3:$H$23,5,0) -> C | L21: 孙悦 | M21: 华东 | N21: =SUBSTITUTE(TRIM(M21),"区","") -> 华东 | O21: CP011 | P21: 办公软件年费授权 | Q21: 699 | R21: 20 | S21: =IF(ISBLANK(R21),U21/Q21,VALUE(R21)) -> 20 | T21: =VLOOKUP(S21,折扣阶梯!$A$3:$C$7,2,TRUE) -> 0.95 | U21: 13980 | V21: =IF(Q21*S21=VALUE(SUBSTITUTE(U21,"¥","")),VALUE(SUBSTITUTE(U21,"¥","")),Q21*S21) -> 13980 | W21: 已完成 | X21: =V21*T21 -> 13281 | Y21: =_xlfn.XLOOKUP(O21,产品信息表!$A$4:$A$15,产品信息表!$E$4:$E$15) -> 300 | Z21: =(X21-Y21*S21)/X21 -> 0.54822679 | AA21: =_xlfn.RANK.EQ(V21,V21:V222,0) -> 78
A22: DD-20260130-0020 | B22: 46052 | C22: =TEXT(SUBSTITUTE(B22,".","/"),"yyyy-mm-dd") -> 2026-01-30 | D22: KH010 | E22: =VLOOKUP(D22,客户信息表!A$3:H$23,2,0) -> 苏州创智科技 | F22: 苏州创智科技 | G22: =INDEX(客户信息表!$A$4:$H$23,MATCH(F22,客户信息表!$B$4:$B$23,0),1) -> KH010 | H22: =_xlfn.XLOOKUP(O22,产品信息表!$A$4:$A$15,产品信息表!$C$4:$C$15) -> 电子数码 | I22: =DATE(MID(A22,4,4),MID(A22,8,2),MID(A22,10,2)) -> 46052 | J22: =RIGHT(A22,4) -> 0020 | K22: =VLOOKUP(D22,客户信息表!$A$3:$H$23,5,0) -> A | L22: 陈静 | M22: 华东 | N22: =SUBSTITUTE(TRIM(M22),"区","") -> 华东 | O22: CP007 | P22: 无线键鼠套装 KeyFree 2.0 | Q22: 299 | R22: 9 | S22: =IF(ISBLANK(R22),U22/Q22,VALUE(R22)) -> 9 | T22: =VLOOKUP(S22,折扣阶梯!$A$3:$C$7,2,TRUE) -> 1 | U22: ¥2,691.00 | V22: =IF(Q22*S22=VALUE(SUBSTITUTE(U22,"¥","")),VALUE(SUBSTITUTE(U22,"¥","")),Q22*S22) -> 2691 | W22: 待付款 | X22: =V22*T22 -> 2691 | Y22: =_xlfn.XLOOKUP(O22,产品信息表!$A$4:$A$15,产品信息表!$E$4:$E$15) -> 190 | Z22: =(X22-Y22*S22)/X22 -> 0.36454849 | AA22: =_xlfn.RANK.EQ(V22,V22:V223,0) -> 161
A23: DD-20260131-0021 | B23: 46053 | C23: =TEXT(SUBSTITUTE(B23,".","/"),"yyyy-mm-dd") -> 2026-01-31 | D23: KH017 | E23: =VLOOKUP(D23,客户信息表!A$3:H$23,2,0) -> 郑州中原物流 | F23: 郑州中原物流 | G23: =INDEX(客户信息表!$A$4:$H$23,MATCH(F23,客户信息表!$B$4:$B$23,0),1) -> KH017 | H23: =_xlfn.XLOOKUP(O23,产品信息表!$A$4:$A$15,产品信息表!$C$4:$C$15) -> 电子数码 | I23: =DATE(MID(A23,4,4),MID(A23,8,2),MID(A23,10,2)) -> 46053 | J23: =RIGHT(A23,4) -> 0021 | K23: =VLOOKUP(D23,客户信息表!$A$3:$H$23,5,0) -> B | L23: 孙悦 | M23: 华中 | N23: =SUBSTITUTE(TRIM(M23),"区","") -> 华中 | O23: CP004 | P23: 笔记本电脑 TechBook 14 | Q23: 5699 | R23: 2 | S23: =IF(ISBLANK(R23),U23/Q23,VALUE(R23)) -> 2 | T23: =VLOOKUP(S23,折扣阶梯!$A$3:$C$7,2,TRUE) -> 1 | U23: 11398 | V23: =IF(Q23*S23=VALUE(SUBSTITUTE(U23,"¥","")),VALUE(SUBSTITUTE(U23,"¥","")),Q23*S23) -> 11398 | W23: 已发货 | X23: =V23*T23 -> 11398 | Y23: =_xlfn.XLOOKUP(O23,产品信息表!$A$4:$A$15,产品信息表!$E$4:$E$15) -> 4800 | Z23: =(X23-Y23*S23)/X23 -> 0.15774697 | AA23: =_xlfn.RANK.EQ(V23,V23:V224,0) -> 92
A24: DD-20260201-0022 | B24: 46054 | C24: =TEXT(SUBSTITUTE(B24,".","/"),"yyyy-mm-dd") -> 2026-02-01 | D24: KH007 | E24: =VLOOKUP(D24,客户信息表!A$3:H$23,2,0) -> 武汉长江实业 | F24: 武汉长江实业 | G24: =INDEX(客户信息表!$A$4:$H$23,MATCH(F24,客户信息表!$B$4:$B$23,0),1) -> KH007 | H24: =_xlfn.XLOOKUP(O24,产品信息表!$A$4:$A$15,产品信息表!$C$4:$C$15) -> 办公耗材 | I24: =DATE(MID(A24,4,4),MID(A24,8,2),MID(A24,10,2)) -> 46054 | J24: =RIGHT(A24,4) -> 0022 | K24: =VLOOKUP(D24,客户信息表!$A$3:$H$23,5,0) -> B | L24: 王强 | M24: 华中 | N24: =SUBSTITUTE(TRIM(M24),"区","") -> 华中 | O24: CP010 | P24: 签字笔盒装（12支） | Q24: 45 | R24: 118 | S24: =IF(ISBLANK(R24),U24/Q24,VALUE(R24)) -> 118 | T24: =VLOOKUP(S24,折扣阶梯!$A$3:$C$7,2,TRUE) -> 0.85 | U24: 5310 | V24: =IF(Q24*S24=VALUE(SUBSTITUTE(U24,"¥","")),VALUE(SUBSTITUTE(U24,"¥","")),Q24*S24) -> 5310 | W24: 已取消 | X24: =V24*T24 -> 4513.5 | Y24: =_xlfn.XLOOKUP(O24,产品信息表!$A$4:$A$15,产品信息表!$E$4:$E$15) -> 28 | Z24: =(X24-Y24*S24)/X24 -> 0.26797386 | AA24: =_xlfn.RANK.EQ(V24,V24:V225,0) -> 129
A25: DD-20260203-0023 | B25: 46056 | C25: =TEXT(SUBSTITUTE(B25,".","/"),"yyyy-mm-dd") -> 2026-02-03 | D25: KH006 | E25: =VLOOKUP(D25,客户信息表!A$3:H$23,2,0) -> 成都天府商贸 | F25: 成都天府商贸 | G25: =INDEX(客户信息表!$A$4:$H$23,MATCH(F25,客户信息表!$B$4:$B$23,0),1) -> KH006 | H25: =_xlfn.XLOOKUP(O25,产品信息表!$A$4:$A$15,产品信息表!$C$4:$C$15) -> 办公设备 | I25: =DATE(MID(A25,4,4),MID(A25,8,2),MID(A25,10,2)) -> 46056 | J25: =RIGHT(A25,4) -> 0023 | K25: =VLOOKUP(D25,客户信息表!$A$3:$H$23,5,0) -> C | L25: 李娜 | M25: 西南 | N25: =SUBSTITUTE(TRIM(M25),"区","") -> 西南 | O25: CP003 | P25: 碎纸机 SafeCut S8 | Q25: 899 | R25: 4 | S25: =IF(ISBLANK(R25),U25/Q25,VALUE(R25)) -> 4 | T25: =VLOOKUP(S25,折扣阶梯!$A$3:$C$7,2,TRUE) -> 1 | U25: 3596 | V25: =IF(Q25*S25=VALUE(SUBSTITUTE(U25,"¥","")),VALUE(SUBSTITUTE(U25,"¥","")),Q25*S25) -> 3596 | W25: 已发货 | X25: =V25*T25 -> 3596 | Y25: =_xlfn.XLOOKUP(O25,产品信息表!$A$4:$A$15,产品信息表!$E$4:$E$15) -> 620 | Z25: =(X25-Y25*S25)/X25 -> 0.31034483 | AA25: =_xlfn.RANK.EQ(V25,V25:V226,0) -> 145
A26: DD-20260206-0024 | B26: 46059 | C26: =TEXT(SUBSTITUTE(B26,".","/"),"yyyy-mm-dd") -> 2026-02-06 | D26: KH005 | E26: =VLOOKUP(D26,客户信息表!A$3:H$23,2,0) -> 杭州云图信息 | F26: 杭州云图信息 | G26: =INDEX(客户信息表!$A$4:$H$23,MATCH(F26,客户信息表!$B$4:$B$23,0),1) -> KH005 | H26: =_xlfn.XLOOKUP(O26,产品信息表!$A$4:$A$15,产品信息表!$C$4:$C$15) -> 办公耗材 | I26: =DATE(MID(A26,4,4),MID(A26,8,2),MID(A26,10,2)) -> 46059 | J26: =RIGHT(A26,4) -> 0024 | K26: =VLOOKUP(D26,客户信息表!$A$3:$H$23,5,0) -> A | L26: 刘洋 | M26: 华东 | N26: =SUBSTITUTE(TRIM(M26),"区","") -> 华东 | O26: CP010 | P26: 签字笔盒装（12支） | Q26: 45 | R26: 103 | S26: =IF(ISBLANK(R26),U26/Q26,VALUE(R26)) -> 103 | T26: =VLOOKUP(S26,折扣阶梯!$A$3:$C$7,2,TRUE) -> 0.85 | U26: 4635 | V26: =IF(Q26*S26=VALUE(SUBSTITUTE(U26,"¥","")),VALUE(SUBSTITUTE(U26,"¥","")),Q26*S26) -> 4635 | W26: 已完成 | X26: =V26*T26 -> 3939.75 | Y26: =_xlfn.XLOOKUP(O26,产品信息表!$A$4:$A$15,产品信息表!$E$4:$E$15) -> 28 | Z26: =(X26-Y26*S26)/X26 -> 0.26797386 | AA26: =_xlfn.RANK.EQ(V26,V26:V227,0) -> 134
A27: DD-20260703-0152 | B27: 46206 | C27: =TEXT(SUBSTITUTE(B27,".","/"),"yyyy-mm-dd") -> 2026-07-03 | D27: KH009 | E27: =VLOOKUP(D27,客户信息表!A$3:H$23,2,0) -> 天津海河传媒 | F27: 天津海河传媒 | G27: =INDEX(客户信息表!$A$4:$H$23,MATCH(F27,客户信息表!$B$4:$B$23,0),1) -> KH009 | H27: =_xlfn.XLOOKUP(O27,产品信息表!$A$4:$A$15,产品信息表!$C$4:$C$15) -> 办公耗材 | I27: =DATE(MID(A27,4,4),MID(A27,8,2),MID(A27,10,2)) -> 46206 | J27: =RIGHT(A27,4) -> 0152 | K27: =VLOOKUP(D27,客户信息表!$A$3:$H$23,5,0) -> C | L27: 杨帆 | M27: 华北区 | N27: =SUBSTITUTE(TRIM(M27),"区","") -> 华北 | O27: CP009 | P27: 激光硒鼓 TonerMax 12A | Q27: 385 | R27: 97 | S27: =IF(ISBLANK(R27),U27/Q27,VALUE(R27)) -> 97 | T27: =VLOOKUP(S27,折扣阶梯!$A$3:$C$7,2,TRUE) -> 0.9 | U27: 37345 | V27: =IF(Q27*S27=VALUE(SUBSTITUTE(U27,"¥","")),VALUE(SUBSTITUTE(U27,"¥","")),Q27*S27) -> 37345 | W27: 已完成 | X27: =V27*T27 -> 33610.5 | Y27: =_xlfn.XLOOKUP(O27,产品信息表!$A$4:$A$15,产品信息表!$E$4:$E$15) -> 260 | Z27: =(X27-Y27*S27)/X27 -> 0.24963925 | AA27: =_xlfn.RANK.EQ(V27,V27:V228,0) -> 17
A28: DD-20260206-0025 | B28: 46059 | C28: =TEXT(SUBSTITUTE(B28,".","/"),"yyyy-mm-dd") -> 2026-02-06 | D28: KH011 | E28: =VLOOKUP(D28,客户信息表!A$3:H$23,2,0) -> 重庆山城办公设备 | F28: 重庆山城办公设备 | G28: =INDEX(客户信息表!$A$4:$H$23,MATCH(F28,客户信息表!$B$4:$B$23,0),1) -> KH011 | H28: =_xlfn.XLOOKUP(O28,产品信息表!$A$4:$A$15,产品信息表!$C$4:$C$15) -> 办公耗材 | I28: =DATE(MID(A28,4,4),MID(A28,8,2),MID(A28,10,2)) -> 46059 | J28: =RIGHT(A28,4) -> 0025 | K28: =VLOOKUP(D28,客户信息表!$A$3:$H$23,5,0) -> B | L28: 李娜 | M28: 西南 | N28: =SUBSTITUTE(TRIM(M28),"区","") -> 西南 | O28: CP009 | P28: 激光硒鼓 TonerMax 12A | Q28: 385 | R28: 26 | S28: =IF(ISBLANK(R28),U28/Q28,VALUE(R28)) -> 26 | T28: =VLOOKUP(S28,折扣阶梯!$A$3:$C$7,2,TRUE) -> 0.95 | U28: 10010 | V28: =IF(Q28*S28=VALUE(SUBSTITUTE(U28,"¥","")),VALUE(SUBSTITUTE(U28,"¥","")),Q28*S28) -> 10010 | W28: 待付款 | X28: =V28*T28 -> 9509.5 | Y28: =_xlfn.XLOOKUP(O28,产品信息表!$A$4:$A$15,产品信息表!$E$4:$E$15) -> 260 | Z28: =(X28-Y28*S28)/X28 -> 0.28913192 | AA28: =_xlfn.RANK.EQ(V28,V28:V229,0) -> 94
A29: DD-20260208-0026 | B29: 46061 | C29: =TEXT(SUBSTITUTE(B29,".","/"),"yyyy-mm-dd") -> 2026-02-08 | D29: KH002 | E29: =VLOOKUP(D29,客户信息表!A$3:H$23,2,0) -> 上海锦程贸易 | F29: 上海锦程贸易 | G29: =INDEX(客户信息表!$A$4:$H$23,MATCH(F29,客户信息表!$B$4:$B$23,0),1) -> KH002 | H29: =_xlfn.XLOOKUP(O29,产品信息表!$A$4:$A$15,产品信息表!$C$4:$C$15) -> 电子数码 | I29: =DATE(MID(A29,4,4),MID(A29,8,2),MID(A29,10,2)) -> 46061 | J29: =RIGHT(A29,4) -> 0026 | K29: =VLOOKUP(D29,客户信息表!$A$3:$H$23,5,0) -> B | L29: 张伟 | M29: 华东 | N29: =SUBSTITUTE(TRIM(M29),"区","") -> 华东 | O29: CP007 | P29: 无线键鼠套装 KeyFree 2.0 | Q29: 299 | R29: 2 | S29: =IF(ISBLANK(R29),U29/Q29,VALUE(R29)) -> 2 | T29: =VLOOKUP(S29,折扣阶梯!$A$3:$C$7,2,TRUE) -> 1 | U29: 598 | V29: =IF(Q29*S29=VALUE(SUBSTITUTE(U29,"¥","")),VALUE(SUBSTITUTE(U29,"¥","")),Q29*S29) -> 598 | W29: 已发货 | X29: =V29*T29 -> 598 | Y29: =_xlfn.XLOOKUP(O29,产品信息表!$A$4:$A$15,产品信息表!$E$4:$E$15) -> 190 | Z29: =(X29-Y29*S29)/X29 -> 0.36454849 | AA29: =_xlfn.RANK.EQ(V29,V29:V230,0) -> 173
A30: DD-20260216-0027 | B30: 46069 | C30: =TEXT(SUBSTITUTE(B30,".","/"),"yyyy-mm-dd") -> 2026-02-16 | D30: KH014 | E30: =VLOOKUP(D30,客户信息表!A$3:H$23,2,0) -> 宁波海港实业 | F30: 宁波海港实业 | G30: =INDEX(客户信息表!$A$4:$H$23,MATCH(F30,客户信息表!$B$4:$B$23,0),1) -> KH014 | H30: =_xlfn.XLOOKUP(O30,产品信息表!$A$4:$A$15,产品信息表!$C$4:$C$15) -> 电子数码 | I30: =DATE(MID(A30,4,4),MID(A30,8,2),MID(A30,10,2)) -> 46069 | J30: =RIGHT(A30,4) -> 0027 | K30: =VLOOKUP(D30,客户信息表!$A$3:$H$23,5,0) -> B | L30: 李娜 | M30: 华东区 | N30: =SUBSTITUTE(TRIM(M30),"区","") -> 华东 | O30: CP004 | P30: 笔记本电脑 TechBook 14 | Q30: 5699 | R30: 11 | S30: =IF(ISBLANK(R30),U30/Q30,VALUE(R30)) -> 11 | T30: =VLOOKUP(S30,折扣阶梯!$A$3:$C$7,2,TRUE) -> 0.95 | U30: ¥62,689.00 | V30: =IF(Q30*S30=VALUE(SUBSTITUTE(U30,"¥","")),VALUE(SUBSTITUTE(U30,"¥","")),Q30*S30) -> 62689 | W30: 已完成 | X30: =V30*T30 -> 59554.55 | Y30: =_xlfn.XLOOKUP(O30,产品信息表!$A$4:$A$15,产品信息表!$E$4:$E$15) -> 4800 | Z30: =(X30-Y30*S30)/X30 -> 0.11341787 | AA30: =_xlfn.RANK.EQ(V30,V30:V231,0) -> 4
A31: DD-20260221-0028 | B31: 2026.2.21 | C31: =TEXT(SUBSTITUTE(B31,".","/"),"yyyy-mm-dd") -> 2026-02-21 | D31: KH005 | E31: =VLOOKUP(D31,客户信息表!A$3:H$23,2,0) -> 杭州云图信息 | F31: 杭州云图信息 | G31: =INDEX(客户信息表!$A$4:$H$23,MATCH(F31,客户信息表!$B$4:$B$23,0),1) -> KH005 | H31: =_xlfn.XLOOKUP(O31,产品信息表!$A$4:$A$15,产品信息表!$C$4:$C$15) -> 软件服务 | I31: =DATE(MID(A31,4,4),MID(A31,8,2),MID(A31,10,2)) -> 46074 | J31: =RIGHT(A31,4) -> 0028 | K31: =VLOOKUP(D31,客户信息表!$A$3:$H$23,5,0) -> A | L31: 杨帆 | M31: 华东 | N31: =SUBSTITUTE(TRIM(M31),"区","") -> 华东 | O31: CP011 | P31: 办公软件年费授权 | Q31: 699 | R31: 20 | S31: =IF(ISBLANK(R31),U31/Q31,VALUE(R31)) -> 20 | T31: =VLOOKUP(S31,折扣阶梯!$A$3:$C$7,2,TRUE) -> 0.95 | U31: 13980 | V31: =IF(Q31*S31=VALUE(SUBSTITUTE(U31,"¥","")),VALUE(SUBSTITUTE(U31,"¥","")),Q31*S31) -> 13980 | W31: 已完成 | X31: =V31*T31 -> 13281 | Y31: =_xlfn.XLOOKUP(O31,产品信息表!$A$4:$A$15,产品信息表!$E$4:$E$15) -> 300 | Z31: =(X31-Y31*S31)/X31 -> 0.54822679 | AA31: =_xlfn.RANK.EQ(V31,V31:V232,0) -> 76
A32: DD-20260221-0029 | B32: 46074 | C32: =TEXT(SUBSTITUTE(B32,".","/"),"yyyy-mm-dd") -> 2026-02-21 | D32: KH005 | E32: =VLOOKUP(D32,客户信息表!A$3:H$23,2,0) -> 杭州云图信息 | F32: 杭州云图信息 | G32: =INDEX(客户信息表!$A$4:$H$23,MATCH(F32,客户信息表!$B$4:$B$23,0),1) -> KH005 | H32: =_xlfn.XLOOKUP(O32,产品信息表!$A$4:$A$15,产品信息表!$C$4:$C$15) -> 办公设备 | I32: =DATE(MID(A32,4,4),MID(A32,8,2),MID(A32,10,2)) -> 46074 | J32: =RIGHT(A32,4) -> 0029 | K32: =VLOOKUP(D32,客户信息表!$A$3:$H$23,5,0) -> A | L32: 赵磊 | M32: 华东 | N32: =SUBSTITUTE(TRIM(M32),"区","") -> 华东 | O32: CP001 | P32: 激光打印机 ProLaser 200 | Q32: 2499 | R32: 5 | S32: =IF(ISBLANK(R32),U32/Q32,VALUE(R32)) -> 5 | T32: =VLOOKUP(S32,折扣阶梯!$A$3:$C$7,2,TRUE) -> 1 | U32: 12495 | V32: =IF(Q32*S32=VALUE(SUBSTITUTE(U32,"¥","")),VALUE(SUBSTITUTE(U32,"¥","")),Q32*S32) -> 12495 | W32: 已取消 | X32: =V32*T32 -> 12495 | Y32: =_xlfn.XLOOKUP(O32,产品信息表!$A$4:$A$15,产品信息表!$E$4:$E$15) -> 1850 | Z32: =(X32-Y32*S32)/X32 -> 0.25970388 | AA32: =_xlfn.RANK.EQ(V32,V32:V233,0) -> 83
A33: DD-20260512-0102 | B33: 46154 | C33: =TEXT(SUBSTITUTE(B33,".","/"),"yyyy-mm-dd") -> 2026-05-12 | D33: KH014 | E33: =VLOOKUP(D33,客户信息表!A$3:H$23,2,0) -> 宁波海港实业 | F33: 宁波海港实业 | G33: =INDEX(客户信息表!$A$4:$H$23,MATCH(F33,客户信息表!$B$4:$B$23,0),1) -> KH014 | H33: =_xlfn.XLOOKUP(O33,产品信息表!$A$4:$A$15,产品信息表!$C$4:$C$15) -> 电子数码 | I33: =DATE(MID(A33,4,4),MID(A33,8,2),MID(A33,10,2)) -> 46154 | J33: =RIGHT(A33,4) -> 0102 | K33: =VLOOKUP(D33,客户信息表!$A$3:$H$23,5,0) -> B | L33: 王强 | M33: 华东 | N33: =SUBSTITUTE(TRIM(M33),"区","") -> 华东 | O33: CP004 | P33: 笔记本电脑 TechBook 14 | Q33: 5699 | R33: 13 | S33: =IF(ISBLANK(R33),U33/Q33,VALUE(R33)) -> 13 | T33: =VLOOKUP(S33,折扣阶梯!$A$3:$C$7,2,TRUE) -> 0.95 | U33: 74087 | V33: =IF(Q33*S33=VALUE(SUBSTITUTE(U33,"¥","")),VALUE(SUBSTITUTE(U33,"¥","")),Q33*S33) -> 74087 | W33: 已发货 | X33: =V33*T33 -> 70382.65 | Y33: =_xlfn.XLOOKUP(O33,产品信息表!$A$4:$A$15,产品信息表!$E$4:$E$15) -> 4800 | Z33: =(X33-Y33*S33)/X33 -> 0.11341787 | AA33: =_xlfn.RANK.EQ(V33,V33:V234,0) -> 1
A34: DD-20260223-0030 | B34: 46076 | C34: =TEXT(SUBSTITUTE(B34,".","/"),"yyyy-mm-dd") -> 2026-02-23 | D34: KH001 | E34: =VLOOKUP(D34,客户信息表!A$3:H$23,2,0) -> 北京华信科技 | F34: 北京华信科技 | G34: =INDEX(客户信息表!$A$4:$H$23,MATCH(F34,客户信息表!$B$4:$B$23,0),1) -> KH001 | H34: =_xlfn.XLOOKUP(O34,产品信息表!$A$4:$A$15,产品信息表!$C$4:$C$15) -> 电子数码 | I34: =DATE(MID(A34,4,4),MID(A34,8,2),MID(A34,10,2)) -> 46076 | J34: =RIGHT(A34,4) -> 0030 | K34: =VLOOKUP(D34,客户信息表!$A$3:$H$23,5,0) -> A | L34: 李娜 | M34: 华北 | N34: =SUBSTITUTE(TRIM(M34),"区","") -> 华北 | O34: CP004 | P34: 笔记本电脑 TechBook 14 | Q34: 5699 | R34: 5 | S34: =IF(ISBLANK(R34),U34/Q34,VALUE(R34)) -> 5 | T34: =VLOOKUP(S34,折扣阶梯!$A$3:$C$7,2,TRUE) -> 1 | U34: 28495 | V34: =IF(Q34*S34=VALUE(SUBSTITUTE(U34,"¥","")),VALUE(SUBSTITUTE(U34,"¥","")),Q34*S34) -> 28495 | W34: 已完成 | X34: =V34*T34 -> 28495 | Y34: =_xlfn.XLOOKUP(O34,产品信息表!$A$4:$A$15,产品信息表!$E$4:$E$15) -> 4800 | Z34: =(X34-Y34*S34)/X34 -> 0.15774697 | AA34: =_xlfn.RANK.EQ(V34,V34:V235,0) -> 23
A35: DD-20260227-0031 | B35: 46080 | C35: =TEXT(SUBSTITUTE(B35,".","/"),"yyyy-mm-dd") -> 2026-02-27 | D35: KH011 | E35: =VLOOKUP(D35,客户信息表!A$3:H$23,2,0) -> 重庆山城办公设备 | F35: 重庆山城办公设备 | G35: =INDEX(客户信息表!$A$4:$H$23,MATCH(F35,客户信息表!$B$4:$B$23,0),1) -> KH011 | H35: =_xlfn.XLOOKUP(O35,产品信息表!$A$4:$A$15,产品信息表!$C$4:$C$15) -> 软件服务 | I35: =DATE(MID(A35,4,4),MID(A35,8,2),MID(A35,10,2)) -> 46080 | J35: =RIGHT(A35,4) -> 0031 | K35: =VLOOKUP(D35,客户信息表!$A$3:$H$23,5,0) -> B | L35: 杨帆 | M35: 西南 | N35: =SUBSTITUTE(TRIM(M35),"区","") -> 西南 | O35: CP012 | P35: 云存储服务（1TB/年） | Q35: 599 | R35: 24 | S35: =IF(ISBLANK(R35),U35/Q35,VALUE(R35)) -> 24 | T35: =VLOOKUP(S35,折扣阶梯!$A$3:$C$7,2,TRUE) -> 0.95 | U35: 14376 | V35: =IF(Q35*S35=VALUE(SUBSTITUTE(U35,"¥","")),VALUE(SUBSTITUTE(U35,"¥","")),Q35*S35) -> 14376 | W35: 已发货 | X35: =V35*T35 -> 13657.2 | Y35: =_xlfn.XLOOKUP(O35,产品信息表!$A$4:$A$15,产品信息表!$E$4:$E$15) -> 250 | Z35: =(X35-Y35*S35)/X35 -> 0.56067129 | AA35: =_xlfn.RANK.EQ(V35,V35:V236,0) -> 71
A36: DD-20260308-0037 | B36: 46089 | C36: =TEXT(SUBSTITUTE(B36,".","/"),"yyyy-mm-dd") -> 2026-03-08 | D36: KH008 | E36: =VLOOKUP(D36,客户信息表!A$3:H$23,2,0) -> 南京紫金山软件园运营 | F36: 南京紫金山软件园运营 | G36: =INDEX(客户信息表!$A$4:$H$23,MATCH(F36,客户信息表!$B$4:$B$23,0),1) -> KH008 | H36: =_xlfn.XLOOKUP(O36,产品信息表!$A$4:$A$15,产品信息表!$C$4:$C$15) -> 办公耗材 | I36: =DATE(MID(A36,4,4),MID(A36,8,2),MID(A36,10,2)) -> 46089 | J36: =RIGHT(A36,4) -> 0037 | K36: =VLOOKUP(D36,客户信息表!$A$3:$H$23,5,0) -> C | L36: 杨帆 | M36: 华东 | N36: =SUBSTITUTE(TRIM(M36),"区","") -> 华东 | O36: CP008 | P36: A4复印纸（5包/箱） | Q36: 128 | R36: 12 | S36: =IF(ISBLANK(R36),U36/Q36,VALUE(R36)) -> 12 | T36: =VLOOKUP(S36,折扣阶梯!$A$3:$C$7,2,TRUE) -> 0.95 | U36: 1536 | V36: =IF(Q36*S36=VALUE(SUBSTITUTE(U36,"¥","")),VALUE(SUBSTITUTE(U36,"¥","")),Q36*S36) -> 1536 | W36: 已完成 | X36: =V36*T36 -> 1459.2 | Y36: =_xlfn.XLOOKUP(O36,产品信息表!$A$4:$A$15,产品信息表!$E$4:$E$15) -> 95 | Z36: =(X36-Y36*S36)/X36 -> 0.21875 | AA36: =_xlfn.RANK.EQ(V36,V36:V237,0) -> 158
A37: DD-20260227-0032 | B37: 2026/2/27 | C37: =TEXT(SUBSTITUTE(B37,".","/"),"yyyy-mm-dd") -> 2026-02-27 | D37: KH012 | E37: =VLOOKUP(D37,客户信息表!A$3:H$23,2,0) -> 长沙麓山科技 | F37: 长沙麓山科技 | G37: =INDEX(客户信息表!$A$4:$H$23,MATCH(F37,客户信息表!$B$4:$B$23,0),1) -> KH012 | H37: =_xlfn.XLOOKUP(O37,产品信息表!$A$4:$A$15,产品信息表!$C$4:$C$15) -> 办公耗材 | I37: =DATE(MID(A37,4,4),MID(A37,8,2),MID(A37,10,2)) -> 46080 | J37: =RIGHT(A37,4) -> 0032 | K37: =VLOOKUP(D37,客户信息表!$A$3:$H$23,5,0) -> B | L37: 张伟 | M37: 华中 | N37: =SUBSTITUTE(TRIM(M37),"区","") -> 华中 | O37: CP009 | P37: 激光硒鼓 TonerMax 12A | Q37: 385 | R37: 88 | S37: =IF(ISBLANK(R37),U37/Q37,VALUE(R37)) -> 88 | T37: =VLOOKUP(S37,折扣阶梯!$A$3:$C$7,2,TRUE) -> 0.9 | U37: 33880 | V37: =IF(Q37*S37=VALUE(SUBSTITUTE(U37,"¥","")),VALUE(SUBSTITUTE(U37,"¥","")),Q37*S37) -> 33880 | W37: 已取消 | X37: =V37*T37 -> 30492 | Y37: =_xlfn.XLOOKUP(O37,产品信息表!$A$4:$A$15,产品信息表!$E$4:$E$15) -> 260 | Z37: =(X37-Y37*S37)/X37 -> 0.24963925 | AA37: =_xlfn.RANK.EQ(V37,V37:V238,0) -> 19
A38: DD-20260228-0033 | B38: 46081 | C38: =TEXT(SUBSTITUTE(B38,".","/"),"yyyy-mm-dd") -> 2026-02-28 | D38: KH005 | E38: =VLOOKUP(D38,客户信息表!A$3:H$23,2,0) -> 杭州云图信息 | F38: 杭州云图信息 | G38: =INDEX(客户信息表!$A$4:$H$23,MATCH(F38,客户信息表!$B$4:$B$23,0),1) -> KH005 | H38: =_xlfn.XLOOKUP(O38,产品信息表!$A$4:$A$15,产品信息表!$C$4:$C$15) -> 电子数码 | I38: =DATE(MID(A38,4,4),MID(A38,8,2),MID(A38,10,2)) -> 46081 | J38: =RIGHT(A38,4) -> 0033 | K38: =VLOOKUP(D38,客户信息表!$A$3:$H$23,5,0) -> A | L38: 赵磊 | M38: 华东区 | N38: =SUBSTITUTE(TRIM(M38),"区","") -> 华东 | O38: CP004 | P38: 笔记本电脑 TechBook 14 | Q38: 5699 | R38: 8 | S38: =IF(ISBLANK(R38),U38/Q38,VALUE(R38)) -> 8 | T38: =VLOOKUP(S38,折扣阶梯!$A$3:$C$7,2,TRUE) -> 1 | U38: ¥45,592.00 | V38: =IF(Q38*S38=VALUE(SUBSTITUTE(U38,"¥","")),VALUE(SUBSTITUTE(U38,"¥","")),Q38*S38) -> 45592 | W38: 已取消 | X38: =V38*T38 -> 45592 | Y38: =_xlfn.XLOOKUP(O38,产品信息表!$A$4:$A$15,产品信息表!$E$4:$E$15) -> 4800 | Z38: =(X38-Y38*S38)/X38 -> 0.15774697 | AA38: =_xlfn.RANK.EQ(V38,V38:V239,0) -> 8
A39: DD-20260303-0034 | B39: 46084 | C39: =TEXT(SUBSTITUTE(B39,".","/"),"yyyy-mm-dd") -> 2026-03-03 | D39: KH017 | E39: =VLOOKUP(D39,客户信息表!A$3:H$23,2,0) -> 郑州中原物流 | F39: 郑州中原物流 | G39: =INDEX(客户信息表!$A$4:$H$23,MATCH(F39,客户信息表!$B$4:$B$23,0),1) -> KH017 | H39: =_xlfn.XLOOKUP(O39,产品信息表!$A$4:$A$15,产品信息表!$C$4:$C$15) -> 办公耗材 | I39: =DATE(MID(A39,4,4),MID(A39,8,2),MID(A39,10,2)) -> 46084 | J39: =RIGHT(A39,4) -> 0034 | K39: =VLOOKUP(D39,客户信息表!$A$3:$H$23,5,0) -> B | L39: 陈静 | M39: 华中 | N39: =SUBSTITUTE(TRIM(M39),"区","") -> 华中 | O39: CP009 | P39: 激光硒鼓 TonerMax 12A | Q39: 385 | R39: 120 | S39: =IF(ISBLANK(R39),U39/Q39,VALUE(R39)) -> 120 | T39: =VLOOKUP(S39,折扣阶梯!$A$3:$C$7,2,TRUE) -> 0.85 | U39: 46200 | V39: =IF(Q39*S39=VALUE(SUBSTITUTE(U39,"¥","")),VALUE(SUBSTITUTE(U39,"¥","")),Q39*S39) -> 46200 | W39: 已完成 | X39: =V39*T39 -> 39270 | Y39: =_xlfn.XLOOKUP(O39,产品信息表!$A$4:$A$15,产品信息表!$E$4:$E$15) -> 260 | Z39: =(X39-Y39*S39)/X39 -> 0.20550038 | AA39: =_xlfn.RANK.EQ(V39,V39:V240,0) -> 7
A40: DD-20260306-0035 | B40: 46087 | C40: =TEXT(SUBSTITUTE(B40,".","/"),"yyyy-mm-dd") -> 2026-03-06 | D40: KH019 | E40: =VLOOKUP(D40,客户信息表!A$3:H$23,2,0) -> 北京中关新材 | F40: 北京中关新材 | G40: =INDEX(客户信息表!$A$4:$H$23,MATCH(F40,客户信息表!$B$4:$B$23,0),1) -> KH019 | H40: =_xlfn.XLOOKUP(O40,产品信息表!$A$4:$A$15,产品信息表!$C$4:$C$15) -> 电子数码 | I40: =DATE(MID(A40,4,4),MID(A40,8,2),MID(A40,10,2)) -> 46087 | J40: =RIGHT(A40,4) -> 0035 | K40: =VLOOKUP(D40,客户信息表!$A$3:$H$23,5,0) -> B | L40: 赵磊 | M40: 华北 | N40: =SUBSTITUTE(TRIM(M40),"区","") -> 华北 | O40: CP006 | P40: 显示器 ViewMax 27 | Q40: 1299 | R40: 12 | S40: =IF(ISBLANK(R40),U40/Q40,VALUE(R40)) -> 12 | T40: =VLOOKUP(S40,折扣阶梯!$A$3:$C$7,2,TRUE) -> 0.95 | U40: 15588 | V40: =IF(Q40*S40=VALUE(SUBSTITUTE(U40,"¥","")),VALUE(SUBSTITUTE(U40,"¥","")),Q40*S40) -> 15588 | W40: 待付款 | X40: =V40*T40 -> 14808.6 | Y40: =_xlfn.XLOOKUP(O40,产品信息表!$A$4:$A$15,产品信息表!$E$4:$E$15) -> 950 | Z40: =(X40-Y40*S40)/X40 -> 0.23017706 | AA40: =_xlfn.RANK.EQ(V40,V40:V241,0) -> 58
A41: DD-20260306-0036 | B41: 46087 | C41: =TEXT(SUBSTITUTE(B41,".","/"),"yyyy-mm-dd") -> 2026-03-06 | D41: KH005 | E41: =VLOOKUP(D41,客户信息表!A$3:H$23,2,0) -> 杭州云图信息 | F41: 杭州云图信息 | G41: =INDEX(客户信息表!$A$4:$H$23,MATCH(F41,客户信息表!$B$4:$B$23,0),1) -> KH005 | H41: =_xlfn.XLOOKUP(O41,产品信息表!$A$4:$A$15,产品信息表!$C$4:$C$15) -> 电子数码 | I41: =DATE(MID(A41,4,4),MID(A41,8,2),MID(A41,10,2)) -> 46087 | J41: =RIGHT(A41,4) -> 0036 | K41: =VLOOKUP(D41,客户信息表!$A$3:$H$23,5,0) -> A | L41: 李娜 | M41: 华东 | N41: =SUBSTITUTE(TRIM(M41),"区","") -> 华东 | O41: CP006 | P41: 显示器 ViewMax 27 | Q41: 1299 | R41: 12 | S41: =IF(ISBLANK(R41),U41/Q41,VALUE(R41)) -> 12 | T41: =VLOOKUP(S41,折扣阶梯!$A$3:$C$7,2,TRUE) -> 0.95 | U41: 15588 | V41: =IF(Q41*S41=VALUE(SUBSTITUTE(U41,"¥","")),VALUE(SUBSTITUTE(U41,"¥","")),Q41*S41) -> 15588 | W41: 已完成 | X41: =V41*T41 -> 14808.6 | Y41: =_xlfn.XLOOKUP(O41,产品信息表!$A$4:$A$15,产品信息表!$E$4:$E$15) -> 950 | Z41: =(X41-Y41*S41)/X41 -> 0.23017706 | AA41: =_xlfn.RANK.EQ(V41,V41:V242,0) -> 58
A42: DD-20260308-0038 | B42: 46089 | C42: =TEXT(SUBSTITUTE(B42,".","/"),"yyyy-mm-dd") -> 2026-03-08 | D42: KH001 | E42: =VLOOKUP(D42,客户信息表!A$3:H$23,2,0) -> 北京华信科技 | F42: 北京华信科技 | G42: =INDEX(客户信息表!$A$4:$H$23,MATCH(F42,客户信息表!$B$4:$B$23,0),1) -> KH001 | H42: =_xlfn.XLOOKUP(O42,产品信息表!$A$4:$A$15,产品信息表!$C$4:$C$15) -> 软件服务 | I42: =DATE(MID(A42,4,4),MID(A42,8,2),MID(A42,10,2)) -> 46089 | J42: =RIGHT(A42,4) -> 0038 | K42: =VLOOKUP(D42,客户信息表!$A$3:$H$23,5,0) -> A | L42: 李娜 | M42: 华北 | N42: =SUBSTITUTE(TRIM(M42),"区","") -> 华北 | O42: CP012 | P42: 云存储服务（1TB/年） | Q42: 599 | R42: 12 | S42: =IF(ISBLANK(R42),U42/Q42,VALUE(R42)) -> 12 | T42: =VLOOKUP(S42,折扣阶梯!$A$3:$C$7,2,TRUE) -> 0.95 | U42: 7188 | V42: =IF(Q42*S42=VALUE(SUBSTITUTE(U42,"¥","")),VALUE(SUBSTITUTE(U42,"¥","")),Q42*S42) -> 7188 | W42: 已完成 | X42: =V42*T42 -> 6828.6 | Y42: =_xlfn.XLOOKUP(O42,产品信息表!$A$4:$A$15,产品信息表!$E$4:$E$15) -> 250 | Z42: =(X42-Y42*S42)/X42 -> 0.56067129 | AA42: =_xlfn.RANK.EQ(V42,V42:V243,0) -> 99
A43: DD-20260308-0039 | B43: 46089 | C43: =TEXT(SUBSTITUTE(B43,".","/"),"yyyy-mm-dd") -> 2026-03-08 | D43: KH002 | E43: =VLOOKUP(D43,客户信息表!A$3:H$23,2,0) -> 上海锦程贸易 | F43: 上海锦程贸易 | G43: =INDEX(客户信息表!$A$4:$H$23,MATCH(F43,客户信息表!$B$4:$B$23,0),1) -> KH002 | H43: =_xlfn.XLOOKUP(O43,产品信息表!$A$4:$A$15,产品信息表!$C$4:$C$15) -> 电子数码 | I43: =DATE(MID(A43,4,4),MID(A43,8,2),MID(A43,10,2)) -> 46089 | J43: =RIGHT(A43,4) -> 0039 | K43: =VLOOKUP(D43,客户信息表!$A$3:$H$23,5,0) -> B | L43: 陈静 | M43: 华东 | N43: =SUBSTITUTE(TRIM(M43),"区","") -> 华东 | O43: CP006 | P43: 显示器 ViewMax 27 | Q43: 1299 | R43: 11 | S43: =IF(ISBLANK(R43),U43/Q43,VALUE(R43)) -> 11 | T43: =VLOOKUP(S43,折扣阶梯!$A$3:$C$7,2,TRUE) -> 0.95 | U43: 14289 | V43: =IF(Q43*S43=VALUE(SUBSTITUTE(U43,"¥","")),VALUE(SUBSTITUTE(U43,"¥","")),Q43*S43) -> 14289 | W43: 已完成 | X43: =V43*T43 -> 13574.55 | Y43: =_xlfn.XLOOKUP(O43,产品信息表!$A$4:$A$15,产品信息表!$E$4:$E$15) -> 950 | Z43: =(X43-Y43*S43)/X43 -> 0.23017706 | AA43: =_xlfn.RANK.EQ(V43,V43:V244,0) -> 66
A44: DD-20260310-0040 | B44: 46091 | C44: =TEXT(SUBSTITUTE(B44,".","/"),"yyyy-mm-dd") -> 2026-03-10 | D44: KH011 | E44: =VLOOKUP(D44,客户信息表!A$3:H$23,2,0) -> 重庆山城办公设备 | F44: 重庆山城办公设备 | G44: =INDEX(客户信息表!$A$4:$H$23,MATCH(F44,客户信息表!$B$4:$B$23,0),1) -> KH011 | H44: =_xlfn.XLOOKUP(O44,产品信息表!$A$4:$A$15,产品信息表!$C$4:$C$15) -> 电子数码 | I44: =DATE(MID(A44,4,4),MID(A44,8,2),MID(A44,10,2)) -> 46091 | J44: =RIGHT(A44,4) -> 0040 | K44: =VLOOKUP(D44,客户信息表!$A$3:$H$23,5,0) -> B | L44: 赵磊 | M44: 西南 | N44: =SUBSTITUTE(TRIM(M44),"区","") -> 西南 | O44: CP006 | P44: 显示器 ViewMax 27 | Q44: 1299 | R44: 7 | S44: =IF(ISBLANK(R44),U44/Q44,VALUE(R44)) -> 7 | T44: =VLOOKUP(S44,折扣阶梯!$A$3:$C$7,2,TRUE) -> 1 | U44: 9093 | V44: =IF(Q44*S44=VALUE(SUBSTITUTE(U44,"¥","")),VALUE(SUBSTITUTE(U44,"¥","")),Q44*S44) -> 9093 | W44: 已完成 | X44: =V44*T44 -> 9093 | Y44: =_xlfn.XLOOKUP(O44,产品信息表!$A$4:$A$15,产品信息表!$E$4:$E$15) -> 950 | Z44: =(X44-Y44*S44)/X44 -> 0.26866821 | AA44: =_xlfn.RANK.EQ(V44,V44:V245,0) -> 87
A45: DD-20260310-0041 | B45: 46091 | C45: =TEXT(SUBSTITUTE(B45,".","/"),"yyyy-mm-dd") -> 2026-03-10 | D45: KH008 | E45: =VLOOKUP(D45,客户信息表!A$3:H$23,2,0) -> 南京紫金山软件园运营 | F45: 南京紫金山软件园运营 | G45: =INDEX(客户信息表!$A$4:$H$23,MATCH(F45,客户信息表!$B$4:$B$23,0),1) -> KH008 | H45: =_xlfn.XLOOKUP(O45,产品信息表!$A$4:$A$15,产品信息表!$C$4:$C$15) -> 电子数码 | I45: =DATE(MID(A45,4,4),MID(A45,8,2),MID(A45,10,2)) -> 46091 | J45: =RIGHT(A45,4) -> 0041 | K45: =VLOOKUP(D45,客户信息表!$A$3:$H$23,5,0) -> C | L45: 王强 | M45: 华东 | N45: =SUBSTITUTE(TRIM(M45),"区","") -> 华东 | O45: CP004 | P45: 笔记本电脑 TechBook 14 | Q45: 5699 | R45: 3 | S45: =IF(ISBLANK(R45),U45/Q45,VALUE(R45)) -> 3 | T45: =VLOOKUP(S45,折扣阶梯!$A$3:$C$7,2,TRUE) -> 1 | U45: 17097 | V45: =IF(Q45*S45=VALUE(SUBSTITUTE(U45,"¥","")),VALUE(SUBSTITUTE(U45,"¥","")),Q45*S45) -> 17097 | W45: 已完成 | X45: =V45*T45 -> 17097 | Y45: =_xlfn.XLOOKUP(O45,产品信息表!$A$4:$A$15,产品信息表!$E$4:$E$15) -> 4800 | Z45: =(X45-Y45*S45)/X45 -> 0.15774697 | AA45: =_xlfn.RANK.EQ(V45,V45:V246,0) -> 56
A46: DD-20260315-0042 | B46: 46096 | C46: =TEXT(SUBSTITUTE(B46,".","/"),"yyyy-mm-dd") -> 2026-03-15 | D46: KH013 | E46: =VLOOKUP(D46,客户信息表!A$3:H$23,2,0) -> 石家庄振华商贸 | F46: 石家庄振华商贸 | G46: =INDEX(客户信息表!$A$4:$H$23,MATCH(F46,客户信息表!$B$4:$B$23,0),1) -> KH013 | H46: =_xlfn.XLOOKUP(O46,产品信息表!$A$4:$A$15,产品信息表!$C$4:$C$15) -> 软件服务 | I46: =DATE(MID(A46,4,4),MID(A46,8,2),MID(A46,10,2)) -> 46096 | J46: =RIGHT(A46,4) -> 0042 | K46: =VLOOKUP(D46,客户信息表!$A$3:$H$23,5,0) -> C | L46: 赵磊 | M46: 华北 | N46: =SUBSTITUTE(TRIM(M46),"区","") -> 华北 | O46: CP012 | P46: 云存储服务（1TB/年） | Q46: 599 | R46: 37 | S46: =IF(ISBLANK(R46),U46/Q46,VALUE(R46)) -> 37 | T46: =VLOOKUP(S46,折扣阶梯!$A$3:$C$7,2,TRUE) -> 0.95 | U46: 22163 | V46: =IF(Q46*S46=VALUE(SUBSTITUTE(U46,"¥","")),VALUE(SUBSTITUTE(U46,"¥","")),Q46*S46) -> 22163 | W46: 待付款 | X46: =V46*T46 -> 21054.85 | Y46: =_xlfn.XLOOKUP(O46,产品信息表!$A$4:$A$15,产品信息表!$E$4:$E$15) -> 250 | Z46: =(X46-Y46*S46)/X46 -> 0.56067129 | AA46: =_xlfn.RANK.EQ(V46,V46:V247,0) -> 38
A47: DD-20260315-0043 | B47: 46096 | C47: =TEXT(SUBSTITUTE(B47,".","/"),"yyyy-mm-dd") -> 2026-03-15 | D47: KH015 | E47: =VLOOKUP(D47,客户信息表!A$3:H$23,2,0) -> 佛山美的家电商贸 | F47: 佛山美的家电商贸 | G47: =INDEX(客户信息表!$A$4:$H$23,MATCH(F47,客户信息表!$B$4:$B$23,0),1) -> KH015 | H47: =_xlfn.XLOOKUP(O47,产品信息表!$A$4:$A$15,产品信息表!$C$4:$C$15) -> 电子数码 | I47: =DATE(MID(A47,4,4),MID(A47,8,2),MID(A47,10,2)) -> 46096 | J47: =RIGHT(A47,4) -> 0043 | K47: =VLOOKUP(D47,客户信息表!$A$3:$H$23,5,0) -> A | L47: 陈静 | M47: 华南 | N47: =SUBSTITUTE(TRIM(M47),"区","") -> 华南 | O47: CP004 | P47: 笔记本电脑 TechBook 14 | Q47: 5699 | R47: 1 | S47: =IF(ISBLANK(R47),U47/Q47,VALUE(R47)) -> 1 | T47: =VLOOKUP(S47,折扣阶梯!$A$3:$C$7,2,TRUE) -> 1 | U47: 5699 | V47: =IF(Q47*S47=VALUE(SUBSTITUTE(U47,"¥","")),VALUE(SUBSTITUTE(U47,"¥","")),Q47*S47) -> 5699 | W47: 已完成 | X47: =V47*T47 -> 5699 | Y47: =_xlfn.XLOOKUP(O47,产品信息表!$A$4:$A$15,产品信息表!$E$4:$E$15) -> 4800 | Z47: =(X47-Y47*S47)/X47 -> 0.15774697 | AA47: =_xlfn.RANK.EQ(V47,V47:V248,0) -> 106
A48: DD-20260316-0044 | B48: 46097 | C48: =TEXT(SUBSTITUTE(B48,".","/"),"yyyy-mm-dd") -> 2026-03-16 | D48: KH008 | E48: =VLOOKUP(D48,客户信息表!A$3:H$23,2,0) -> 南京紫金山软件园运营 | F48: 南京紫金山软件园运营 | G48: =INDEX(客户信息表!$A$4:$H$23,MATCH(F48,客户信息表!$B$4:$B$23,0),1) -> KH008 | H48: =_xlfn.XLOOKUP(O48,产品信息表!$A$4:$A$15,产品信息表!$C$4:$C$15) -> 软件服务 | I48: =DATE(MID(A48,4,4),MID(A48,8,2),MID(A48,10,2)) -> 46097 | J48: =RIGHT(A48,4) -> 0044 | K48: =VLOOKUP(D48,客户信息表!$A$3:$H$23,5,0) -> C | L48: 李娜 | M48: 华东 | N48: =SUBSTITUTE(TRIM(M48),"区","") -> 华东 | O48: CP012 | P48: 云存储服务（1TB/年） | Q48: 599 | R48: 10 | S48: =IF(ISBLANK(R48),U48/Q48,VALUE(R48)) -> 10 | T48: =VLOOKUP(S48,折扣阶梯!$A$3:$C$7,2,TRUE) -> 0.95 | U48: 5990 | V48: =IF(Q48*S48=VALUE(SUBSTITUTE(U48,"¥","")),VALUE(SUBSTITUTE(U48,"¥","")),Q48*S48) -> 5990 | W48: 待付款 | X48: =V48*T48 -> 5690.5 | Y48: =_xlfn.XLOOKUP(O48,产品信息表!$A$4:$A$15,产品信息表!$E$4:$E$15) -> 250 | Z48: =(X48-Y48*S48)/X48 -> 0.56067129 | AA48: =_xlfn.RANK.EQ(V48,V48:V249,0) -> 105
A49: DD-20260316-0045 | B49: 46097 | C49: =TEXT(SUBSTITUTE(B49,".","/"),"yyyy-mm-dd") -> 2026-03-16 | D49: KH010 | E49: =VLOOKUP(D49,客户信息表!A$3:H$23,2,0) -> 苏州创智科技 | F49: 苏州创智科技 | G49: =INDEX(客户信息表!$A$4:$H$23,MATCH(F49,客户信息表!$B$4:$B$23,0),1) -> KH010 | H49: =_xlfn.XLOOKUP(O49,产品信息表!$A$4:$A$15,产品信息表!$C$4:$C$15) -> 办公耗材 | I49: =DATE(MID(A49,4,4),MID(A49,8,2),MID(A49,10,2)) -> 46097 | J49: =RIGHT(A49,4) -> 0045 | K49: =VLOOKUP(D49,客户信息表!$A$3:$H$23,5,0) -> A | L49: 陈静 | M49: 华东 | N49: =SUBSTITUTE(TRIM(M49),"区","") -> 华东 | O49: CP009 | P49: 激光硒鼓 TonerMax 12A | Q49: 385 | R49: 115 | S49: =IF(ISBLANK(R49),U49/Q49,VALUE(R49)) -> 115 | T49: =VLOOKUP(S49,折扣阶梯!$A$3:$C$7,2,TRUE) -> 0.85 | U49: 44275 | V49: =IF(Q49*S49=VALUE(SUBSTITUTE(U49,"¥","")),VALUE(SUBSTITUTE(U49,"¥","")),Q49*S49) -> 44275 | W49: 已完成 | X49: =V49*T49 -> 37633.75 | Y49: =_xlfn.XLOOKUP(O49,产品信息表!$A$4:$A$15,产品信息表!$E$4:$E$15) -> 260 | Z49: =(X49-Y49*S49)/X49 -> 0.20550038 | AA49: =_xlfn.RANK.EQ(V49,V49:V250,0) -> 7
A50: DD-20260317-0046 | B50: 46098 | C50: =TEXT(SUBSTITUTE(B50,".","/"),"yyyy-mm-dd") -> 2026-03-17 | D50: KH010 | E50: =VLOOKUP(D50,客户信息表!A$3:H$23,2,0) -> 苏州创智科技 | F50: 苏州创智科技 | G50: =INDEX(客户信息表!$A$4:$H$23,MATCH(F50,客户信息表!$B$4:$B$23,0),1) -> KH010 | H50: =_xlfn.XLOOKUP(O50,产品信息表!$A$4:$A$15,产品信息表!$C$4:$C$15) -> 办公耗材 | I50: =DATE(MID(A50,4,4),MID(A50,8,2),MID(A50,10,2)) -> 46098 | J50: =RIGHT(A50,4) -> 0046 | K50: =VLOOKUP(D50,客户信息表!$A$3:$H$23,5,0) -> A | L50: 张伟 | M50: 华东 | N50: =SUBSTITUTE(TRIM(M50),"区","") -> 华东 | O50: CP010 | P50: 签字笔盒装（12支） | Q50: 45 | R50: 17 | S50: =IF(ISBLANK(R50),U50/Q50,VALUE(R50)) -> 17 | T50: =VLOOKUP(S50,折扣阶梯!$A$3:$C$7,2,TRUE) -> 0.95 | U50: ¥765.00 | V50: =IF(Q50*S50=VALUE(SUBSTITUTE(U50,"¥","")),VALUE(SUBSTITUTE(U50,"¥","")),Q50*S50) -> 765 | W50: 已发货 | X50: =V50*T50 -> 726.75 | Y50: =_xlfn.XLOOKUP(O50,产品信息表!$A$4:$A$15,产品信息表!$E$4:$E$15) -> 28 | Z50: =(X50-Y50*S50)/X50 -> 0.34502924 | AA50: =_xlfn.RANK.EQ(V50,V50:V251,0) -> 151
A51: DD-20260320-0047 | B51: 46101 | C51: =TEXT(SUBSTITUTE(B51,".","/"),"yyyy-mm-dd") -> 2026-03-20 | D51: KH004 | E51: =VLOOKUP(D51,客户信息表!A$3:H$23,2,0) -> 深圳蓝鲸网络 | F51: 深圳蓝鲸网络 | G51: =INDEX(客户信息表!$A$4:$H$23,MATCH(F51,客户信息表!$B$4:$B$23,0),1) -> KH004 | H51: =_xlfn.XLOOKUP(O51,产品信息表!$A$4:$A$15,产品信息表!$C$4:$C$15) -> 办公设备 | I51: =DATE(MID(A51,4,4),MID(A51,8,2),MID(A51,10,2)) -> 46101 | J51: =RIGHT(A51,4) -> 0047 | K51: =VLOOKUP(D51,客户信息表!$A$3:$H$23,5,0) -> B | L51: 王强 | M51: 华南 | N51: =SUBSTITUTE(TRIM(M51),"区","") -> 华南 | O51: CP001 | P51: 激光打印机 ProLaser 200 | Q51: 2499 | R51: 4 | S51: =IF(ISBLANK(R51),U51/Q51,VALUE(R51)) -> 4 | T51: =VLOOKUP(S51,折扣阶梯!$A$3:$C$7,2,TRUE) -> 1 | U51: 9996 | V51: =IF(Q51*S51=VALUE(SUBSTITUTE(U51,"¥","")),VALUE(SUBSTITUTE(U51,"¥","")),Q51*S51) -> 9996 | W51: 已取消 | X51: =V51*T51 -> 9996 | Y51: =_xlfn.XLOOKUP(O51,产品信息表!$A$4:$A$15,产品信息表!$E$4:$E$15) -> 1850 | Z51: =(X51-Y51*S51)/X51 -> 0.25970388 | AA51: =_xlfn.RANK.EQ(V51,V51:V252,0) -> 80
A52: DD-20260321-0048 | B52: 46102 | C52: =TEXT(SUBSTITUTE(B52,".","/"),"yyyy-mm-dd") -> 2026-03-21 | D52: KH018 | E52: =VLOOKUP(D52,客户信息表!A$3:H$23,2,0) -> 厦门鹭岛文创 | F52: 厦门鹭岛文创 | G52: =INDEX(客户信息表!$A$4:$H$23,MATCH(F52,客户信息表!$B$4:$B$23,0),1) -> KH018 | H52: =_xlfn.XLOOKUP(O52,产品信息表!$A$4:$A$15,产品信息表!$C$4:$C$15) -> 电子数码 | I52: =DATE(MID(A52,4,4),MID(A52,8,2),MID(A52,10,2)) -> 46102 | J52: =RIGHT(A52,4) -> 0048 | K52: =VLOOKUP(D52,客户信息表!$A$3:$H$23,5,0) -> C | L52: 刘洋 | M52: 华南区 | N52: =SUBSTITUTE(TRIM(M52),"区","") -> 华南 | O52: CP007 | P52: 无线键鼠套装 KeyFree 2.0 | Q52: 299 | R52: 6 | S52: =IF(ISBLANK(R52),U52/Q52,VALUE(R52)) -> 6 | T52: =VLOOKUP(S52,折扣阶梯!$A$3:$C$7,2,TRUE) -> 1 | U52: 1794 | V52: =IF(Q52*S52=VALUE(SUBSTITUTE(U52,"¥","")),VALUE(SUBSTITUTE(U52,"¥","")),Q52*S52) -> 1794 | W52: 已完成 | X52: =V52*T52 -> 1794 | Y52: =_xlfn.XLOOKUP(O52,产品信息表!$A$4:$A$15,产品信息表!$E$4:$E$15) -> 190 | Z52: =(X52-Y52*S52)/X52 -> 0.36454849 | AA52: =_xlfn.RANK.EQ(V52,V52:V253,0) -> 142
A53: DD-20260322-0049 | B53: 46103 | C53: =TEXT(SUBSTITUTE(B53,".","/"),"yyyy-mm-dd") -> 2026-03-22 | D53: KH005 | E53: =VLOOKUP(D53,客户信息表!A$3:H$23,2,0) -> 杭州云图信息 | F53: 杭州云图信息 | G53: =INDEX(客户信息表!$A$4:$H$23,MATCH(F53,客户信息表!$B$4:$B$23,0),1) -> KH005 | H53: =_xlfn.XLOOKUP(O53,产品信息表!$A$4:$A$15,产品信息表!$C$4:$C$15) -> 软件服务 | I53: =DATE(MID(A53,4,4),MID(A53,8,2),MID(A53,10,2)) -> 46103 | J53: =RIGHT(A53,4) -> 0049 | K53: =VLOOKUP(D53,客户信息表!$A$3:$H$23,5,0) -> A | L53: 杨帆 | M53: 华东 | N53: =SUBSTITUTE(TRIM(M53),"区","") -> 华东 | O53: CP011 | P53: 办公软件年费授权 | Q53: 699 | R53: 25 | S53: =IF(ISBLANK(R53),U53/Q53,VALUE(R53)) -> 25 | T53: =VLOOKUP(S53,折扣阶梯!$A$3:$C$7,2,TRUE) -> 0.95 | U53: 17475 | V53: =IF(Q53*S53=VALUE(SUBSTITUTE(U53,"¥","")),VALUE(SUBSTITUTE(U53,"¥","")),Q53*S53) -> 17475 | W53: 已完成 | X53: =V53*T53 -> 16601.25 | Y53: =_xlfn.XLOOKUP(O53,产品信息表!$A$4:$A$15,产品信息表!$E$4:$E$15) -> 300 | Z53: =(X53-Y53*S53)/X53 -> 0.54822679 | AA53: =_xlfn.RANK.EQ(V53,V53:V254,0) -> 53
A54: DD-20260323-0050 | B54: 46104 | C54: =TEXT(SUBSTITUTE(B54,".","/"),"yyyy-mm-dd") -> 2026-03-23 | D54: KH009 | E54: =VLOOKUP(D54,客户信息表!A$3:H$23,2,0) -> 天津海河传媒 | F54: 天津海河传媒 | G54: =INDEX(客户信息表!$A$4:$H$23,MATCH(F54,客户信息表!$B$4:$B$23,0),1) -> KH009 | H54: =_xlfn.XLOOKUP(O54,产品信息表!$A$4:$A$15,产品信息表!$C$4:$C$15) -> 软件服务 | I54: =DATE(MID(A54,4,4),MID(A54,8,2),MID(A54,10,2)) -> 46104 | J54: =RIGHT(A54,4) -> 0050 | K54: =VLOOKUP(D54,客户信息表!$A$3:$H$23,5,0) -> C | L54: 陈静 | M54: 华北 | N54: =SUBSTITUTE(TRIM(M54),"区","") -> 华北 | O54: CP011 | P54: 办公软件年费授权 | Q54: 699 | R54: 39 | S54: =IF(ISBLANK(R54),U54/Q54,VALUE(R54)) -> 39 | T54: =VLOOKUP(S54,折扣阶梯!$A$3:$C$7,2,TRUE) -> 0.95 | U54: 27261 | V54: =IF(Q54*S54=VALUE(SUBSTITUTE(U54,"¥","")),VALUE(SUBSTITUTE(U54,"¥","")),Q54*S54) -> 27261 | W54: 已完成 | X54: =V54*T54 -> 25897.95 | Y54: =_xlfn.XLOOKUP(O54,产品信息表!$A$4:$A$15,产品信息表!$E$4:$E$15) -> 300 | Z54: =(X54-Y54*S54)/X54 -> 0.54822679 | AA54: =_xlfn.RANK.EQ(V54,V54:V255,0) -> 22
A55: DD-20260323-0051 | B55: 46104 | C55: =TEXT(SUBSTITUTE(B55,".","/"),"yyyy-mm-dd") -> 2026-03-23 | D55: KH012 | E55: =VLOOKUP(D55,客户信息表!A$3:H$23,2,0) -> 长沙麓山科技 | F55: 长沙麓山科技 | G55: =INDEX(客户信息表!$A$4:$H$23,MATCH(F55,客户信息表!$B$4:$B$23,0),1) -> KH012 | H55: =_xlfn.XLOOKUP(O55,产品信息表!$A$4:$A$15,产品信息表!$C$4:$C$15) -> 办公设备 | I55: =DATE(MID(A55,4,4),MID(A55,8,2),MID(A55,10,2)) -> 46104 | J55: =RIGHT(A55,4) -> 0051 | K55: =VLOOKUP(D55,客户信息表!$A$3:$H$23,5,0) -> B | L55: 杨帆 | M55: 华中 | N55: =SUBSTITUTE(TRIM(M55),"区","") -> 华中 | O55: CP003 | P55: 碎纸机 SafeCut S8 | Q55: 899 | R55: 1 | S55: =IF(ISBLANK(R55),U55/Q55,VALUE(R55)) -> 1 | T55: =VLOOKUP(S55,折扣阶梯!$A$3:$C$7,2,TRUE) -> 1 | U55: 899 | V55: =IF(Q55*S55=VALUE(SUBSTITUTE(U55,"¥","")),VALUE(SUBSTITUTE(U55,"¥","")),Q55*S55) -> 899 | W55: 待付款 | X55: =V55*T55 -> 899 | Y55: =_xlfn.XLOOKUP(O55,产品信息表!$A$4:$A$15,产品信息表!$E$4:$E$15) -> 620 | Z55: =(X55-Y55*S55)/X55 -> 0.31034483 | AA55: =_xlfn.RANK.EQ(V55,V55:V256,0) -> 145
A56: DD-20260329-0052 | B56: 46110 | C56: =TEXT(SUBSTITUTE(B56,".","/"),"yyyy-mm-dd") -> 2026-03-29 | D56: KH016 | E56: =VLOOKUP(D56,客户信息表!A$3:H$23,2,0) -> 昆明滇池科技 | F56: 昆明滇池科技 | G56: =INDEX(客户信息表!$A$4:$H$23,MATCH(F56,客户信息表!$B$4:$B$23,0),1) -> KH016 | H56: =_xlfn.XLOOKUP(O56,产品信息表!$A$4:$A$15,产品信息表!$C$4:$C$15) -> 办公耗材 | I56: =DATE(MID(A56,4,4),MID(A56,8,2),MID(A56,10,2)) -> 46110 | J56: =RIGHT(A56,4) -> 0052 | K56: =VLOOKUP(D56,客户信息表!$A$3:$H$23,5,0) -> C | L56: 张伟 | M56: 西南 | N56: =SUBSTITUTE(TRIM(M56),"区","") -> 西南 | O56: CP009 | P56: 激光硒鼓 TonerMax 12A | Q56: 385 | R56: 111 | S56: =IF(ISBLANK(R56),U56/Q56,VALUE(R56)) -> 111 | T56: =VLOOKUP(S56,折扣阶梯!$A$3:$C$7,2,TRUE) -> 0.85 | U56: 42735 | V56: =IF(Q56*S56=VALUE(SUBSTITUTE(U56,"¥","")),VALUE(SUBSTITUTE(U56,"¥","")),Q56*S56) -> 42735 | W56: 已发货 | X56: =V56*T56 -> 36324.75 | Y56: =_xlfn.XLOOKUP(O56,产品信息表!$A$4:$A$15,产品信息表!$E$4:$E$15) -> 260 | Z56: =(X56-Y56*S56)/X56 -> 0.20550038 | AA56: =_xlfn.RANK.EQ(V56,V56:V257,0) -> 7
A57: DD-20260331-0053 | B57: 46112 | C57: =TEXT(SUBSTITUTE(B57,".","/"),"yyyy-mm-dd") -> 2026-03-31 | D57: KH002 | E57: =VLOOKUP(D57,客户信息表!A$3:H$23,2,0) -> 上海锦程贸易 | F57: 上海锦程贸易 | G57: =INDEX(客户信息表!$A$4:$H$23,MATCH(F57,客户信息表!$B$4:$B$23,0),1) -> KH002 | H57: =_xlfn.XLOOKUP(O57,产品信息表!$A$4:$A$15,产品信息表!$C$4:$C$15) -> 电子数码 | I57: =DATE(MID(A57,4,4),MID(A57,8,2),MID(A57,10,2)) -> 46112 | J57: =RIGHT(A57,4) -> 0053 | K57: =VLOOKUP(D57,客户信息表!$A$3:$H$23,5,0) -> B | L57: 陈静 | M57: 华东 | N57: =SUBSTITUTE(TRIM(M57),"区","") -> 华东 | O57: CP006 | P57: 显示器 ViewMax 27 | Q57: 1299 | S57: =IF(ISBLANK(R57),U57/Q57,VALUE(R57)) -> 12 | T57: =VLOOKUP(S57,折扣阶梯!$A$3:$C$7,2,TRUE) -> 0.95 | U57: 15588 | V57: =IF(Q57*S57=VALUE(SUBSTITUTE(U57,"¥","")),VALUE(SUBSTITUTE(U57,"¥","")),Q57*S57) -> 15588 | W57: 已完成 | X57: =V57*T57 -> 14808.6 | Y57: =_xlfn.XLOOKUP(O57,产品信息表!$A$4:$A$15,产品信息表!$E$4:$E$15) -> 950 | Z57: =(X57-Y57*S57)/X57 -> 0.23017706 | AA57: =_xlfn.RANK.EQ(V57,V57:V258,0) -> 52
A58: DD-20260402-0054 | B58: 46114 | C58: =TEXT(SUBSTITUTE(B58,".","/"),"yyyy-mm-dd") -> 2026-04-02 | D58: KH015 | E58: =VLOOKUP(D58,客户信息表!A$3:H$23,2,0) -> 佛山美的家电商贸 | F58: 佛山美的家电商贸 | G58: =INDEX(客户信息表!$A$4:$H$23,MATCH(F58,客户信息表!$B$4:$B$23,0),1) -> KH015 | H58: =_xlfn.XLOOKUP(O58,产品信息表!$A$4:$A$15,产品信息表!$C$4:$C$15) -> 软件服务 | I58: =DATE(MID(A58,4,4),MID(A58,8,2),MID(A58,10,2)) -> 46114 | J58: =RIGHT(A58,4) -> 0054 | K58: =VLOOKUP(D58,客户信息表!$A$3:$H$23,5,0) -> A | L58: 刘洋 | M58: 华南 | N58: =SUBSTITUTE(TRIM(M58),"区","") -> 华南 | O58: CP012 | P58: 云存储服务（1TB/年） | Q58: 599 | R58: 3 | S58: =IF(ISBLANK(R58),U58/Q58,VALUE(R58)) -> 3 | T58: =VLOOKUP(S58,折扣阶梯!$A$3:$C$7,2,TRUE) -> 1 | U58: 1797 | V58: =IF(Q58*S58=VALUE(SUBSTITUTE(U58,"¥","")),VALUE(SUBSTITUTE(U58,"¥","")),Q58*S58) -> 1797 | W58: 待付款 | X58: =V58*T58 -> 1797 | Y58: =_xlfn.XLOOKUP(O58,产品信息表!$A$4:$A$15,产品信息表!$E$4:$E$15) -> 250 | Z58: =(X58-Y58*S58)/X58 -> 0.58263773 | AA58: =_xlfn.RANK.EQ(V58,V58:V259,0) -> 135
A59: DD-20260403-0055 | B59: 46115 | C59: =TEXT(SUBSTITUTE(B59,".","/"),"yyyy-mm-dd") -> 2026-04-03 | D59: KH014 | E59: =VLOOKUP(D59,客户信息表!A$3:H$23,2,0) -> 宁波海港实业 | F59: 宁波海港实业 | G59: =INDEX(客户信息表!$A$4:$H$23,MATCH(F59,客户信息表!$B$4:$B$23,0),1) -> KH014 | H59: =_xlfn.XLOOKUP(O59,产品信息表!$A$4:$A$15,产品信息表!$C$4:$C$15) -> 电子数码 | I59: =DATE(MID(A59,4,4),MID(A59,8,2),MID(A59,10,2)) -> 46115 | J59: =RIGHT(A59,4) -> 0055 | K59: =VLOOKUP(D59,客户信息表!$A$3:$H$23,5,0) -> B | L59: 赵磊 | M59: 华东 | N59: =SUBSTITUTE(TRIM(M59),"区","") -> 华东 | O59: CP006 | P59: 显示器 ViewMax 27 | Q59: 1299 | R59: 1 | S59: =IF(ISBLANK(R59),U59/Q59,VALUE(R59)) -> 1 | T59: =VLOOKUP(S59,折扣阶梯!$A$3:$C$7,2,TRUE) -> 1 | U59: 1299 | V59: =IF(Q59*S59=VALUE(SUBSTITUTE(U59,"¥","")),VALUE(SUBSTITUTE(U59,"¥","")),Q59*S59) -> 1299 | W59: 已完成 | X59: =V59*T59 -> 1299 | Y59: =_xlfn.XLOOKUP(O59,产品信息表!$A$4:$A$15,产品信息表!$E$4:$E$15) -> 950 | Z59: =(X59-Y59*S59)/X59 -> 0.26866821 | AA59: =_xlfn.RANK.EQ(V59,V59:V260,0) -> 139
A60: DD-20260404-0056 | B60: 46116 | C60: =TEXT(SUBSTITUTE(B60,".","/"),"yyyy-mm-dd") -> 2026-04-04 | D60: KH019 | E60: =VLOOKUP(D60,客户信息表!A$3:H$23,2,0) -> 北京中关新材 | F60: 北京中关新材 | G60: =INDEX(客户信息表!$A$4:$H$23,MATCH(F60,客户信息表!$B$4:$B$23,0),1) -> KH019 | H60: =_xlfn.XLOOKUP(O60,产品信息表!$A$4:$A$15,产品信息表!$C$4:$C$15) -> 办公耗材 | I60: =DATE(MID(A60,4,4),MID(A60,8,2),MID(A60,10,2)) -> 46116 | J60: =RIGHT(A60,4) -> 0056 | K60: =VLOOKUP(D60,客户信息表!$A$3:$H$23,5,0) -> B | L60: 王强 | M60: 华北 | N60: =SUBSTITUTE(TRIM(M60),"区","") -> 华北 | O60: CP008 | P60: A4复印纸（5包/箱） | Q60: 128 | S60: =IF(ISBLANK(R60),U60/Q60,VALUE(R60)) -> 92 | T60: =VLOOKUP(S60,折扣阶梯!$A$3:$C$7,2,TRUE) -> 0.9 | U60: 11776 | V60: =IF(Q60*S60=VALUE(SUBSTITUTE(U60,"¥","")),VALUE(SUBSTITUTE(U60,"¥","")),Q60*S60) -> 11776 | W60: 已取消 | X60: =V60*T60 -> 10598.4 | Y60: =_xlfn.XLOOKUP(O60,产品信息表!$A$4:$A$15,产品信息表!$E$4:$E$15) -> 95 | Z60: =(X60-Y60*S60)/X60 -> 0.17534722 | AA60: =_xlfn.RANK.EQ(V60,V60:V261,0) -> 69
A61: DD-20260405-0057 | B61: 46117 | C61: =TEXT(SUBSTITUTE(B61,".","/"),"yyyy-mm-dd") -> 2026-04-05 | D61: KH002 | E61: =VLOOKUP(D61,客户信息表!A$3:H$23,2,0) -> 上海锦程贸易 | F61: 上海锦程贸易 | G61: =INDEX(客户信息表!$A$4:$H$23,MATCH(F61,客户信息表!$B$4:$B$23,0),1) -> KH002 | H61: =_xlfn.XLOOKUP(O61,产品信息表!$A$4:$A$15,产品信息表!$C$4:$C$15) -> 办公设备 | I61: =DATE(MID(A61,4,4),MID(A61,8,2),MID(A61,10,2)) -> 46117 | J61: =RIGHT(A61,4) -> 0057 | K61: =VLOOKUP(D61,客户信息表!$A$3:$H$23,5,0) -> B | L61: 杨帆 | M61: 华东 | N61: =SUBSTITUTE(TRIM(M61),"区","") -> 华东 | O61: CP003 | P61: 碎纸机 SafeCut S8 | Q61: 899 | R61: 7 | S61: =IF(ISBLANK(R61),U61/Q61,VALUE(R61)) -> 7 | T61: =VLOOKUP(S61,折扣阶梯!$A$3:$C$7,2,TRUE) -> 1 | U61: 6293 | V61: =IF(Q61*S61=VALUE(SUBSTITUTE(U61,"¥","")),VALUE(SUBSTITUTE(U61,"¥","")),Q61*S61) -> 6293 | W61: 已完成 | X61: =V61*T61 -> 6293 | Y61: =_xlfn.XLOOKUP(O61,产品信息表!$A$4:$A$15,产品信息表!$E$4:$E$15) -> 620 | Z61: =(X61-Y61*S61)/X61 -> 0.31034483 | AA61: =_xlfn.RANK.EQ(V61,V61:V262,0) -> 94
A62: DD-20260405-0058 | B62: 46117 | C62: =TEXT(SUBSTITUTE(B62,".","/"),"yyyy-mm-dd") -> 2026-04-05 | D62: KH005 | E62: =VLOOKUP(D62,客户信息表!A$3:H$23,2,0) -> 杭州云图信息 | F62: 杭州云图信息 | G62: =INDEX(客户信息表!$A$4:$H$23,MATCH(F62,客户信息表!$B$4:$B$23,0),1) -> KH005 | H62: =_xlfn.XLOOKUP(O62,产品信息表!$A$4:$A$15,产品信息表!$C$4:$C$15) -> 办公耗材 | I62: =DATE(MID(A62,4,4),MID(A62,8,2),MID(A62,10,2)) -> 46117 | J62: =RIGHT(A62,4) -> 0058 | K62: =VLOOKUP(D62,客户信息表!$A$3:$H$23,5,0) -> A | L62: 刘洋 | M62: 华东 | N62: =SUBSTITUTE(TRIM(M62),"区","") -> 华东 | O62: CP010 | P62: 签字笔盒装（12支） | Q62: 45 | R62: 94 | S62: =IF(ISBLANK(R62),U62/Q62,VALUE(R62)) -> 94 | T62: =VLOOKUP(S62,折扣阶梯!$A$3:$C$7,2,TRUE) -> 0.9 | U62: 4230 | V62: =IF(Q62*S62=VALUE(SUBSTITUTE(U62,"¥","")),VALUE(SUBSTITUTE(U62,"¥","")),Q62*S62) -> 4230 | W62: 已完成 | X62: =V62*T62 -> 3807 | Y62: =_xlfn.XLOOKUP(O62,产品信息表!$A$4:$A$15,产品信息表!$E$4:$E$15) -> 28 | Z62: =(X62-Y62*S62)/X62 -> 0.30864198 | AA62: =_xlfn.RANK.EQ(V62,V62:V263,0) -> 110
A63: DD-20260407-0059 | B63: 46119 | C63: =TEXT(SUBSTITUTE(B63,".","/"),"yyyy-mm-dd") -> 2026-04-07 | D63: KH005 | E63: =VLOOKUP(D63,客户信息表!A$3:H$23,2,0) -> 杭州云图信息 | F63: 杭州云图信息 | G63: =INDEX(客户信息表!$A$4:$H$23,MATCH(F63,客户信息表!$B$4:$B$23,0),1) -> KH005 | H63: =_xlfn.XLOOKUP(O63,产品信息表!$A$4:$A$15,产品信息表!$C$4:$C$15) -> 办公耗材 | I63: =DATE(MID(A63,4,4),MID(A63,8,2),MID(A63,10,2)) -> 46119 | J63: =RIGHT(A63,4) -> 0059 | K63: =VLOOKUP(D63,客户信息表!$A$3:$H$23,5,0) -> A | L63: 王强 | M63: 华东 | N63: =SUBSTITUTE(TRIM(M63),"区","") -> 华东 | O63: CP008 | P63: A4复印纸（5包/箱） | Q63: 128 | R63: 55 | S63: =IF(ISBLANK(R63),U63/Q63,VALUE(R63)) -> 55 | T63: =VLOOKUP(S63,折扣阶梯!$A$3:$C$7,2,TRUE) -> 0.9 | U63: ¥7,040.00 | V63: =IF(Q63*S63=VALUE(SUBSTITUTE(U63,"¥","")),VALUE(SUBSTITUTE(U63,"¥","")),Q63*S63) -> 7040 | W63: 已取消 | X63: =V63*T63 -> 6336 | Y63: =_xlfn.XLOOKUP(O63,产品信息表!$A$4:$A$15,产品信息表!$E$4:$E$15) -> 95 | Z63: =(X63-Y63*S63)/X63 -> 0.17534722 | AA63: =_xlfn.RANK.EQ(V63,V63:V264,0) -> 88
A64: DD-20260412-0060 | B64: 46124 | C64: =TEXT(SUBSTITUTE(B64,".","/"),"yyyy-mm-dd") -> 2026-04-12 | D64: KH003 | E64: =VLOOKUP(D64,客户信息表!A$3:H$23,2,0) -> 广州启航教育 | F64: 广州启航教育 | G64: =INDEX(客户信息表!$A$4:$H$23,MATCH(F64,客户信息表!$B$4:$B$23,0),1) -> KH003 | H64: =_xlfn.XLOOKUP(O64,产品信息表!$A$4:$A$15,产品信息表!$C$4:$C$15) -> 办公耗材 | I64: =DATE(MID(A64,4,4),MID(A64,8,2),MID(A64,10,2)) -> 46124 | J64: =RIGHT(A64,4) -> 0060 | K64: =VLOOKUP(D64,客户信息表!$A$3:$H$23,5,0) -> A | L64: 孙悦 | M64: 华南 | N64: =SUBSTITUTE(TRIM(M64),"区","") -> 华南 | O64: CP010 | P64: 签字笔盒装（12支） | Q64: 45 | R64: 11 | S64: =IF(ISBLANK(R64),U64/Q64,VALUE(R64)) -> 11 | T64: =VLOOKUP(S64,折扣阶梯!$A$3:$C$7,2,TRUE) -> 0.95 | U64: 495 | V64: =IF(Q64*S64=VALUE(SUBSTITUTE(U64,"¥","")),VALUE(SUBSTITUTE(U64,"¥","")),Q64*S64) -> 495 | W64: 已取消 | X64: =V64*T64 -> 470.25 | Y64: =_xlfn.XLOOKUP(O64,产品信息表!$A$4:$A$15,产品信息表!$E$4:$E$15) -> 28 | Z64: =(X64-Y64*S64)/X64 -> 0.34502924 | AA64: =_xlfn.RANK.EQ(V64,V64:V265,0) -> 140
A65: DD-20260412-0061 | B65: 46124 | C65: =TEXT(SUBSTITUTE(B65,".","/"),"yyyy-mm-dd") -> 2026-04-12 | D65: KH006 | E65: =VLOOKUP(D65,客户信息表!A$3:H$23,2,0) -> 成都天府商贸 | F65: 成都天府商贸 | G65: =INDEX(客户信息表!$A$4:$H$23,MATCH(F65,客户信息表!$B$4:$B$23,0),1) -> KH006 | H65: =_xlfn.XLOOKUP(O65,产品信息表!$A$4:$A$15,产品信息表!$C$4:$C$15) -> 办公耗材 | I65: =DATE(MID(A65,4,4),MID(A65,8,2),MID(A65,10,2)) -> 46124 | J65: =RIGHT(A65,4) -> 0061 | K65: =VLOOKUP(D65,客户信息表!$A$3:$H$23,5,0) -> C | L65: 王强 | M65: 西南 | N65: =SUBSTITUTE(TRIM(M65),"区","") -> 西南 | O65: CP010 | P65: 签字笔盒装（12支） | Q65: 45 | R65: 109 | S65: =IF(ISBLANK(R65),U65/Q65,VALUE(R65)) -> 109 | T65: =VLOOKUP(S65,折扣阶梯!$A$3:$C$7,2,TRUE) -> 0.85 | U65: 4905 | V65: =IF(Q65*S65=VALUE(SUBSTITUTE(U65,"¥","")),VALUE(SUBSTITUTE(U65,"¥","")),Q65*S65) -> 4905 | W65: 已发货 | X65: =V65*T65 -> 4169.25 | Y65: =_xlfn.XLOOKUP(O65,产品信息表!$A$4:$A$15,产品信息表!$E$4:$E$15) -> 28 | Z65: =(X65-Y65*S65)/X65 -> 0.26797386 | AA65: =_xlfn.RANK.EQ(V65,V65:V266,0) -> 104
A66: DD-20260413-0062 | B66: 46125 | C66: =TEXT(SUBSTITUTE(B66,".","/"),"yyyy-mm-dd") -> 2026-04-13 | D66: KH001 | E66: =VLOOKUP(D66,客户信息表!A$3:H$23,2,0) -> 北京华信科技 | F66: 北京华信科技 | G66: =INDEX(客户信息表!$A$4:$H$23,MATCH(F66,客户信息表!$B$4:$B$23,0),1) -> KH001 | H66: =_xlfn.XLOOKUP(O66,产品信息表!$A$4:$A$15,产品信息表!$C$4:$C$15) -> 电子数码 | I66: =DATE(MID(A66,4,4),MID(A66,8,2),MID(A66,10,2)) -> 46125 | J66: =RIGHT(A66,4) -> 0062 | K66: =VLOOKUP(D66,客户信息表!$A$3:$H$23,5,0) -> A | L66: 王强 | M66: 华北 | N66: =SUBSTITUTE(TRIM(M66),"区","") -> 华北 | O66: CP006 | P66: 显示器 ViewMax 27 | Q66: 1299 | R66: 3 | S66: =IF(ISBLANK(R66),U66/Q66,VALUE(R66)) -> 3 | T66: =VLOOKUP(S66,折扣阶梯!$A$3:$C$7,2,TRUE) -> 1 | U66: 3897 | V66: =IF(Q66*S66=VALUE(SUBSTITUTE(U66,"¥","")),VALUE(SUBSTITUTE(U66,"¥","")),Q66*S66) -> 3897 | W66: 已完成 | X66: =V66*T66 -> 3897 | Y66: =_xlfn.XLOOKUP(O66,产品信息表!$A$4:$A$15,产品信息表!$E$4:$E$15) -> 950 | Z66: =(X66-Y66*S66)/X66 -> 0.26866821 | AA66: =_xlfn.RANK.EQ(V66,V66:V267,0) -> 109
A67: DD-20260413-0063 | B67: 46125 | C67: =TEXT(SUBSTITUTE(B67,".","/"),"yyyy-mm-dd") -> 2026-04-13 | D67: KH002 | E67: =VLOOKUP(D67,客户信息表!A$3:H$23,2,0) -> 上海锦程贸易 | F67: 上海锦程贸易 | G67: =INDEX(客户信息表!$A$4:$H$23,MATCH(F67,客户信息表!$B$4:$B$23,0),1) -> KH002 | H67: =_xlfn.XLOOKUP(O67,产品信息表!$A$4:$A$15,产品信息表!$C$4:$C$15) -> 办公耗材 | I67: =DATE(MID(A67,4,4),MID(A67,8,2),MID(A67,10,2)) -> 46125 | J67: =RIGHT(A67,4) -> 0063 | K67: =VLOOKUP(D67,客户信息表!$A$3:$H$23,5,0) -> B | L67: 张伟 | M67: 华东 | N67: =SUBSTITUTE(TRIM(M67),"区","") -> 华东 | O67: CP009 | P67: 激光硒鼓 TonerMax 12A | Q67: 385 | R67: 100 | S67: =IF(ISBLANK(R67),U67/Q67,VALUE(R67)) -> 100 | T67: =VLOOKUP(S67,折扣阶梯!$A$3:$C$7,2,TRUE) -> 0.85 | U67: 38500 | V67: =IF(Q67*S67=VALUE(SUBSTITUTE(U67,"¥","")),VALUE(SUBSTITUTE(U67,"¥","")),Q67*S67) -> 38500 | W67: 待付款 | X67: =V67*T67 -> 32725 | Y67: =_xlfn.XLOOKUP(O67,产品信息表!$A$4:$A$15,产品信息表!$E$4:$E$15) -> 260 | Z67: =(X67-Y67*S67)/X67 -> 0.20550038 | AA67: =_xlfn.RANK.EQ(V67,V67:V268,0) -> 10
A68: DD-20260413-0064 | B68: 46125 | C68: =TEXT(SUBSTITUTE(B68,".","/"),"yyyy-mm-dd") -> 2026-04-13 | D68: KH001 | E68: =VLOOKUP(D68,客户信息表!A$3:H$23,2,0) -> 北京华信科技 | F68: 北京华信科技 | G68: =INDEX(客户信息表!$A$4:$H$23,MATCH(F68,客户信息表!$B$4:$B$23,0),1) -> KH001 | H68: =_xlfn.XLOOKUP(O68,产品信息表!$A$4:$A$15,产品信息表!$C$4:$C$15) -> 电子数码 | I68: =DATE(MID(A68,4,4),MID(A68,8,2),MID(A68,10,2)) -> 46125 | J68: =RIGHT(A68,4) -> 0064 | K68: =VLOOKUP(D68,客户信息表!$A$3:$H$23,5,0) -> A | L68: 王强 | M68: 华北 | N68: =SUBSTITUTE(TRIM(M68),"区","") -> 华北 | O68: CP006 | P68: 显示器 ViewMax 27 | Q68: 1299 | R68: 9 | S68: =IF(ISBLANK(R68),U68/Q68,VALUE(R68)) -> 9 | T68: =VLOOKUP(S68,折扣阶梯!$A$3:$C$7,2,TRUE) -> 1 | U68: 11691 | V68: =IF(Q68*S68=VALUE(SUBSTITUTE(U68,"¥","")),VALUE(SUBSTITUTE(U68,"¥","")),Q68*S68) -> 11691 | W68: 已发货 | X68: =V68*T68 -> 11691 | Y68: =_xlfn.XLOOKUP(O68,产品信息表!$A$4:$A$15,产品信息表!$E$4:$E$15) -> 950 | Z68: =(X68-Y68*S68)/X68 -> 0.26866821 | AA68: =_xlfn.RANK.EQ(V68,V68:V269,0) -> 68
A69: DD-20260418-0065 | B69: 46130 | C69: =TEXT(SUBSTITUTE(B69,".","/"),"yyyy-mm-dd") -> 2026-04-18 | D69: KH004 | E69: =VLOOKUP(D69,客户信息表!A$3:H$23,2,0) -> 深圳蓝鲸网络 | F69: 深圳蓝鲸网络 | G69: =INDEX(客户信息表!$A$4:$H$23,MATCH(F69,客户信息表!$B$4:$B$23,0),1) -> KH004 | H69: =_xlfn.XLOOKUP(O69,产品信息表!$A$4:$A$15,产品信息表!$C$4:$C$15) -> 办公设备 | I69: =DATE(MID(A69,4,4),MID(A69,8,2),MID(A69,10,2)) -> 46130 | J69: =RIGHT(A69,4) -> 0065 | K69: =VLOOKUP(D69,客户信息表!$A$3:$H$23,5,0) -> B | L69: 孙悦 | M69: 华南 | N69: =SUBSTITUTE(TRIM(M69),"区","") -> 华南 | O69: CP002 | P69: 多功能一体机 PrintMaster 300 | Q69: 3599 | R69: 6 | S69: =IF(ISBLANK(R69),U69/Q69,VALUE(R69)) -> 6 | T69: =VLOOKUP(S69,折扣阶梯!$A$3:$C$7,2,TRUE) -> 1 | U69: 21594 | V69: =IF(Q69*S69=VALUE(SUBSTITUTE(U69,"¥","")),VALUE(SUBSTITUTE(U69,"¥","")),Q69*S69) -> 21594 | W69: 已完成 | X69: =V69*T69 -> 21594 | Y69: =_xlfn.XLOOKUP(O69,产品信息表!$A$4:$A$15,产品信息表!$E$4:$E$15) -> 2700 | Z69: =(X69-Y69*S69)/X69 -> 0.24979161 | AA69: =_xlfn.RANK.EQ(V69,V69:V270,0) -> 35
A70: DD-20260418-0066 | B70: 46130 | C70: =TEXT(SUBSTITUTE(B70,".","/"),"yyyy-mm-dd") -> 2026-04-18 | D70: KH016 | E70: =VLOOKUP(D70,客户信息表!A$3:H$23,2,0) -> 昆明滇池科技 | F70: 昆明滇池科技 | G70: =INDEX(客户信息表!$A$4:$H$23,MATCH(F70,客户信息表!$B$4:$B$23,0),1) -> KH016 | H70: =_xlfn.XLOOKUP(O70,产品信息表!$A$4:$A$15,产品信息表!$C$4:$C$15) -> 办公设备 | I70: =DATE(MID(A70,4,4),MID(A70,8,2),MID(A70,10,2)) -> 46130 | J70: =RIGHT(A70,4) -> 0066 | K70: =VLOOKUP(D70,客户信息表!$A$3:$H$23,5,0) -> C | L70: 陈静 | M70: 西南 | N70: =SUBSTITUTE(TRIM(M70),"区","") -> 西南 | O70: CP002 | P70: 多功能一体机 PrintMaster 300 | Q70: 3599 | S70: =IF(ISBLANK(R70),U70/Q70,VALUE(R70)) -> 5 | T70: =VLOOKUP(S70,折扣阶梯!$A$3:$C$7,2,TRUE) -> 1 | U70: 17995 | V70: =IF(Q70*S70=VALUE(SUBSTITUTE(U70,"¥","")),VALUE(SUBSTITUTE(U70,"¥","")),Q70*S70) -> 17995 | W70: 已发货 | X70: =V70*T70 -> 17995 | Y70: =_xlfn.XLOOKUP(O70,产品信息表!$A$4:$A$15,产品信息表!$E$4:$E$15) -> 2700 | Z70: =(X70-Y70*S70)/X70 -> 0.24979161 | AA70: =_xlfn.RANK.EQ(V70,V70:V271,0) -> 47
A71: DD-20260419-0067 | B71: 46131 | C71: =TEXT(SUBSTITUTE(B71,".","/"),"yyyy-mm-dd") -> 2026-04-19 | D71: KH006 | E71: =VLOOKUP(D71,客户信息表!A$3:H$23,2,0) -> 成都天府商贸 | F71: 成都天府商贸 | G71: =INDEX(客户信息表!$A$4:$H$23,MATCH(F71,客户信息表!$B$4:$B$23,0),1) -> KH006 | H71: =_xlfn.XLOOKUP(O71,产品信息表!$A$4:$A$15,产品信息表!$C$4:$C$15) -> 软件服务 | I71: =DATE(MID(A71,4,4),MID(A71,8,2),MID(A71,10,2)) -> 46131 | J71: =RIGHT(A71,4) -> 0067 | K71: =VLOOKUP(D71,客户信息表!$A$3:$H$23,5,0) -> C | L71: 刘洋 | M71: 西南 | N71: =SUBSTITUTE(TRIM(M71),"区","") -> 西南 | O71: CP011 | P71: 办公软件年费授权 | Q71: 699 | R71: 9 | S71: =IF(ISBLANK(R71),U71/Q71,VALUE(R71)) -> 9 | T71: =VLOOKUP(S71,折扣阶梯!$A$3:$C$7,2,TRUE) -> 1 | U71: 6291 | V71: =IF(Q71*S71=VALUE(SUBSTITUTE(U71,"¥","")),VALUE(SUBSTITUTE(U71,"¥","")),Q71*S71) -> 6291 | W71: 待付款 | X71: =V71*T71 -> 6291 | Y71: =_xlfn.XLOOKUP(O71,产品信息表!$A$4:$A$15,产品信息表!$E$4:$E$15) -> 300 | Z71: =(X71-Y71*S71)/X71 -> 0.57081545 | AA71: =_xlfn.RANK.EQ(V71,V71:V272,0) -> 91
A72: DD-20260419-0068 | B72: 46131 | C72: =TEXT(SUBSTITUTE(B72,".","/"),"yyyy-mm-dd") -> 2026-04-19 | D72: KH014 | E72: =VLOOKUP(D72,客户信息表!A$3:H$23,2,0) -> 宁波海港实业 | F72: 宁波海港实业 | G72: =INDEX(客户信息表!$A$4:$H$23,MATCH(F72,客户信息表!$B$4:$B$23,0),1) -> KH014 | H72: =_xlfn.XLOOKUP(O72,产品信息表!$A$4:$A$15,产品信息表!$C$4:$C$15) -> 电子数码 | I72: =DATE(MID(A72,4,4),MID(A72,8,2),MID(A72,10,2)) -> 46131 | J72: =RIGHT(A72,4) -> 0068 | K72: =VLOOKUP(D72,客户信息表!$A$3:$H$23,5,0) -> B | L72: 杨帆 | M72: 华东 | N72: =SUBSTITUTE(TRIM(M72),"区","") -> 华东 | O72: CP007 | P72: 无线键鼠套装 KeyFree 2.0 | Q72: 299 | R72: 10 | S72: =IF(ISBLANK(R72),U72/Q72,VALUE(R72)) -> 10 | T72: =VLOOKUP(S72,折扣阶梯!$A$3:$C$7,2,TRUE) -> 0.95 | U72: 2990 | V72: =IF(Q72*S72=VALUE(SUBSTITUTE(U72,"¥","")),VALUE(SUBSTITUTE(U72,"¥","")),Q72*S72) -> 2990 | W72: 已完成 | X72: =V72*T72 -> 2840.5 | Y72: =_xlfn.XLOOKUP(O72,产品信息表!$A$4:$A$15,产品信息表!$E$4:$E$15) -> 190 | Z72: =(X72-Y72*S72)/X72 -> 0.33110368 | AA72: =_xlfn.RANK.EQ(V72,V72:V273,0) -> 113
A73: DD-20260419-0069 | B73: 46131 | C73: =TEXT(SUBSTITUTE(B73,".","/"),"yyyy-mm-dd") -> 2026-04-19 | D73: KH015 | E73: =VLOOKUP(D73,客户信息表!A$3:H$23,2,0) -> 佛山美的家电商贸 | F73: 佛山美的家电商贸 | G73: =INDEX(客户信息表!$A$4:$H$23,MATCH(F73,客户信息表!$B$4:$B$23,0),1) -> KH015 | H73: =_xlfn.XLOOKUP(O73,产品信息表!$A$4:$A$15,产品信息表!$C$4:$C$15) -> 办公设备 | I73: =DATE(MID(A73,4,4),MID(A73,8,2),MID(A73,10,2)) -> 46131 | J73: =RIGHT(A73,4) -> 0069 | K73: =VLOOKUP(D73,客户信息表!$A$3:$H$23,5,0) -> A | L73: 陈静 | M73: 华南 | N73: =SUBSTITUTE(TRIM(M73),"区","") -> 华南 | O73: CP002 | P73: 多功能一体机 PrintMaster 300 | Q73: 3599 | R73: 8 | S73: =IF(ISBLANK(R73),U73/Q73,VALUE(R73)) -> 8 | T73: =VLOOKUP(S73,折扣阶梯!$A$3:$C$7,2,TRUE) -> 1 | U73: 28792 | V73: =IF(Q73*S73=VALUE(SUBSTITUTE(U73,"¥","")),VALUE(SUBSTITUTE(U73,"¥","")),Q73*S73) -> 28792 | W73: 已完成 | X73: =V73*T73 -> 28792 | Y73: =_xlfn.XLOOKUP(O73,产品信息表!$A$4:$A$15,产品信息表!$E$4:$E$15) -> 2700 | Z73: =(X73-Y73*S73)/X73 -> 0.24979161 | AA73: =_xlfn.RANK.EQ(V73,V73:V274,0) -> 15
A74: DD-20260420-0070 | B74: 46132 | C74: =TEXT(SUBSTITUTE(B74,".","/"),"yyyy-mm-dd") -> 2026-04-20 | D74: KH013 | E74: =VLOOKUP(D74,客户信息表!A$3:H$23,2,0) -> 石家庄振华商贸 | F74: 石家庄振华商贸 | G74: =INDEX(客户信息表!$A$4:$H$23,MATCH(F74,客户信息表!$B$4:$B$23,0),1) -> KH013 | H74: =_xlfn.XLOOKUP(O74,产品信息表!$A$4:$A$15,产品信息表!$C$4:$C$15) -> 办公设备 | I74: =DATE(MID(A74,4,4),MID(A74,8,2),MID(A74,10,2)) -> 46132 | J74: =RIGHT(A74,4) -> 0070 | K74: =VLOOKUP(D74,客户信息表!$A$3:$H$23,5,0) -> C | L74: 杨帆 | M74: 华北 | N74: =SUBSTITUTE(TRIM(M74),"区","") -> 华北 | O74: CP003 | P74: 碎纸机 SafeCut S8 | Q74: 899 | R74: 7 | S74: =IF(ISBLANK(R74),U74/Q74,VALUE(R74)) -> 7 | T74: =VLOOKUP(S74,折扣阶梯!$A$3:$C$7,2,TRUE) -> 1 | U74: 6293 | V74: =IF(Q74*S74=VALUE(SUBSTITUTE(U74,"¥","")),VALUE(SUBSTITUTE(U74,"¥","")),Q74*S74) -> 6293 | W74: 已完成 | X74: =V74*T74 -> 6293 | Y74: =_xlfn.XLOOKUP(O74,产品信息表!$A$4:$A$15,产品信息表!$E$4:$E$15) -> 620 | Z74: =(X74-Y74*S74)/X74 -> 0.31034483 | AA74: =_xlfn.RANK.EQ(V74,V74:V275,0) -> 88
A75: DD-20260421-0071 | B75: 46133 | C75: =TEXT(SUBSTITUTE(B75,".","/"),"yyyy-mm-dd") -> 2026-04-21 | D75: KH018 | E75: =VLOOKUP(D75,客户信息表!A$3:H$23,2,0) -> 厦门鹭岛文创 | F75: 厦门鹭岛文创 | G75: =INDEX(客户信息表!$A$4:$H$23,MATCH(F75,客户信息表!$B$4:$B$23,0),1) -> KH018 | H75: =_xlfn.XLOOKUP(O75,产品信息表!$A$4:$A$15,产品信息表!$C$4:$C$15) -> 办公耗材 | I75: =DATE(MID(A75,4,4),MID(A75,8,2),MID(A75,10,2)) -> 46133 | J75: =RIGHT(A75,4) -> 0071 | K75: =VLOOKUP(D75,客户信息表!$A$3:$H$23,5,0) -> C | L75: 赵磊 | M75: 华南 | N75: =SUBSTITUTE(TRIM(M75),"区","") -> 华南 | O75: CP009 | P75: 激光硒鼓 TonerMax 12A | Q75: 385 | R75: 73 | S75: =IF(ISBLANK(R75),U75/Q75,VALUE(R75)) -> 73 | T75: =VLOOKUP(S75,折扣阶梯!$A$3:$C$7,2,TRUE) -> 0.9 | U75: 28105 | V75: =IF(Q75*S75=VALUE(SUBSTITUTE(U75,"¥","")),VALUE(SUBSTITUTE(U75,"¥","")),Q75*S75) -> 28105 | W75: 已完成 | X75: =V75*T75 -> 25294.5 | Y75: =_xlfn.XLOOKUP(O75,产品信息表!$A$4:$A$15,产品信息表!$E$4:$E$15) -> 260 | Z75: =(X75-Y75*S75)/X75 -> 0.24963925 | AA75: =_xlfn.RANK.EQ(V75,V75:V276,0) -> 17
A76: DD-20260422-0072 | B76: 46134 | C76: =TEXT(SUBSTITUTE(B76,".","/"),"yyyy-mm-dd") -> 2026-04-22 | D76: KH003 | E76: =VLOOKUP(D76,客户信息表!A$3:H$23,2,0) -> 广州启航教育 | F76: 厦门鹭岛文创 | G76: =INDEX(客户信息表!$A$4:$H$23,MATCH(F76,客户信息表!$B$4:$B$23,0),1) -> KH018 | H76: =_xlfn.XLOOKUP(O76,产品信息表!$A$4:$A$15,产品信息表!$C$4:$C$15) -> 电子数码 | I76: =DATE(MID(A76,4,4),MID(A76,8,2),MID(A76,10,2)) -> 46134 | J76: =RIGHT(A76,4) -> 0072 | K76: =VLOOKUP(D76,客户信息表!$A$3:$H$23,5,0) -> A | L76: 杨帆 | M76: 华南 | N76: =SUBSTITUTE(TRIM(M76),"区","") -> 华南 | O76: CP007 | P76: 无线键鼠套装 KeyFree 2.0 | Q76: 299 | R76: 12 | S76: =IF(ISBLANK(R76),U76/Q76,VALUE(R76)) -> 12 | T76: =VLOOKUP(S76,折扣阶梯!$A$3:$C$7,2,TRUE) -> 0.95 | U76: 3588 | V76: =IF(Q76*S76=VALUE(SUBSTITUTE(U76,"¥","")),VALUE(SUBSTITUTE(U76,"¥","")),Q76*S76) -> 3588 | W76: 已发货 | X76: =V76*T76 -> 3408.6 | Y76: =_xlfn.XLOOKUP(O76,产品信息表!$A$4:$A$15,产品信息表!$E$4:$E$15) -> 190 | Z76: =(X76-Y76*S76)/X76 -> 0.33110368 | AA76: =_xlfn.RANK.EQ(V76,V76:V277,0) -> 105
A77: DD-20260423-0073 | B77: 46135 | C77: =TEXT(SUBSTITUTE(B77,".","/"),"yyyy-mm-dd") -> 2026-04-23 | D77: KH006 | E77: =VLOOKUP(D77,客户信息表!A$3:H$23,2,0) -> 成都天府商贸 | F77: 成都天府商贸 | G77: =INDEX(客户信息表!$A$4:$H$23,MATCH(F77,客户信息表!$B$4:$B$23,0),1) -> KH006 | H77: =_xlfn.XLOOKUP(O77,产品信息表!$A$4:$A$15,产品信息表!$C$4:$C$15) -> 软件服务 | I77: =DATE(MID(A77,4,4),MID(A77,8,2),MID(A77,10,2)) -> 46135 | J77: =RIGHT(A77,4) -> 0073 | K77: =VLOOKUP(D77,客户信息表!$A$3:$H$23,5,0) -> C | L77: 赵磊 | M77: 西南 | N77: =SUBSTITUTE(TRIM(M77),"区","") -> 西南 | O77: CP011 | P77: 办公软件年费授权 | Q77: 699 | R77: 39 | S77: =IF(ISBLANK(R77),U77/Q77,VALUE(R77)) -> 39 | T77: =VLOOKUP(S77,折扣阶梯!$A$3:$C$7,2,TRUE) -> 0.95 | U77: 27261 | V77: =IF(Q77*S77=VALUE(SUBSTITUTE(U77,"¥","")),VALUE(SUBSTITUTE(U77,"¥","")),Q77*S77) -> 27261 | W77: 已完成 | X77: =V77*T77 -> 25897.95 | Y77: =_xlfn.XLOOKUP(O77,产品信息表!$A$4:$A$15,产品信息表!$E$4:$E$15) -> 300 | Z77: =(X77-Y77*S77)/X77 -> 0.54822679 | AA77: =_xlfn.RANK.EQ(V77,V77:V278,0) -> 18
A78: DD-20260423-0074 | B78: 46135 | C78: =TEXT(SUBSTITUTE(B78,".","/"),"yyyy-mm-dd") -> 2026-04-23 | D78: KH008 | E78: =VLOOKUP(D78,客户信息表!A$3:H$23,2,0) -> 南京紫金山软件园运营 | F78: 南京紫金山软件园运营 | G78: =INDEX(客户信息表!$A$4:$H$23,MATCH(F78,客户信息表!$B$4:$B$23,0),1) -> KH008 | H78: =_xlfn.XLOOKUP(O78,产品信息表!$A$4:$A$15,产品信息表!$C$4:$C$15) -> 办公耗材 | I78: =DATE(MID(A78,4,4),MID(A78,8,2),MID(A78,10,2)) -> 46135 | J78: =RIGHT(A78,4) -> 0074 | K78: =VLOOKUP(D78,客户信息表!$A$3:$H$23,5,0) -> C | L78: 王强 | M78: 华东 | N78: =SUBSTITUTE(TRIM(M78),"区","") -> 华东 | O78: CP008 | P78: A4复印纸（5包/箱） | Q78: 128 | R78: 104 | S78: =IF(ISBLANK(R78),U78/Q78,VALUE(R78)) -> 104 | T78: =VLOOKUP(S78,折扣阶梯!$A$3:$C$7,2,TRUE) -> 0.85 | U78: 13312 | V78: =IF(Q78*S78=VALUE(SUBSTITUTE(U78,"¥","")),VALUE(SUBSTITUTE(U78,"¥","")),Q78*S78) -> 13312 | W78: 已完成 | X78: =V78*T78 -> 11315.2 | Y78: =_xlfn.XLOOKUP(O78,产品信息表!$A$4:$A$15,产品信息表!$E$4:$E$15) -> 95 | Z78: =(X78-Y78*S78)/X78 -> 0.12683824 | AA78: =_xlfn.RANK.EQ(V78,V78:V279,0) -> 55
A79: DD-20260426-0075 | B79: 46138 | C79: =TEXT(SUBSTITUTE(B79,".","/"),"yyyy-mm-dd") -> 2026-04-26 | D79: KH005 | E79: =VLOOKUP(D79,客户信息表!A$3:H$23,2,0) -> 杭州云图信息 | F79: 杭州云图信息 | G79: =INDEX(客户信息表!$A$4:$H$23,MATCH(F79,客户信息表!$B$4:$B$23,0),1) -> KH005 | H79: =_xlfn.XLOOKUP(O79,产品信息表!$A$4:$A$15,产品信息表!$C$4:$C$15) -> 办公设备 | I79: =DATE(MID(A79,4,4),MID(A79,8,2),MID(A79,10,2)) -> 46138 | J79: =RIGHT(A79,4) -> 0075 | K79: =VLOOKUP(D79,客户信息表!$A$3:$H$23,5,0) -> A | L79: 孙悦 | M79: 华东 | N79: =SUBSTITUTE(TRIM(M79),"区","") -> 华东 | O79: CP003 | P79: 碎纸机 SafeCut S8 | Q79: 899 | R79: 5 | S79: =IF(ISBLANK(R79),U79/Q79,VALUE(R79)) -> 5 | T79: =VLOOKUP(S79,折扣阶梯!$A$3:$C$7,2,TRUE) -> 1 | U79: ¥4,495.00 | V79: =IF(Q79*S79=VALUE(SUBSTITUTE(U79,"¥","")),VALUE(SUBSTITUTE(U79,"¥","")),Q79*S79) -> 4495 | W79: 已完成 | X79: =V79*T79 -> 4495 | Y79: =_xlfn.XLOOKUP(O79,产品信息表!$A$4:$A$15,产品信息表!$E$4:$E$15) -> 620 | Z79: =(X79-Y79*S79)/X79 -> 0.31034483 | AA79: =_xlfn.RANK.EQ(V79,V79:V280,0) -> 94
A80: DD-20260426-0076 | B80: 46138 | C80: =TEXT(SUBSTITUTE(B80,".","/"),"yyyy-mm-dd") -> 2026-04-26 | D80: KH010 | E80: =VLOOKUP(D80,客户信息表!A$3:H$23,2,0) -> 苏州创智科技 | F80: 苏州创智科技 | G80: =INDEX(客户信息表!$A$4:$H$23,MATCH(F80,客户信息表!$B$4:$B$23,0),1) -> KH010 | H80: =_xlfn.XLOOKUP(O80,产品信息表!$A$4:$A$15,产品信息表!$C$4:$C$15) -> 电子数码 | I80: =DATE(MID(A80,4,4),MID(A80,8,2),MID(A80,10,2)) -> 46138 | J80: =RIGHT(A80,4) -> 0076 | K80: =VLOOKUP(D80,客户信息表!$A$3:$H$23,5,0) -> A | L80: 王强 | M80: 华东 | N80: =SUBSTITUTE(TRIM(M80),"区","") -> 华东 | O80: CP005 | P80: 台式电脑 PowerDesk 500 | Q80: 4299 | R80: 6 | S80: =IF(ISBLANK(R80),U80/Q80,VALUE(R80)) -> 6 | T80: =VLOOKUP(S80,折扣阶梯!$A$3:$C$7,2,TRUE) -> 1 | U80: 25794 | V80: =IF(Q80*S80=VALUE(SUBSTITUTE(U80,"¥","")),VALUE(SUBSTITUTE(U80,"¥","")),Q80*S80) -> 25794 | W80: 已完成 | X80: =V80*T80 -> 25794 | Y80: =_xlfn.XLOOKUP(O80,产品信息表!$A$4:$A$15,产品信息表!$E$4:$E$15) -> 3500 | Z80: =(X80-Y80*S80)/X80 -> 0.18585718 | AA80: =_xlfn.RANK.EQ(V80,V80:V281,0) -> 20
A81: DD-20260427-0077 | B81: 46139 | C81: =TEXT(SUBSTITUTE(B81,".","/"),"yyyy-mm-dd") -> 2026-04-27 | D81: KH002 | E81: =VLOOKUP(D81,客户信息表!A$3:H$23,2,0) -> 上海锦程贸易 | F81: 上海锦程贸易 | G81: =INDEX(客户信息表!$A$4:$H$23,MATCH(F81,客户信息表!$B$4:$B$23,0),1) -> KH002 | H81: =_xlfn.XLOOKUP(O81,产品信息表!$A$4:$A$15,产品信息表!$C$4:$C$15) -> 电子数码 | I81: =DATE(MID(A81,4,4),MID(A81,8,2),MID(A81,10,2)) -> 46139 | J81: =RIGHT(A81,4) -> 0077 | K81: =VLOOKUP(D81,客户信息表!$A$3:$H$23,5,0) -> B | L81: 赵磊 | M81: 华东 | N81: =SUBSTITUTE(TRIM(M81),"区","") -> 华东 | O81: CP005 | P81: 台式电脑 PowerDesk 500 | Q81: 4299 | S81: =IF(ISBLANK(R81),U81/Q81,VALUE(R81)) -> 8 | T81: =VLOOKUP(S81,折扣阶梯!$A$3:$C$7,2,TRUE) -> 1 | U81: 34392 | V81: =IF(Q81*S81=VALUE(SUBSTITUTE(U81,"¥","")),VALUE(SUBSTITUTE(U81,"¥","")),Q81*S81) -> 34392 | W81: 已完成 | X81: =V81*T81 -> 34392 | Y81: =_xlfn.XLOOKUP(O81,产品信息表!$A$4:$A$15,产品信息表!$E$4:$E$15) -> 3500 | Z81: =(X81-Y81*S81)/X81 -> 0.18585718 | AA81: =_xlfn.RANK.EQ(V81,V81:V282,0) -> 12
A82: DD-20260428-0078 | B82: 46140 | C82: =TEXT(SUBSTITUTE(B82,".","/"),"yyyy-mm-dd") -> 2026-04-28 | D82: KH010 | E82: =VLOOKUP(D82,客户信息表!A$3:H$23,2,0) -> 苏州创智科技 | F82: 苏州创智科技 | G82: =INDEX(客户信息表!$A$4:$H$23,MATCH(F82,客户信息表!$B$4:$B$23,0),1) -> KH010 | H82: =_xlfn.XLOOKUP(O82,产品信息表!$A$4:$A$15,产品信息表!$C$4:$C$15) -> 电子数码 | I82: =DATE(MID(A82,4,4),MID(A82,8,2),MID(A82,10,2)) -> 46140 | J82: =RIGHT(A82,4) -> 0078 | K82: =VLOOKUP(D82,客户信息表!$A$3:$H$23,5,0) -> A | L82: 杨帆 | M82: 华东 | N82: =SUBSTITUTE(TRIM(M82),"区","") -> 华东 | O82: CP006 | P82: 显示器 ViewMax 27 | Q82: 1299 | R82: 7 | S82: =IF(ISBLANK(R82),U82/Q82,VALUE(R82)) -> 7 | T82: =VLOOKUP(S82,折扣阶梯!$A$3:$C$7,2,TRUE) -> 1 | U82: 9093 | V82: =IF(Q82*S82=VALUE(SUBSTITUTE(U82,"¥","")),VALUE(SUBSTITUTE(U82,"¥","")),Q82*S82) -> 9093 | W82: 已完成 | X82: =V82*T82 -> 9093 | Y82: =_xlfn.XLOOKUP(O82,产品信息表!$A$4:$A$15,产品信息表!$E$4:$E$15) -> 950 | Z82: =(X82-Y82*S82)/X82 -> 0.26866821 | AA82: =_xlfn.RANK.EQ(V82,V82:V283,0) -> 68
A83: DD-20260428-0079 | B83: 46140 | C83: =TEXT(SUBSTITUTE(B83,".","/"),"yyyy-mm-dd") -> 2026-04-28 | D83: KH015 | E83: =VLOOKUP(D83,客户信息表!A$3:H$23,2,0) -> 佛山美的家电商贸 | F83: 佛山美的家电商贸 | G83: =INDEX(客户信息表!$A$4:$H$23,MATCH(F83,客户信息表!$B$4:$B$23,0),1) -> KH015 | H83: =_xlfn.XLOOKUP(O83,产品信息表!$A$4:$A$15,产品信息表!$C$4:$C$15) -> 办公耗材 | I83: =DATE(MID(A83,4,4),MID(A83,8,2),MID(A83,10,2)) -> 46140 | J83: =RIGHT(A83,4) -> 0079 | K83: =VLOOKUP(D83,客户信息表!$A$3:$H$23,5,0) -> A | L83: 刘洋 | M83: 华南区 | N83: =SUBSTITUTE(TRIM(M83),"区","") -> 华南 | O83: CP008 | P83: A4复印纸（5包/箱） | Q83: 128 | R83: 96 | S83: =IF(ISBLANK(R83),U83/Q83,VALUE(R83)) -> 96 | T83: =VLOOKUP(S83,折扣阶梯!$A$3:$C$7,2,TRUE) -> 0.9 | U83: 12288 | V83: =IF(Q83*S83=VALUE(SUBSTITUTE(U83,"¥","")),VALUE(SUBSTITUTE(U83,"¥","")),Q83*S83) -> 12288 | W83: 已完成 | X83: =V83*T83 -> 11059.2 | Y83: =_xlfn.XLOOKUP(O83,产品信息表!$A$4:$A$15,产品信息表!$E$4:$E$15) -> 95 | Z83: =(X83-Y83*S83)/X83 -> 0.17534722 | AA83: =_xlfn.RANK.EQ(V83,V83:V284,0) -> 58
A84: DD-20260428-0080 | B84: 46140 | C84: =TEXT(SUBSTITUTE(B84,".","/"),"yyyy-mm-dd") -> 2026-04-28 | D84: KH012 | E84: =VLOOKUP(D84,客户信息表!A$3:H$23,2,0) -> 长沙麓山科技 | F84: 长沙麓山科技 | G84: =INDEX(客户信息表!$A$4:$H$23,MATCH(F84,客户信息表!$B$4:$B$23,0),1) -> KH012 | H84: =_xlfn.XLOOKUP(O84,产品信息表!$A$4:$A$15,产品信息表!$C$4:$C$15) -> 办公设备 | I84: =DATE(MID(A84,4,4),MID(A84,8,2),MID(A84,10,2)) -> 46140 | J84: =RIGHT(A84,4) -> 0080 | K84: =VLOOKUP(D84,客户信息表!$A$3:$H$23,5,0) -> B | L84: 王强 | M84: 华中 | N84: =SUBSTITUTE(TRIM(M84),"区","") -> 华中 | O84: CP002 | P84: 多功能一体机 PrintMaster 300 | Q84: 3599 | R84: 7 | S84: =IF(ISBLANK(R84),U84/Q84,VALUE(R84)) -> 7 | T84: =VLOOKUP(S84,折扣阶梯!$A$3:$C$7,2,TRUE) -> 1 | U84: 25193 | V84: =IF(Q84*S84=VALUE(SUBSTITUTE(U84,"¥","")),VALUE(SUBSTITUTE(U84,"¥","")),Q84*S84) -> 25193 | W84: 已完成 | X84: =V84*T84 -> 25193 | Y84: =_xlfn.XLOOKUP(O84,产品信息表!$A$4:$A$15,产品信息表!$E$4:$E$15) -> 2700 | Z84: =(X84-Y84*S84)/X84 -> 0.24979161 | AA84: =_xlfn.RANK.EQ(V84,V84:V285,0) -> 22
A85: DD-20260429-0081 | B85: 46141 | C85: =TEXT(SUBSTITUTE(B85,".","/"),"yyyy-mm-dd") -> 2026-04-29 | D85: KH011 | E85: =VLOOKUP(D85,客户信息表!A$3:H$23,2,0) -> 重庆山城办公设备 | F85: 重庆山城办公设备 | G85: =INDEX(客户信息表!$A$4:$H$23,MATCH(F85,客户信息表!$B$4:$B$23,0),1) -> KH011 | H85: =_xlfn.XLOOKUP(O85,产品信息表!$A$4:$A$15,产品信息表!$C$4:$C$15) -> 电子数码 | I85: =DATE(MID(A85,4,4),MID(A85,8,2),MID(A85,10,2)) -> 46141 | J85: =RIGHT(A85,4) -> 0081 | K85: =VLOOKUP(D85,客户信息表!$A$3:$H$23,5,0) -> B | L85: 赵磊 | M85: 西南 | N85: =SUBSTITUTE(TRIM(M85),"区","") -> 西南 | O85: CP005 | P85: 台式电脑 PowerDesk 500 | Q85: 4299 | R85: 6 | S85: =IF(ISBLANK(R85),U85/Q85,VALUE(R85)) -> 6 | T85: =VLOOKUP(S85,折扣阶梯!$A$3:$C$7,2,TRUE) -> 1 | U85: 25794 | V85: =IF(Q85*S85=VALUE(SUBSTITUTE(U85,"¥","")),VALUE(SUBSTITUTE(U85,"¥","")),Q85*S85) -> 25794 | W85: 待付款 | X85: =V85*T85 -> 25794 | Y85: =_xlfn.XLOOKUP(O85,产品信息表!$A$4:$A$15,产品信息表!$E$4:$E$15) -> 3500 | Z85: =(X85-Y85*S85)/X85 -> 0.18585718 | AA85: =_xlfn.RANK.EQ(V85,V85:V286,0) -> 19
A86: DD-20260430-0082 | B86: 46142 | C86: =TEXT(SUBSTITUTE(B86,".","/"),"yyyy-mm-dd") -> 2026-04-30 | D86: KH015 | E86: =VLOOKUP(D86,客户信息表!A$3:H$23,2,0) -> 佛山美的家电商贸 | F86: 佛山美的家电商贸 | G86: =INDEX(客户信息表!$A$4:$H$23,MATCH(F86,客户信息表!$B$4:$B$23,0),1) -> KH015 | H86: =_xlfn.XLOOKUP(O86,产品信息表!$A$4:$A$15,产品信息表!$C$4:$C$15) -> 软件服务 | I86: =DATE(MID(A86,4,4),MID(A86,8,2),MID(A86,10,2)) -> 46142 | J86: =RIGHT(A86,4) -> 0082 | K86: =VLOOKUP(D86,客户信息表!$A$3:$H$23,5,0) -> A | L86: 杨帆 | M86: 华南 | N86: =SUBSTITUTE(TRIM(M86),"区","") -> 华南 | O86: CP011 | P86: 办公软件年费授权 | Q86: 699 | R86: 32 | S86: =IF(ISBLANK(R86),U86/Q86,VALUE(R86)) -> 32 | T86: =VLOOKUP(S86,折扣阶梯!$A$3:$C$7,2,TRUE) -> 0.95 | U86: 22368 | V86: =IF(Q86*S86=VALUE(SUBSTITUTE(U86,"¥","")),VALUE(SUBSTITUTE(U86,"¥","")),Q86*S86) -> 22368 | W86: 已完成 | X86: =V86*T86 -> 21249.6 | Y86: =_xlfn.XLOOKUP(O86,产品信息表!$A$4:$A$15,产品信息表!$E$4:$E$15) -> 300 | Z86: =(X86-Y86*S86)/X86 -> 0.54822679 | AA86: =_xlfn.RANK.EQ(V86,V86:V287,0) -> 26
A87: DD-20260501-0083 | B87: 46143 | C87: =TEXT(SUBSTITUTE(B87,".","/"),"yyyy-mm-dd") -> 2026-05-01 | D87: KH015 | E87: =VLOOKUP(D87,客户信息表!A$3:H$23,2,0) -> 佛山美的家电商贸 | F87: 佛山美的家电商贸 | G87: =INDEX(客户信息表!$A$4:$H$23,MATCH(F87,客户信息表!$B$4:$B$23,0),1) -> KH015 | H87: =_xlfn.XLOOKUP(O87,产品信息表!$A$4:$A$15,产品信息表!$C$4:$C$15) -> 办公耗材 | I87: =DATE(MID(A87,4,4),MID(A87,8,2),MID(A87,10,2)) -> 46143 | J87: =RIGHT(A87,4) -> 0083 | K87: =VLOOKUP(D87,客户信息表!$A$3:$H$23,5,0) -> A | L87: 陈静 | M87: 华南 | N87: =SUBSTITUTE(TRIM(M87),"区","") -> 华南 | O87: CP009 | P87: 激光硒鼓 TonerMax 12A | Q87: 385 | R87: 94 | S87: =IF(ISBLANK(R87),U87/Q87,VALUE(R87)) -> 94 | T87: =VLOOKUP(S87,折扣阶梯!$A$3:$C$7,2,TRUE) -> 0.9 | U87: 36190 | V87: =IF(Q87*S87=VALUE(SUBSTITUTE(U87,"¥","")),VALUE(SUBSTITUTE(U87,"¥","")),Q87*S87) -> 36190 | W87: 已完成 | X87: =V87*T87 -> 32571 | Y87: =_xlfn.XLOOKUP(O87,产品信息表!$A$4:$A$15,产品信息表!$E$4:$E$15) -> 260 | Z87: =(X87-Y87*S87)/X87 -> 0.24963925 | AA87: =_xlfn.RANK.EQ(V87,V87:V288,0) -> 10
A88: DD-20260501-0084 | B88: 2026.5.1 | C88: =TEXT(SUBSTITUTE(B88,".","/"),"yyyy-mm-dd") -> 2026-05-01 | D88: KH015 | E88: =VLOOKUP(D88,客户信息表!A$3:H$23,2,0) -> 佛山美的家电商贸 | F88: 佛山美的家电商贸 | G88: =INDEX(客户信息表!$A$4:$H$23,MATCH(F88,客户信息表!$B$4:$B$23,0),1) -> KH015 | H88: =_xlfn.XLOOKUP(O88,产品信息表!$A$4:$A$15,产品信息表!$C$4:$C$15) -> 办公耗材 | I88: =DATE(MID(A88,4,4),MID(A88,8,2),MID(A88,10,2)) -> 46143 | J88: =RIGHT(A88,4) -> 0084 | K88: =VLOOKUP(D88,客户信息表!$A$3:$H$23,5,0) -> A | L88: 陈静 | M88: 华南 | N88: =SUBSTITUTE(TRIM(M88),"区","") -> 华南 | O88: CP010 | P88: 签字笔盒装（12支） | Q88: 45 | R88: 75 | S88: =IF(ISBLANK(R88),U88/Q88,VALUE(R88)) -> 75 | T88: =VLOOKUP(S88,折扣阶梯!$A$3:$C$7,2,TRUE) -> 0.9 | U88: 3375 | V88: =IF(Q88*S88=VALUE(SUBSTITUTE(U88,"¥","")),VALUE(SUBSTITUTE(U88,"¥","")),Q88*S88) -> 3375 | W88: 已发货 | X88: =V88*T88 -> 3037.5 | Y88: =_xlfn.XLOOKUP(O88,产品信息表!$A$4:$A$15,产品信息表!$E$4:$E$15) -> 28 | Z88: =(X88-Y88*S88)/X88 -> 0.30864198 | AA88: =_xlfn.RANK.EQ(V88,V88:V289,0) -> 96
A89: DD-20260503-0085 | B89: 46145 | C89: =TEXT(SUBSTITUTE(B89,".","/"),"yyyy-mm-dd") -> 2026-05-03 | D89: KH007 | E89: =VLOOKUP(D89,客户信息表!A$3:H$23,2,0) -> 武汉长江实业 | F89: 武汉长江实业 | G89: =INDEX(客户信息表!$A$4:$H$23,MATCH(F89,客户信息表!$B$4:$B$23,0),1) -> KH007 | H89: =_xlfn.XLOOKUP(O89,产品信息表!$A$4:$A$15,产品信息表!$C$4:$C$15) -> 办公耗材 | I89: =DATE(MID(A89,4,4),MID(A89,8,2),MID(A89,10,2)) -> 46145 | J89: =RIGHT(A89,4) -> 0085 | K89: =VLOOKUP(D89,客户信息表!$A$3:$H$23,5,0) -> B | L89: 张伟 | M89: 华中 | N89: =SUBSTITUTE(TRIM(M89),"区","") -> 华中 | O89: CP008 | P89: A4复印纸（5包/箱） | Q89: 128 | R89: 34 | S89: =IF(ISBLANK(R89),U89/Q89,VALUE(R89)) -> 34 | T89: =VLOOKUP(S89,折扣阶梯!$A$3:$C$7,2,TRUE) -> 0.95 | U89: 4352 | V89: =IF(Q89*S89=VALUE(SUBSTITUTE(U89,"¥","")),VALUE(SUBSTITUTE(U89,"¥","")),Q89*S89) -> 4352 | W89: 已取消 | X89: =V89*T89 -> 4134.4 | Y89: =_xlfn.XLOOKUP(O89,产品信息表!$A$4:$A$15,产品信息表!$E$4:$E$15) -> 95 | Z89: =(X89-Y89*S89)/X89 -> 0.21875 | AA89: =_xlfn.RANK.EQ(V89,V89:V290,0) -> 88
A90: DD-20260503-0086 | B90: 46145 | C90: =TEXT(SUBSTITUTE(B90,".","/"),"yyyy-mm-dd") -> 2026-05-03 | D90: KH003 | E90: =VLOOKUP(D90,客户信息表!A$3:H$23,2,0) -> 广州启航教育 | F90: 广州启航教育 | G90: =INDEX(客户信息表!$A$4:$H$23,MATCH(F90,客户信息表!$B$4:$B$23,0),1) -> KH003 | H90: =_xlfn.XLOOKUP(O90,产品信息表!$A$4:$A$15,产品信息表!$C$4:$C$15) -> 软件服务 | I90: =DATE(MID(A90,4,4),MID(A90,8,2),MID(A90,10,2)) -> 46145 | J90: =RIGHT(A90,4) -> 0086 | K90: =VLOOKUP(D90,客户信息表!$A$3:$H$23,5,0) -> A | L90: 刘洋 | M90: 华南 | N90: =SUBSTITUTE(TRIM(M90),"区","") -> 华南 | O90: CP012 | P90: 云存储服务（1TB/年） | Q90: 599 | R90: 31 | S90: =IF(ISBLANK(R90),U90/Q90,VALUE(R90)) -> 31 | T90: =VLOOKUP(S90,折扣阶梯!$A$3:$C$7,2,TRUE) -> 0.95 | U90: 18569 | V90: =IF(Q90*S90=VALUE(SUBSTITUTE(U90,"¥","")),VALUE(SUBSTITUTE(U90,"¥","")),Q90*S90) -> 18569 | W90: 已发货 | X90: =V90*T90 -> 17640.55 | Y90: =_xlfn.XLOOKUP(O90,产品信息表!$A$4:$A$15,产品信息表!$E$4:$E$15) -> 250 | Z90: =(X90-Y90*S90)/X90 -> 0.56067129 | AA90: =_xlfn.RANK.EQ(V90,V90:V291,0) -> 35
A91: DD-20260503-0087 | B91: 2026/5/3 | C91: =TEXT(SUBSTITUTE(B91,".","/"),"yyyy-mm-dd") -> 2026-05-03 | D91: KH003 | E91: =VLOOKUP(D91,客户信息表!A$3:H$23,2,0) -> 广州启航教育 | F91: 广州启航教育 | G91: =INDEX(客户信息表!$A$4:$H$23,MATCH(F91,客户信息表!$B$4:$B$23,0),1) -> KH003 | H91: =_xlfn.XLOOKUP(O91,产品信息表!$A$4:$A$15,产品信息表!$C$4:$C$15) -> 电子数码 | I91: =DATE(MID(A91,4,4),MID(A91,8,2),MID(A91,10,2)) -> 46145 | J91: =RIGHT(A91,4) -> 0087 | K91: =VLOOKUP(D91,客户信息表!$A$3:$H$23,5,0) -> A | L91: 赵磊 | M91: 华南 | N91: =SUBSTITUTE(TRIM(M91),"区","") -> 华南 | O91: CP006 | P91: 显示器 ViewMax 27 | Q91: 1299 | R91: 10 | S91: =IF(ISBLANK(R91),U91/Q91,VALUE(R91)) -> 10 | T91: =VLOOKUP(S91,折扣阶梯!$A$3:$C$7,2,TRUE) -> 0.95 | U91: 12990 | V91: =IF(Q91*S91=VALUE(SUBSTITUTE(U91,"¥","")),VALUE(SUBSTITUTE(U91,"¥","")),Q91*S91) -> 12990 | W91: 已发货 | X91: =V91*T91 -> 12340.5 | Y91: =_xlfn.XLOOKUP(O91,产品信息表!$A$4:$A$15,产品信息表!$E$4:$E$15) -> 950 | Z91: =(X91-Y91*S91)/X91 -> 0.23017706 | AA91: =_xlfn.RANK.EQ(V91,V91:V292,0) -> 49
A92: DD-20260504-0088 | B92: 46146 | C92: =TEXT(SUBSTITUTE(B92,".","/"),"yyyy-mm-dd") -> 2026-05-04 | D92: KH013 | E92: =VLOOKUP(D92,客户信息表!A$3:H$23,2,0) -> 石家庄振华商贸 | F92: 石家庄振华商贸 | G92: =INDEX(客户信息表!$A$4:$H$23,MATCH(F92,客户信息表!$B$4:$B$23,0),1) -> KH013 | H92: =_xlfn.XLOOKUP(O92,产品信息表!$A$4:$A$15,产品信息表!$C$4:$C$15) -> 办公耗材 | I92: =DATE(MID(A92,4,4),MID(A92,8,2),MID(A92,10,2)) -> 46146 | J92: =RIGHT(A92,4) -> 0088 | K92: =VLOOKUP(D92,客户信息表!$A$3:$H$23,5,0) -> C | L92: 张伟 | M92: 华北 | N92: =SUBSTITUTE(TRIM(M92),"区","") -> 华北 | O92: CP008 | P92: A4复印纸（5包/箱） | Q92: 128 | R92: 23 | S92: =IF(ISBLANK(R92),U92/Q92,VALUE(R92)) -> 23 | T92: =VLOOKUP(S92,折扣阶梯!$A$3:$C$7,2,TRUE) -> 0.95 | U92: 2944 | V92: =IF(Q92*S92=VALUE(SUBSTITUTE(U92,"¥","")),VALUE(SUBSTITUTE(U92,"¥","")),Q92*S92) -> 2944 | W92: 已完成 | X92: =V92*T92 -> 2796.8 | Y92: =_xlfn.XLOOKUP(O92,产品信息表!$A$4:$A$15,产品信息表!$E$4:$E$15) -> 95 | Z92: =(X92-Y92*S92)/X92 -> 0.21875 | AA92: =_xlfn.RANK.EQ(V92,V92:V293,0) -> 96
A93: DD-20260505-0089 | B93: 46147 | C93: =TEXT(SUBSTITUTE(B93,".","/"),"yyyy-mm-dd") -> 2026-05-05 | D93: KH008 | E93: =VLOOKUP(D93,客户信息表!A$3:H$23,2,0) -> 南京紫金山软件园运营 | F93: 南京紫金山软件园运营 | G93: =INDEX(客户信息表!$A$4:$H$23,MATCH(F93,客户信息表!$B$4:$B$23,0),1) -> KH008 | H93: =_xlfn.XLOOKUP(O93,产品信息表!$A$4:$A$15,产品信息表!$C$4:$C$15) -> 电子数码 | I93: =DATE(MID(A93,4,4),MID(A93,8,2),MID(A93,10,2)) -> 46147 | J93: =RIGHT(A93,4) -> 0089 | K93: =VLOOKUP(D93,客户信息表!$A$3:$H$23,5,0) -> C | L93: 刘洋 | M93: 华东 | N93: =SUBSTITUTE(TRIM(M93),"区","") -> 华东 | O93: CP004 | P93: 笔记本电脑 TechBook 14 | Q93: 5699 | R93: 12 | S93: =IF(ISBLANK(R93),U93/Q93,VALUE(R93)) -> 12 | T93: =VLOOKUP(S93,折扣阶梯!$A$3:$C$7,2,TRUE) -> 0.95 | U93: 68388 | V93: =IF(Q93*S93=VALUE(SUBSTITUTE(U93,"¥","")),VALUE(SUBSTITUTE(U93,"¥","")),Q93*S93) -> 68388 | W93: 已取消 | X93: =V93*T93 -> 64968.6 | Y93: =_xlfn.XLOOKUP(O93,产品信息表!$A$4:$A$15,产品信息表!$E$4:$E$15) -> 4800 | Z93: =(X93-Y93*S93)/X93 -> 0.11341787 | AA93: =_xlfn.RANK.EQ(V93,V93:V294,0) -> 1
A94: DD-20260506-0090 | B94: 46148 | C94: =TEXT(SUBSTITUTE(B94,".","/"),"yyyy-mm-dd") -> 2026-05-06 | D94: KH018 | E94: =VLOOKUP(D94,客户信息表!A$3:H$23,2,0) -> 厦门鹭岛文创 | F94: 厦门鹭岛文创 | G94: =INDEX(客户信息表!$A$4:$H$23,MATCH(F94,客户信息表!$B$4:$B$23,0),1) -> KH018 | H94: =_xlfn.XLOOKUP(O94,产品信息表!$A$4:$A$15,产品信息表!$C$4:$C$15) -> 办公耗材 | I94: =DATE(MID(A94,4,4),MID(A94,8,2),MID(A94,10,2)) -> 46148 | J94: =RIGHT(A94,4) -> 0090 | K94: =VLOOKUP(D94,客户信息表!$A$3:$H$23,5,0) -> C | L94: 杨帆 | M94: 华南 | N94: =SUBSTITUTE(TRIM(M94),"区","") -> 华南 | O94: CP009 | P94: 激光硒鼓 TonerMax 12A | Q94: 385 | R94: 53 | S94: =IF(ISBLANK(R94),U94/Q94,VALUE(R94)) -> 53 | T94: =VLOOKUP(S94,折扣阶梯!$A$3:$C$7,2,TRUE) -> 0.9 | U94: 20405 | V94: =IF(Q94*S94=VALUE(SUBSTITUTE(U94,"¥","")),VALUE(SUBSTITUTE(U94,"¥","")),Q94*S94) -> 20405 | W94: 已完成 | X94: =V94*T94 -> 18364.5 | Y94: =_xlfn.XLOOKUP(O94,产品信息表!$A$4:$A$15,产品信息表!$E$4:$E$15) -> 260 | Z94: =(X94-Y94*S94)/X94 -> 0.24963925 | AA94: =_xlfn.RANK.EQ(V94,V94:V295,0) -> 28
A95: DD-20260506-0091 | B95: 46148 | C95: =TEXT(SUBSTITUTE(B95,".","/"),"yyyy-mm-dd") -> 2026-05-06 | D95: KH012 | E95: =VLOOKUP(D95,客户信息表!A$3:H$23,2,0) -> 长沙麓山科技 | F95: 长沙麓山科技 | G95: =INDEX(客户信息表!$A$4:$H$23,MATCH(F95,客户信息表!$B$4:$B$23,0),1) -> KH012 | H95: =_xlfn.XLOOKUP(O95,产品信息表!$A$4:$A$15,产品信息表!$C$4:$C$15) -> 电子数码 | I95: =DATE(MID(A95,4,4),MID(A95,8,2),MID(A95,10,2)) -> 46148 | J95: =RIGHT(A95,4) -> 0091 | K95: =VLOOKUP(D95,客户信息表!$A$3:$H$23,5,0) -> B | L95: 陈静 | M95: 华中 | N95: =SUBSTITUTE(TRIM(M95),"区","") -> 华中 | O95: CP005 | P95: 台式电脑 PowerDesk 500 | Q95: 4299 | R95: 6 | S95: =IF(ISBLANK(R95),U95/Q95,VALUE(R95)) -> 6 | T95: =VLOOKUP(S95,折扣阶梯!$A$3:$C$7,2,TRUE) -> 1 | U95: 25794 | V95: =IF(Q95*S95=VALUE(SUBSTITUTE(U95,"¥","")),VALUE(SUBSTITUTE(U95,"¥","")),Q95*S95) -> 25794 | W95: 已完成 | X95: =V95*T95 -> 25794 | Y95: =_xlfn.XLOOKUP(O95,产品信息表!$A$4:$A$15,产品信息表!$E$4:$E$15) -> 3500 | Z95: =(X95-Y95*S95)/X95 -> 0.18585718 | AA95: =_xlfn.RANK.EQ(V95,V95:V296,0) -> 17
A96: DD-20260506-0092 | B96: 2026/5/6 | C96: =TEXT(SUBSTITUTE(B96,".","/"),"yyyy-mm-dd") -> 2026-05-06 | D96: KH010 | E96: =VLOOKUP(D96,客户信息表!A$3:H$23,2,0) -> 苏州创智科技 | F96: 苏州创智科技 | G96: =INDEX(客户信息表!$A$4:$H$23,MATCH(F96,客户信息表!$B$4:$B$23,0),1) -> KH010 | H96: =_xlfn.XLOOKUP(O96,产品信息表!$A$4:$A$15,产品信息表!$C$4:$C$15) -> 办公设备 | I96: =DATE(MID(A96,4,4),MID(A96,8,2),MID(A96,10,2)) -> 46148 | J96: =RIGHT(A96,4) -> 0092 | K96: =VLOOKUP(D96,客户信息表!$A$3:$H$23,5,0) -> A | L96: 陈静 | M96: 华东 | N96: =SUBSTITUTE(TRIM(M96),"区","") -> 华东 | O96: CP001 | P96: 激光打印机 ProLaser 200 | Q96: 2499 | R96: 6 | S96: =IF(ISBLANK(R96),U96/Q96,VALUE(R96)) -> 6 | T96: =VLOOKUP(S96,折扣阶梯!$A$3:$C$7,2,TRUE) -> 1 | U96: 14994 | V96: =IF(Q96*S96=VALUE(SUBSTITUTE(U96,"¥","")),VALUE(SUBSTITUTE(U96,"¥","")),Q96*S96) -> 14994 | W96: 待付款 | X96: =V96*T96 -> 14994 | Y96: =_xlfn.XLOOKUP(O96,产品信息表!$A$4:$A$15,产品信息表!$E$4:$E$15) -> 1850 | Z96: =(X96-Y96*S96)/X96 -> 0.25970388 | AA96: =_xlfn.RANK.EQ(V96,V96:V297,0) -> 38
A97: DD-20260506-0093 | B97: 46148 | C97: =TEXT(SUBSTITUTE(B97,".","/"),"yyyy-mm-dd") -> 2026-05-06 | D97: KH009 | E97: =VLOOKUP(D97,客户信息表!A$3:H$23,2,0) -> 天津海河传媒 | F97: 天津海河传媒 | G97: =INDEX(客户信息表!$A$4:$H$23,MATCH(F97,客户信息表!$B$4:$B$23,0),1) -> KH009 | H97: =_xlfn.XLOOKUP(O97,产品信息表!$A$4:$A$15,产品信息表!$C$4:$C$15) -> 电子数码 | I97: =DATE(MID(A97,4,4),MID(A97,8,2),MID(A97,10,2)) -> 46148 | J97: =RIGHT(A97,4) -> 0093 | K97: =VLOOKUP(D97,客户信息表!$A$3:$H$23,5,0) -> C | L97: 赵磊 | M97: 华北 | N97: =SUBSTITUTE(TRIM(M97),"区","") -> 华北 | O97: CP006 | P97: 显示器 ViewMax 27 | Q97: 1299 | R97: 9 | S97: =IF(ISBLANK(R97),U97/Q97,VALUE(R97)) -> 9 | T97: =VLOOKUP(S97,折扣阶梯!$A$3:$C$7,2,TRUE) -> 1 | U97: 11691 | V97: =IF(Q97*S97=VALUE(SUBSTITUTE(U97,"¥","")),VALUE(SUBSTITUTE(U97,"¥","")),Q97*S97) -> 11691 | W97: 已完成 | X97: =V97*T97 -> 11691 | Y97: =_xlfn.XLOOKUP(O97,产品信息表!$A$4:$A$15,产品信息表!$E$4:$E$15) -> 950 | Z97: =(X97-Y97*S97)/X97 -> 0.26866821 | AA97: =_xlfn.RANK.EQ(V97,V97:V298,0) -> 49
A98: DD-20260508-0094 | B98: 46150 | C98: =TEXT(SUBSTITUTE(B98,".","/"),"yyyy-mm-dd") -> 2026-05-08 | D98: KH011 | E98: =VLOOKUP(D98,客户信息表!A$3:H$23,2,0) -> 重庆山城办公设备 | F98: 重庆山城办公设备 | G98: =INDEX(客户信息表!$A$4:$H$23,MATCH(F98,客户信息表!$B$4:$B$23,0),1) -> KH011 | H98: =_xlfn.XLOOKUP(O98,产品信息表!$A$4:$A$15,产品信息表!$C$4:$C$15) -> 软件服务 | I98: =DATE(MID(A98,4,4),MID(A98,8,2),MID(A98,10,2)) -> 46150 | J98: =RIGHT(A98,4) -> 0094 | K98: =VLOOKUP(D98,客户信息表!$A$3:$H$23,5,0) -> B | L98: 陈静 | M98: 西南区 | N98: =SUBSTITUTE(TRIM(M98),"区","") -> 西南 | O98: CP011 | P98: 办公软件年费授权 | Q98: 699 | R98: 6 | S98: =IF(ISBLANK(R98),U98/Q98,VALUE(R98)) -> 6 | T98: =VLOOKUP(S98,折扣阶梯!$A$3:$C$7,2,TRUE) -> 1 | U98: ¥4,194.00 | V98: =IF(Q98*S98=VALUE(SUBSTITUTE(U98,"¥","")),VALUE(SUBSTITUTE(U98,"¥","")),Q98*S98) -> 4194 | W98: 已取消 | X98: =V98*T98 -> 4194 | Y98: =_xlfn.XLOOKUP(O98,产品信息表!$A$4:$A$15,产品信息表!$E$4:$E$15) -> 300 | Z98: =(X98-Y98*S98)/X98 -> 0.57081545 | AA98: =_xlfn.RANK.EQ(V98,V98:V299,0) -> 81
A99: DD-20260508-0095 | B99: 46150 | C99: =TEXT(SUBSTITUTE(B99,".","/"),"yyyy-mm-dd") -> 2026-05-08 | D99: KH012 | E99: =VLOOKUP(D99,客户信息表!A$3:H$23,2,0) -> 长沙麓山科技 | F99: 武汉长江实业 | G99: =INDEX(客户信息表!$A$4:$H$23,MATCH(F99,客户信息表!$B$4:$B$23,0),1) -> KH007 | H99: =_xlfn.XLOOKUP(O99,产品信息表!$A$4:$A$15,产品信息表!$C$4:$C$15) -> 软件服务 | I99: =DATE(MID(A99,4,4),MID(A99,8,2),MID(A99,10,2)) -> 46150 | J99: =RIGHT(A99,4) -> 0095 | K99: =VLOOKUP(D99,客户信息表!$A$3:$H$23,5,0) -> B | L99: 杨帆 | M99: 华中 | N99: =SUBSTITUTE(TRIM(M99),"区","") -> 华中 | O99: CP011 | P99: 办公软件年费授权 | Q99: 699 | R99: 35 | S99: =IF(ISBLANK(R99),U99/Q99,VALUE(R99)) -> 35 | T99: =VLOOKUP(S99,折扣阶梯!$A$3:$C$7,2,TRUE) -> 0.95 | U99: 24465 | V99: =IF(Q99*S99=VALUE(SUBSTITUTE(U99,"¥","")),VALUE(SUBSTITUTE(U99,"¥","")),Q99*S99) -> 24465 | W99: 已完成 | X99: =V99*T99 -> 23241.75 | Y99: =_xlfn.XLOOKUP(O99,产品信息表!$A$4:$A$15,产品信息表!$E$4:$E$15) -> 300 | Z99: =(X99-Y99*S99)/X99 -> 0.54822679 | AA99: =_xlfn.RANK.EQ(V99,V99:V300,0) -> 18
A100: DD-20260508-0096 | B100: 2026年5月8日 | C100: =TEXT(SUBSTITUTE(B100,".","/"),"yyyy-mm-dd") -> 2026-05-08 | D100: KH013 | E100: =VLOOKUP(D100,客户信息表!A$3:H$23,2,0) -> 石家庄振华商贸 | F100: 石家庄振华商贸 | G100: =INDEX(客户信息表!$A$4:$H$23,MATCH(F100,客户信息表!$B$4:$B$23,0),1) -> KH013 | H100: =_xlfn.XLOOKUP(O100,产品信息表!$A$4:$A$15,产品信息表!$C$4:$C$15) -> 电子数码 | I100: =DATE(MID(A100,4,4),MID(A100,8,2),MID(A100,10,2)) -> 46150 | J100: =RIGHT(A100,4) -> 0096 | K100: =VLOOKUP(D100,客户信息表!$A$3:$H$23,5,0) -> C | L100: 王强 | M100: 华北 | N100: =SUBSTITUTE(TRIM(M100),"区","") -> 华北 | O100: CP006 | P100: 显示器 ViewMax 27 | Q100: 1299 | R100: 2 | S100: =IF(ISBLANK(R100),U100/Q100,VALUE(R100)) -> 2 | T100: =VLOOKUP(S100,折扣阶梯!$A$3:$C$7,2,TRUE) -> 1 | U100: 2598 | V100: =IF(Q100*S100=VALUE(SUBSTITUTE(U100,"¥","")),VALUE(SUBSTITUTE(U100,"¥","")),Q100*S100) -> 2598 | W100: 已发货 | X100: =V100*T100 -> 2598 | Y100: =_xlfn.XLOOKUP(O100,产品信息表!$A$4:$A$15,产品信息表!$E$4:$E$15) -> 950 | Z100: =(X100-Y100*S100)/X100 -> 0.26866821 | AA100: =_xlfn.RANK.EQ(V100,V100:V301,0) -> 93
...

Sheet 客户信息表
A1: 客户主数据（20家）
A2: 客户等级：A=重点客户 B=普通客户 C=小额客户。查找练习的标准数据源。
A3: 客户ID | B3: 客户名称 | C3: 所属区域 | D3: 所属行业 | E3: 客户等级 | F3: 信用额度(万元) | G3: 账期(天) | H3: 合作起始日期
A4: KH001 | B4: 北京华信科技 | C4: 华北 | D4: 互联网 | E4: A | F4: 55 | G4: 30 | H4: 43536
A5: KH002 | B5: 上海锦程贸易 | C5: 华东 | D5: 零售 | E5: B | F5: 32 | G5: 45 | H5: 43983
A6: KH003 | B6: 广州启航教育 | C6: 华南 | D6: 教育 | E6: A | F6: 60 | G6: 30 | H6: 43363
A7: KH004 | B7: 深圳蓝鲸网络 | C7: 华南 | D7: 互联网 | E7: B | F7: 40 | G7: 30 | H7: 44211
A8: KH005 | B8: 杭州云图信息 | C8: 华东 | D8: 互联网 | E8: A | F8: 50 | G8: 60 | H8: 44143
A9: KH006 | B9: 成都天府商贸 | C9: 西南 | D9: 零售 | E9: C | F9: 20 | G9: 45 | H9: 44625
A10: KH007 | B10: 武汉长江实业 | C10: 华中 | D10: 制造业 | E10: B | F10: 35 | G10: 60 | H10: 43668
A11: KH008 | B11: 南京紫金山软件园运营 | C11: 华东 | D11: 互联网 | E11: C | F11: 25 | G11: 30 | H11: 44438
A12: KH009 | B12: 天津海河传媒 | C12: 华北 | D12: 文化传媒 | E12: C | F12: 15 | G12: 45 | H12: 44698
A13: KH010 | B13: 苏州创智科技 | C13: 华东 | D13: 制造业 | E13: A | F13: 55 | G13: 30 | H13: 43887
A14: KH011 | B14: 重庆山城办公设备 | C14: 西南 | D14: 零售 | E14: B | F14: 28 | G14: 45 | H14: 44480
A15: KH012 | B15: 长沙麓山科技 | C15: 华中 | D15: 互联网 | E15: B | F15: 32 | G15: 30 | H15: 44168
... A23: KH020 | B23: 合肥科大国创 | C23: 华东 | D23: 教育 | E23: C | F23: 22 | G23: 45 | H23: 44571

Sheet 产品信息表
A1: 产品主数据（12个）
A2: 毛利计算数据源：毛利 = 标准单价 × 数量 − 单位成本 × 数量（结合折扣另算，见题目）。
A3: 产品编码 | B3: 产品名称 | C3: 类别 | D3: 标准单价(元) | E3: 单位成本(元) | F3: 供应商
A4: CP001 | B4: 激光打印机 ProLaser 200 | C4: 办公设备 | D4: 2499 | E4: 1850 | F4: 惠普商用分销
A5: CP002 | B5: 多功能一体机 PrintMaster 300 | C5: 办公设备 | D5: 3599 | E5: 2700 | F5: 佳能(中国)
A6: CP003 | B6: 碎纸机 SafeCut S8 | C6: 办公设备 | D6: 899 | E6: 620 | F6: 得力集团
A7: CP004 | B7: 笔记本电脑 TechBook 14 | C7: 电子数码 | D7: 5699 | E7: 4800 | F7: 联想授权经销商
A8: CP005 | B8: 台式电脑 PowerDesk 500 | C8: 电子数码 | D8: 4299 | E8: 3500 | F8: 联想授权经销商
A9: CP006 | B9: 显示器 ViewMax 27 | C9: 电子数码 | D9: 1299 | E9: 950 | F9: 戴尔金牌店
A10: CP007 | B10: 无线键鼠套装 KeyFree 2.0 | C10: 电子数码 | D10: 299 | E10: 190 | F10: 罗技分销
A11: CP008 | B11: A4复印纸（5包/箱） | C11: 办公耗材 | D11: 128 | E11: 95 | F11: 得力集团
A12: CP009 | B12: 激光硒鼓 TonerMax 12A | C12: 办公耗材 | D12: 385 | E12: 260 | F12: 格之格
A13: CP010 | B13: 签字笔盒装（12支） | C13: 办公耗材 | D13: 45 | E13: 28 | F13: 晨光文具
A14: CP011 | B14: 办公软件年费授权 | C14: 软件服务 | D14: 699 | E14: 300 | F14: 金山软件
A15: CP012 | B15: 云存储服务（1TB/年） | C15: 软件服务 | D15: 599 | E15: 250 | F15: 阿里云渠道

Sheet 折扣阶梯
A1: 数量折扣阶梯表
A2: VLOOKUP 近似匹配（第4参数TRUE）练习用。注意：首列必须升序排列才能正确匹配。
A3: 数量下限(件) | B3: 折扣率 | C3: 说明
A4: 1 | B4: 1 | C4: 1~9件 按原价
A5: 10 | B5: 0.95 | C5: 10~49件 95折
A6: 50 | B6: 0.9 | C6: 50~99件 9折
A7: 100 | B7: 0.85 | C7: 100件及以上 85折

Sheet 详细信息1
A1: 求和项:金额(修正后) - 区域(修正后): 华北, 月(日期): Jan 的详细信息
A3: 订单编号 | B3: 下单日期 | C3: 下单日期(修正后) | D3: 客户ID | E3: 客户名称(修正后) | F3: 客户名称 | G3: 客户ID(修正后) | H3: 字段8 | I3: 日期 | J3: 流水号 | K3: 用户登记（修正后） | L3: 销售员 | M3: 区域 | N3: 区域(修正后) | O3: 产品编码 | P3: 产品名称 | Q3: 单价(元) | R3: 数量 | S3: 修正后 | T3: 折扣(修正后) | U3: 金额(元) | V3: 金额(修正后) | W3: 订单状态 | X3: 应收金额
A4: DD-20260126-0015 | B4: 46048 | C4: 2026-01-26 | D4: KH019 | E4: 北京中关新材 | F4: 北京中关新材 | G4: KH019 | H4: KH019 | I4: 46048 | J4: 0015 | K4: B | L4: 孙悦 | M4: 华北 | N4: 华北 | O4: CP001 | P4: 激光打印机 ProLaser 200 | Q4: 2499 | S4: 4 | T4: 1 | U4: 9996 | V4: 9996 | W4: 已发货 | X4: 9996
A5: DD-20260125-0014 | B5: 46047 | C5: 2026-01-25 | D5: KH001 | E5: 北京华信科技 | F5: 北京华信科技 | G5: KH001 | H5: KH001 | I5: 46047 | J5: 0014 | K5: A | L5: 张伟 | M5: 华北 | N5: 华北 | O5: CP009 | P5: 激光硒鼓 TonerMax 12A | Q5: 385 | R5: 32 | S5: 32 | T5: 0.95 | U5: 12320 | V5: 12320 | W5: 已发货 | X5: 11704
A6: DD-20260120-0010 | B6: 46042 | C6: 2026-01-20 | D6: KH019 | E6: 北京中关新材 | F6: 北京中关新材 | G6: KH019 | H6: KH019 | I6: 46042 | J6: 0010 | K6: B | L6: 孙悦 | M6: 华北 | N6: 华北 | O6: CP012 | P6: 云存储服务（1TB/年） | Q6: 599 | R6: 3 | S6: 3 | T6: 1 | U6: 1797 | V6: 1797 | W6: 已完成 | X6: 1797
A7: DD-20260109-0007 | B7: 46031 | C7: 2026-01-09 | D7: KH019 | E7: 北京中关新材 | F7: 北京中关新材 | G7: KH019 | H7: KH019 | I7: 46031 | J7: 0007 | K7: B | L7: 陈静 | M7: 华北 | N7: 华北 | O7: CP010 | P7: 签字笔盒装（12支） | Q7: 45 | R7: 85 | S7: 85 | T7: 0.9 | U7: 3825 | V7: 3825 | W7: 已完成 | X7: 3442.5

Sheet 销售目标
A1: 2026年1-8月 各区域销售目标（元）
A2: 完成率练习：实际 = 清洗后订单表按区域汇总金额；是否剔除「已取消」订单由自己定口径并说明。
A3: 区域 | B3: 2026-01 | C3: 2026-02 | D3: 2026-03 | E3: 2026-04 | F3: 2026-05 | G3: 2026-06 | H3: 2026-07 | I3: 2026-08 | J3: 合计
A4: 华东 | B4: 23000 | C4: 129000 | D4: 108000 | E4: 104000 | F4: 292000 | G4: 110000 | H4: 162000 | I4: 82000 | J4: =SUM(B4:I4) -> 1010000
A5: 华北 | B5: 29000 | C5: 30000 | D5: 77000 | E5: 23000 | F5: 143000 | G5: 122000 | H5: 116000 | I5: 43000 | J5: =SUM(B5:I5) -> 583000
A6: 华南 | B6: 8000 | C6: 8000 | D6: 17000 | E6: 114000 | F6: 127000 | G6: 49000 | H6: 43000 | I6: 46000 | J6: =SUM(B6:I6) -> 412000
A7: 西南 | B7: 39000 | C7: 25000 | D7: 46000 | E7: 57000 | F7: 24000 | G7: 46000 | H7: 79000 | I7: 60000 | J7: =SUM(B7:I7) -> 376000
A8: 华中 | B8: 50000 | C8: 43000 | D8: 51000 | E8: 27000 | F8: 94000 | G8: 58000 | H8: 26000 | I8: 84000 | J8: =SUM(B8:I8) -> 433000
A9: 总计 | B9: =SUM(B4:B8) -> 149000 | C9: =SUM(C4:C8) -> 235000 | D9: =SUM(D4:D8) -> 299000 | E9: =SUM(E4:E8) -> 325000 | F9: =SUM(F4:F8) -> 680000 | G9: =SUM(G4:G8) -> 385000 | H9: =SUM(H4:H8) -> 426000 | I9: =SUM(I4:I8) -> 315000 | J9: =SUM(J4:J8) -> 2814000
A16: 求和项:金额(修正后) | B16: 列标签
A17: 行标签 | B17: 1月 | C17: 2月 | D17: 3月 | E17: 4月 | F17: 5月 | G17: 6月 | H17: 7月 | I17: 8月 | J17: 总计
A18: 华北 | B18: 27938 | C18: 28495 | D18: 72200 | E18: 21881 | F18: 102625 | G18: 114784 | H18: 109154 | I18: 40329 | J18: 517406
A19: 华东 | B19: 22857 | C19: 81902 | D19: 132603 | E19: 140398 | F19: 246587 | G19: 99600 | H19: 169804 | I19: 88661 | J19: 982412
A20: 华南 | B20: 899 | D20: 7493 | E20: 118532 | F20: 132452 | G20: 51222 | H20: 44867 | I20: 47679 | J20: 403144
A21: 华中 | B21: 45734 | D21: 47099 | E21: 25193 | F21: 82255 | G21: 46471 | H21: 23569 | I21: 77390 | J21: 347711
A22: 西南 | B22: 44649 | C22: 27982 | D22: 51828 | E22: 82246 | F22: 23121 | G22: 51800 | H22: 89874 | I22: 67642 | J22: 439142
A23: 总计 | B23: 142077 | C23: 138379 | D23: 311223 | E23: 388250 | F23: 587040 | G23: 363877 | H23: 437268 | I23: 321701 | J23: 2689815
A26: 华北 | B26: =VLOOKUP($A26,$A$17:$J$23,COLUMN(B3),0)/VLOOKUP($A26,$A$3:$J$9,COLUMN(B3),0) -> 0.96337931 | C26: =VLOOKUP($A26,$A$17:$J$23,COLUMN(C3),0)/VLOOKUP($A26,$A$3:$J$9,COLUMN(C3),0) -> 0.94983333 | D26: =VLOOKUP($A26,$A$17:$J$23,COLUMN(D3),0)/VLOOKUP($A26,$A$3:$J$9,COLUMN(D3),0) -> 0.93766234 | E26: =VLOOKUP($A26,$A$17:$J$23,COLUMN(E3),0)/VLOOKUP($A26,$A$3:$J$9,COLUMN(E3),0) -> 0.95134783 | F26: =VLOOKUP($A26,$A$17:$J$23,COLUMN(F3),0)/VLOOKUP($A26,$A$3:$J$9,COLUMN(F3),0) -> 0.71765734 | G26: =VLOOKUP($A26,$A$17:$J$23,COLUMN(G3),0)/VLOOKUP($A26,$A$3:$J$9,COLUMN(G3),0) -> 0.94085246 | H26: =VLOOKUP($A26,$A$17:$J$23,COLUMN(H3),0)/VLOOKUP($A26,$A$3:$J$9,COLUMN(H3),0) -> 0.94098276 | I26: =VLOOKUP($A26,$A$17:$J$23,COLUMN(I3),0)/VLOOKUP($A26,$A$3:$J$9,COLUMN(I3),0) -> 0.93788372 | J26: =VLOOKUP($A26,$A$17:$J$23,COLUMN(J3),0)/VLOOKUP($A26,$A$3:$J$9,COLUMN(J3),0) -> 0.88748885
A27: 华东 | B27: =VLOOKUP($A27,$A$17:$J$23,COLUMN(B4),0)/VLOOKUP($A27,$A$3:$J$9,COLUMN(B4),0) -> 0.99378261 | C27: =VLOOKUP($A27,$A$17:$J$23,COLUMN(C4),0)/VLOOKUP($A27,$A$3:$J$9,COLUMN(C4),0) -> 0.63489922 | D27: =VLOOKUP($A27,$A$17:$J$23,COLUMN(D4),0)/VLOOKUP($A27,$A$3:$J$9,COLUMN(D4),0) -> 1.2278056 | E27: =VLOOKUP($A27,$A$17:$J$23,COLUMN(E4),0)/VLOOKUP($A27,$A$3:$J$9,COLUMN(E4),0) -> 1.3499808 | F27: =VLOOKUP($A27,$A$17:$J$23,COLUMN(F4),0)/VLOOKUP($A27,$A$3:$J$9,COLUMN(F4),0) -> 0.84447603 | G27: =VLOOKUP($A27,$A$17:$J$23,COLUMN(G4),0)/VLOOKUP($A27,$A$3:$J$9,COLUMN(G4),0) -> 0.90545455 | H27: =VLOOKUP($A27,$A$17:$J$23,COLUMN(H4),0)/VLOOKUP($A27,$A$3:$J$9,COLUMN(H4),0) -> 1.0481728 | I27: =VLOOKUP($A27,$A$17:$J$23,COLUMN(I4),0)/VLOOKUP($A27,$A$3:$J$9,COLUMN(I4),0) -> 1.0812317 | J27: =VLOOKUP($A27,$A$17:$J$23,COLUMN(J4),0)/VLOOKUP($A27,$A$3:$J$9,COLUMN(J4),0) -> 0.97268515
A28: 华南 | B28: =VLOOKUP($A28,$A$17:$J$23,COLUMN(B5),0)/VLOOKUP($A28,$A$3:$J$9,COLUMN(B5),0) -> 0.112375 | C28: =VLOOKUP($A28,$A$17:$J$23,COLUMN(C5),0)/VLOOKUP($A28,$A$3:$J$9,COLUMN(C5),0) -> 0 | D28: =VLOOKUP($A28,$A$17:$J$23,COLUMN(D5),0)/VLOOKUP($A28,$A$3:$J$9,COLUMN(D5),0) -> 0.44076471 | E28: =VLOOKUP($A28,$A$17:$J$23,COLUMN(E5),0)/VLOOKUP($A28,$A$3:$J$9,COLUMN(E5),0) -> 1.0397544 | F28: =VLOOKUP($A28,$A$17:$J$23,COLUMN(F5),0)/VLOOKUP($A28,$A$3:$J$9,COLUMN(F5),0) -> 1.0429291 | G28: =VLOOKUP($A28,$A$17:$J$23,COLUMN(G5),0)/VLOOKUP($A28,$A$3:$J$9,COLUMN(G5),0) -> 1.0453469 | H28: =VLOOKUP($A28,$A$17:$J$23,COLUMN(H5),0)/VLOOKUP($A28,$A$3:$J$9,COLUMN(H5),0) -> 1.0434186 | I28: =VLOOKUP($A28,$A$17:$J$23,COLUMN(I5),0)/VLOOKUP($A28,$A$3:$J$9,COLUMN(I5),0) -> 1.0365 | J28: =VLOOKUP($A28,$A$17:$J$23,COLUMN(J5),0)/VLOOKUP($A28,$A$3:$J$9,COLUMN(J5),0) -> 0.97850485
A29: 华中 | B29: =VLOOKUP($A29,$A$17:$J$23,COLUMN(B6),0)/VLOOKUP($A29,$A$3:$J$9,COLUMN(B6),0) -> 0.91468 | C29: =VLOOKUP($A29,$A$17:$J$23,COLUMN(C6),0)/VLOOKUP($A29,$A$3:$J$9,COLUMN(C6),0) -> 0 | D29: =VLOOKUP($A29,$A$17:$J$23,COLUMN(D6),0)/VLOOKUP($A29,$A$3:$J$9,COLUMN(D6),0) -> 0.9235098 | E29: =VLOOKUP($A29,$A$17:$J$23,COLUMN(E6),0)/VLOOKUP($A29,$A$3:$J$9,COLUMN(E6),0) -> 0.93307407 | F29: =VLOOKUP($A29,$A$17:$J$23,COLUMN(F6),0)/VLOOKUP($A29,$A$3:$J$9,COLUMN(F6),0) -> 0.87505319 | G29: =VLOOKUP($A29,$A$17:$J$23,COLUMN(G6),0)/VLOOKUP($A29,$A$3:$J$9,COLUMN(G6),0) -> 0.80122414 | H29: =VLOOKUP($A29,$A$17:$J$23,COLUMN(H6),0)/VLOOKUP($A29,$A$3:$J$9,COLUMN(H6),0) -> 0.9065 | I29: =VLOOKUP($A29,$A$17:$J$23,COLUMN(I6),0)/VLOOKUP($A29,$A$3:$J$9,COLUMN(I6),0) -> 0.92130952 | J29: =VLOOKUP($A29,$A$17:$J$23,COLUMN(J6),0)/VLOOKUP($A29,$A$3:$J$9,COLUMN(J6),0) -> 0.80302771
A30: 西南 | B30: =VLOOKUP($A30,$A$17:$J$23,COLUMN(B7),0)/VLOOKUP($A30,$A$3:$J$9,COLUMN(B7),0) -> 1.1448462 | C30: =VLOOKUP($A30,$A$17:$J$23,COLUMN(C7),0)/VLOOKUP($A30,$A$3:$J$9,COLUMN(C7),0) -> 1.11928 | D30: =VLOOKUP($A30,$A$17:$J$23,COLUMN(D7),0)/VLOOKUP($A30,$A$3:$J$9,COLUMN(D7),0) -> 1.1266957 | E30: =VLOOKUP($A30,$A$17:$J$23,COLUMN(E7),0)/VLOOKUP($A30,$A$3:$J$9,COLUMN(E7),0) -> 1.4429123 | F30: =VLOOKUP($A30,$A$17:$J$23,COLUMN(F7),0)/VLOOKUP($A30,$A$3:$J$9,COLUMN(F7),0) -> 0.963375 | G30: =VLOOKUP($A30,$A$17:$J$23,COLUMN(G7),0)/VLOOKUP($A30,$A$3:$J$9,COLUMN(G7),0) -> 1.126087 | H30: =VLOOKUP($A30,$A$17:$J$23,COLUMN(H7),0)/VLOOKUP($A30,$A$3:$J$9,COLUMN(H7),0) -> 1.1376456 | I30: =VLOOKUP($A30,$A$17:$J$23,COLUMN(I7),0)/VLOOKUP($A30,$A$3:$J$9,COLUMN(I7),0) -> 1.1273667 | J30: =VLOOKUP($A30,$A$17:$J$23,COLUMN(J7),0)/VLOOKUP($A30,$A$3:$J$9,COLUMN(J7),0) -> 1.1679309
A31: 总计 | B31: =VLOOKUP($A31,$A$17:$J$23,COLUMN(B8),0)/VLOOKUP($A31,$A$3:$J$9,COLUMN(B8),0) -> 0.95353691 | C31: =VLOOKUP($A31,$A$17:$J$23,COLUMN(C8),0)/VLOOKUP($A31,$A$3:$J$9,COLUMN(C8),0) -> 0.58884681 | D31: =VLOOKUP($A31,$A$17:$J$23,COLUMN(D8),0)/VLOOKUP($A31,$A$3:$J$9,COLUMN(D8),0) -> 1.0408796 | E31: =VLOOKUP($A31,$A$17:$J$23,COLUMN(E8),0)/VLOOKUP($A31,$A$3:$J$9,COLUMN(E8),0) -> 1.1946154 | F31: =VLOOKUP($A31,$A$17:$J$23,COLUMN(F8),0)/VLOOKUP($A31,$A$3:$J$9,COLUMN(F8),0) -> 0.86329412 | G31: =VLOOKUP($A31,$A$17:$J$23,COLUMN(G8),0)/VLOOKUP($A31,$A$3:$J$9,COLUMN(G8),0) -> 0.94513506 | H31: =VLOOKUP($A31,$A$17:$J$23,COLUMN(H8),0)/VLOOKUP($A31,$A$3:$J$9,COLUMN(H8),0) -> 1.0264507 | I31: =VLOOKUP($A31,$A$17:$J$23,COLUMN(I8),0)/VLOOKUP($A31,$A$3:$J$9,COLUMN(I8),0) -> 1.021273 | J31: =VLOOKUP($A31,$A$17:$J$23,COLUMN(J8),0)/VLOOKUP($A31,$A$3:$J$9,COLUMN(J8),0) -> 0.95586887
B35: 实际金额 | C35: 目标金额 | D35: 日期
A36: 华北 | B36: =VLOOKUP($A36,$A$17:$J$22,2,0) -> 27938 | C36: =VLOOKUP($A36,$A$4:$J$8,2,0) -> 29000 | D36: 46023
A37: 华东 | B37: =VLOOKUP($A37,$A$17:$J$22,2,0) -> 22857 | C37: =VLOOKUP($A37,$A$4:$J$8,2,0) -> 23000 | D37: 46054
A38: 华南 | B38: =VLOOKUP($A38,$A$17:$J$22,2,0) -> 899 | C38: =VLOOKUP($A38,$A$4:$J$8,2,0) -> 8000 | D38: 46082
A39: 华中 | B39: =VLOOKUP($A39,$A$17:$J$22,2,0) -> 45734 | C39: =VLOOKUP($A39,$A$4:$J$8,2,0) -> 50000 | D39: 46113
A40: 西南 | B40: =VLOOKUP($A40,$A$17:$J$22,2,0) -> 44649 | C40: =VLOOKUP($A40,$A$4:$J$8,2,0) -> 39000 | D40: 46143
